Workbook

Sheet Certificate
A1: COMPLIANCE CERTIFICATE
A3: To: Lakeshore Merchants Bank, N.A., as Administrative Agent
A4: Re: Credit Agreement dated as of November 14, 2024, as amended by Amendment No. 1 dated as of February 26, 2026 (the Credit Agreement), among Brennecke Precision Components, Inc., as Borrower, the Lenders party thereto, and Lakeshore Merchants Bank, N.A., as Administrative Agent
A5: Fiscal Quarter ended August 31, 2026
A7: The undersigned Responsible Officer of the Borrower certifies to the Administrative Agent and the Lenders that:
A8: 1. The undersigned has reviewed the terms of the Credit Agreement and has made, or has caused to be made under the undersigned's supervision, a review of the transactions and financial condition of the Borrower and its Subsidiaries during the Fiscal Quarter ended August 31, 2026.
A9: 2. Except as set forth on Schedule 1, no Default has occurred and is continuing.
A10: 3. Schedule 2 sets forth calculations demonstrating compliance with Sections 6.11 and 6.12 of the Credit Agreement as of August 31, 2026, and reports Capital Expenditures under Section 6.13 for the Fiscal Year to date.
A12: BRENNECKE PRECISION COMPONENTS, INC.
A13: By: ______________________________
A14: Name: Wade Kirchner
A15: Title: Chief Financial Officer
... A19: An Event of Default under Section 7.01(d) of the Credit Agreement exists by reason of the Borrower's failure to comply with Section 6.12 as of August 31, 2026, as follows.
A20: Fixed Charge Coverage Ratio, Test Period ended August 31, 2026 (Section 6.12) | B20: ='Fixed Charges'!$B$33 -> 1.16
A21: Minimum required under Section 6.12 | B21: =Parameters!$B$5 -> 1.2
A22: Cure Amount required under Section 6.14 (shortfall in the numerator) | B22: ='Fixed Charges'!$B$37 -> 117515.74
A23: Action proposed: exercise of the equity cure right under Section 6.14 in the Cure Amount shown above, by cash common equity contributed within ten Business Days after October 15, 2026, or such other action as is agreed with the Administrative Agent within that period.
A25: SCHEDULE 2 - FINANCIAL COVENANT CALCULATIONS
A26: Section 6.11 Total Leverage Ratio
A27: Consolidated Funded Debt as of August 31, 2026 | B27: ='Funded Debt'!$B$13 -> 14167103
A28: Consolidated EBITDA, Test Period ended August 31, 2026 | B28: =EBITDA!$B$20 -> 5414830
A29: of which Acquired EBITDA, Ostrander Machine LLC, clause (f), shown separately | B29: ='Ostrander PF'!$H$30 -> 434009.02
A30: Total Leverage Ratio | B30: =ROUND(B27/B28,2) -> 2.62
A31: Maximum permitted, Section 6.11, Fiscal Quarter ending August 31, 2026 | B31: =Parameters!$B$4 -> 2.75
A32: Section 6.11 status | B32: =IF(B30<=B31,"In compliance","Not in compliance") -> In compliance
A34: Section 6.12 Fixed Charge Coverage Ratio
A35: Consolidated EBITDA, Test Period ended August 31, 2026 | B35: =EBITDA!$B$20 -> 5414830
A36: Less Unfinanced Capital Expenditures | B36: ='Capex and Taxes'!$D$22 -> 1188565.8
A37: Less Cash Taxes | B37: ='Capex and Taxes'!$C$35 -> 583845
A38: Less Restricted Payments | B38: =SUMIFS('GL TTM'!$P$5:$P$43,'GL TTM'!$C$5:$C$43,"Restricted payment") -> 437500
A39: Numerator | B39: ='Fixed Charges'!$B$31 -> 3204919.2
A40: Fixed Charges | B40: ='Fixed Charges'!$B$24 -> 2768695.8
A41: Fixed Charge Coverage Ratio | B41: ='Fixed Charges'!$B$33 -> 1.16
A42: Minimum required, Section 6.12 | B42: =Parameters!$B$5 -> 1.2
A43: Section 6.12 status | B43: ='Fixed Charges'!$B$35 -> Not in compliance
A45: Section 6.13 Capital Expenditures (reported; tested as of the last day of the Fiscal Year)
A46: Capital Expenditures, December 1, 2025 through August 31, 2026 | B46: ='Capex and Taxes'!$D$23 -> 1420452.8
A47: Limit for the Fiscal Year ending November 30, 2026, Section 6.13 | B47: =Parameters!$B$8 -> 2400000

Sheet GL TTM
A1: General ledger activity by account, September 2025 through August 2026
A2: Source: gl_activity_sep25_aug26.csv as exported (debits positive, credits negative). TTM ACTIVITY sums the twelve months; INCOME EFFECT reverses the sign so income is positive.
A4: ACCOUNT | B4: DESCRIPTION | C4: COVENANT LINE | D4: Sep-25 | E4: Oct-25 | F4: Nov-25 | G4: Dec-25 | H4: Jan-26 | I4: Feb-26 | J4: Mar-26 | K4: Apr-26 | L4: May-26 | M4: Jun-26 | N4: Jul-26 | O4: Aug-26 | P4: TTM ACTIVITY | Q4: INCOME EFFECT
A5: 4000 | B5: Product sales - Fond du Lac plant | C5: Sales | D5: -1523828.2 | E5: -1564895.6 | F5: -1506637.6 | G5: -1337473.2 | H5: -1577088.1 | I5: -1602134.4 | J5: -1620406.8 | K5: -1568265.6 | L5: -1597470.4 | M5: -1620242.2 | N5: -1529284.2 | O5: -1542154.3 | P5: =SUM(D5:O5) -> -18589881 | Q5: =-P5 -> 18589881
A6: 4010 | B6: Product sales - Beaver Dam plant | C6: Sales | D6: -915747.61 | E6: -987076.25 | F6: -909597.69 | G6: -842373.68 | H6: -950522.25 | I6: -985538.62 | J6: -993694.92 | K6: -949533.92 | L6: -1011304.8 | M6: -970991.02 | N6: -925773.43 | O6: -941441.42 | P6: =SUM(D6:O6) -> -11383596 | Q6: =-P6 -> 11383596
A7: 4020 | B7: Product sales - Oshkosh plant | C7: Sales | D7: 0 | E7: 0 | F7: 0 | G7: 0 | H7: 0 | I7: 0 | J7: -264378.76 | K7: -295403.38 | L7: -303747.68 | M7: -282790.44 | N7: -292602.92 | O7: -280734.67 | P7: =SUM(D7:O7) -> -1719657.9 | Q7: =-P7 -> 1719657.9
A8: 4050 | B8: Freight and tooling billed to customers | C8: Sales | D8: -29641.73 | E8: -28755.83 | F8: -28368.21 | G8: -26777.9 | H8: -29606.26 | I8: -29471.5 | J8: -29281.19 | K8: -28555.44 | L8: -27869.53 | M8: -27800.4 | N8: -26830.06 | O8: -30287.77 | P8: =SUM(D8:O8) -> -343245.82 | Q8: =-P8 -> 343245.82
A9: 4090 | B9: Sales returns and allowances | C9: Sales | D9: 15241.14 | E9: 13172.48 | F9: 15355.28 | G9: 15941.53 | H9: 14603.48 | I9: 14479.63 | J9: 11972.63 | K9: 11226.07 | L9: 10809.97 | M9: 11198.04 | N9: 12702.47 | O9: 9814.84 | P9: =SUM(D9:O9) -> 156517.56 | Q9: =-P9 -> -156517.56
A10: 5000 | B10: Materials and outside processing | C10: Cost of sales | D10: 911127.89 | E10: 962528.45 | F10: 896415.31 | G10: 826495.93 | H10: 934991.98 | I10: 980923.69 | J10: 1071554.5 | K10: 1041339.6 | L10: 1085497.8 | M10: 1067295.5 | N10: 1020426.2 | O10: 1023059.2 | P10: =SUM(D10:O10) -> 11821656 | Q10: =-P10 -> -11821656
A11: 5010 | B11: Direct labor | C11: Cost of sales | D11: 363699.97 | E11: 382989.79 | F11: 374578.18 | G11: 324845.53 | H11: 387870.25 | I11: 398105.7 | J11: 438949.42 | K11: 429989.57 | L11: 440014.59 | M11: 440693.92 | N11: 414666.19 | O11: 419392.47 | P11: =SUM(D11:O11) -> 4815795.6 | Q11: =-P11 -> -4815795.6
A12: 5020 | B12: Indirect plant labor and supervision | C12: Cost of sales | D12: 121089.73 | E12: 125242.6 | F12: 119031.31 | G12: 108213.58 | H12: 122398.76 | I12: 128955.75 | J12: 140745.05 | K12: 138280.22 | L12: 142624.46 | M12: 141762.92 | N12: 135986.13 | O12: 137366.58 | P12: =SUM(D12:O12) -> 1561697.1 | Q12: =-P12 -> -1561697.1
A13: 5030 | B13: Perishable tooling and shop supplies | C13: Cost of sales | D13: 73998.24 | E13: 76671.83 | F13: 71642.29 | G13: 70748.95 | H13: 79520.67 | I13: 76645.57 | J13: 88714.4 | K13: 91410.19 | L13: 88341.71 | M13: 93051.64 | N13: 89019.09 | O13: 85510.06 | P13: =SUM(D13:O13) -> 985274.64 | Q13: =-P13 -> -985274.64
A14: 5040 | B14: Plant utilities | C14: Cost of sales | D14: 36417.65 | E14: 40189.73 | F14: 45603.42 | G14: 49152.83 | H14: 53622.5 | I14: 50283.26 | J14: 44580.45 | K14: 40851.65 | L14: 38188.08 | M14: 42148.9 | N14: 42548.65 | O14: 40939.17 | P14: =SUM(D14:O14) -> 524526.29 | Q14: =-P14 -> -524526.29
A15: 5050 | B15: Depreciation - plant machinery and equipment | C15: Depreciation and amortization | D15: 116418.22 | E15: 116418.22 | F15: 116418.22 | G15: 116418.22 | H15: 126263.55 | I15: 126263.55 | J15: 139497.31 | K15: 139497.31 | L15: 139497.31 | M15: 139497.31 | N15: 139497.31 | O15: 139497.31 | P15: =SUM(D15:O15) -> 1555183.8 | Q15: =-P15 -> -1555183.8
A16: 5060 | B16: Freight out | C16: Cost of sales | D16: 27302.89 | E16: 29256.5 | F16: 26198.28 | G16: 23428.03 | H16: 28139.05 | I16: 28295.93 | J16: 32372.41 | K16: 31852.4 | L16: 30218.03 | M16: 31141.25 | N16: 28645.41 | O16: 31135.61 | P16: =SUM(D16:O16) -> 347985.79 | Q16: =-P16 -> -347985.79
... A41: 8010 | B41: Provision for income taxes - state | C41: Income taxes | D41: 15864.9 | E41: 8014.36 | F41: 13120.28 | G41: 0 | H41: 7644.65 | I41: 9548.89 | J41: 17273.11 | K41: 18555.55 | L41: 21826.69 | M41: 0 | N41: 18478.01 | O41: 19418.25 | P41: =SUM(D41:O41) -> 149744.69 | Q41: =-P41 -> -149744.69
A43: 3900 | B43: Dividends paid to shareholders | C43: Restricted payment | D43: 0 | E43: 0 | F43: 0 | G43: 437500 | H43: 0 | I43: 0 | J43: 0 | K43: 0 | L43: 0 | M43: 0 | N43: 0 | O43: 0 | P43: =SUM(D43:O43) -> 437500
A45: Account 3900 is an equity account and is outside net income; it is carried here because the dividend is a Restricted Payment in the fixed charge coverage test.

Sheet Parameters
A1: Covenant parameters and sources
A3: PARAMETER | B3: VALUE | C3: SOURCE
A4: Maximum Total Leverage Ratio, Fiscal Quarter ending August 31, 2026 | B4: 2.75 | C4: Section 6.11 of the Credit Agreement, third row of the table
A5: Minimum Fixed Charge Coverage Ratio | B5: 1.2 | C5: Section 6.12 of the Credit Agreement
A6: Clause (e) cap, share of Consolidated EBITDA before clause (e) | B6: 0.1 | C6: Section 1.01, definition of Consolidated EBITDA, clause (e)
A7: Clause (e) amount approved in writing, Waupun severance and retention | B7: 412000 | C7: Yablonski email of September 8, 2026
A8: Capital Expenditures limit per Fiscal Year | B8: 2400000 | C8: Section 6.13 of the Credit Agreement
A9: Days after quarter end for the Compliance Certificate | B9: 45 | C9: Section 5.01 of the Credit Agreement
A10: Business Days after the certificate due date for an equity cure | B10: 10 | C10: Section 6.14 of the Credit Agreement
A11: Business Days after knowledge of a Default for written notice | B11: 5 | C11: Section 5.02 of the Credit Agreement
A13: Test Period: September 1, 2025 through August 31, 2026 (the four Fiscal Quarters ended August 31, 2026).
A14: Ostrander Machine LLC acquired March 2, 2026; pre-closing months in the Test Period are September 2025 through February 2026.
A15: Certificate due October 15, 2026, which is 45 days after August 31, 2026.

Sheet Ostrander PF
A1: Acquired EBITDA, Ostrander Machine LLC, September 2025 through February 2026
A2: Source: ostrander_pl_sep25_feb26.xlsx, the seller's monthly statements delivered to the Agent on March 20, 2026. Pre-closing months only; March 2026 onward is in the Oshkosh accounts of the ledger.
A4: LINE | B4: Sep 2025 | C4: Oct 2025 | D4: Nov 2025 | E4: Dec 2025 | F4: Jan 2026 | G4: Feb 2026 | H4: SIX MONTHS | I4: INCOME EFFECT
A5: Sales | B5: 267424.98 | C5: 283646.37 | D5: 269270.23 | E5: 253723.12 | F5: 296599.06 | G5: 297898.35 | H5: =SUM(B5:G5) -> 1668562.1 | I5: =H5 -> 1668562.1
A6: Sales returns | B6: -4177.38 | C6: -2930.83 | D6: -2196.04 | E6: -2340.11 | F6: -2496.02 | G6: -2898.81 | H6: =SUM(B6:G6) -> -17039.19 | I6: =H6 -> -17039.19
A7: Materials and outside services | B7: 90427.76 | C7: 96493.97 | D7: 89038.58 | E7: 84409.66 | F7: 99908.69 | G7: 97641.7 | H7: =SUM(B7:G7) -> 557920.36 | I7: =-H7 -> -557920.36
A8: Shop wages | B8: 57486.93 | C8: 59002.86 | D8: 58026.84 | E8: 54413.14 | F8: 62358.39 | G8: 63270.98 | H8: =SUM(B8:G8) -> 354559.14 | I8: =-H8 -> -354559.14
A9: Shop supplies and tooling | B9: 9212.81 | C9: 10028.9 | D9: 9454.4 | E9: 9251.27 | F9: 10375.38 | G9: 10269.98 | H9: =SUM(B9:G9) -> 58592.74 | I9: =-H9 -> -58592.74
A10: Utilities | B10: 4177.89 | C10: 4567.89 | D10: 5273.61 | E10: 5922.22 | F10: 5856.89 | G10: 5368.68 | H10: =SUM(B10:G10) -> 31167.18 | I10: =-H10 -> -31167.18
A11: Depreciation | B11: 7916.67 | C11: 7916.67 | D11: 7916.67 | E11: 7916.67 | F11: 7916.67 | G11: 7916.67 | H11: =SUM(B11:G11) -> 47500.02 | I11: =-H11 -> -47500.02
A12: Officer salary - D. Ostrander | B12: 18500 | C12: 18500 | D12: 18500 | E12: 18500 | F12: 18500 | G12: 18500 | H12: =SUM(B12:G12) -> 111000 | I12: =-H12 -> -111000
A13: Office wages | B13: 9833.26 | C13: 9624.09 | D13: 9626.84 | E13: 9891.37 | F13: 10111.78 | G13: 9806.79 | H13: =SUM(B13:G13) -> 58894.13 | I13: =-H13 -> -58894.13
A14: Payroll taxes | B14: 6496.45 | C14: 6393.21 | D14: 6366.09 | E14: 6412.32 | F14: 6392.03 | G14: 6618.12 | H14: =SUM(B14:G14) -> 38678.22 | I14: =-H14 -> -38678.22
A15: Rent | B15: 8750 | C15: 8750 | D15: 8750 | E15: 8750 | F15: 8750 | G15: 8750 | H15: =SUM(B15:G15) -> 52500 | I15: =-H15 -> -52500
A16: Insurance | B16: 3226.58 | C16: 3260.05 | D16: 3272.31 | E16: 3234.91 | F16: 3243.1 | G16: 3258.26 | H16: =SUM(B16:G16) -> 19495.21 | I16: =-H16 -> -19495.21
A17: Auto and travel - D. Ostrander | B17: 1370.78 | C17: 1699.19 | D17: 1288.34 | E17: 1820.66 | F17: 1355.78 | G17: 1690.74 | H17: =SUM(B17:G17) -> 9225.49 | I17: =-H17 -> -9225.49
A18: Professional fees | B18: 1400.34 | C18: 1191.15 | D18: 3078.01 | E18: 6338.03 | F18: 1236.62 | G18: 1617.33 | H18: =SUM(B18:G18) -> 14861.48 | I18: =-H18 -> -14861.48
... A23: Miscellaneous | B23: 773 | C23: 967.56 | D23: 529.22 | E23: 959.36 | F23: 817.77 | G23: 568.82 | H23: =SUM(B23:G23) -> 4615.73 | I23: =-H23 -> -4615.73
A25: ACQUIRED EBITDA BUILD | H25: SIX MONTHS
A26: Net ordinary income, six months | H26: =SUM(I5:I23) -> 262405.69
A27: Plus interest expense, line of credit (repaid at closing) | H27: =H21 -> 13103.31
A28: Plus depreciation | H28: =H11 -> 47500.02
A29: Plus officer salary, D. Ostrander (ended at closing; approved in writing September 8, 2026) | H29: =H12 -> 111000
A30: Acquired EBITDA, clause (f) | H30: =SUM(H26:H29) -> 434009.02
A32: Not added: auto and travel, D. Ostrander (no written approval) | H32: =H17 -> 9225.49
A33: Not added: income taxes (none recorded; the seller was taxed as a partnership)

Sheet EBITDA
A1: Consolidated EBITDA, Test Period ended August 31, 2026
A2: Built line by line under Section 1.01 of the Credit Agreement, definition of Consolidated EBITDA. Ledger figures are SUMIFS over the ledger activity tab by covenant line or by account.
A4: INTEREST DETAIL, CLAUSE (a) | B4: AMOUNT | C4: SOURCE
A5: Cash interest expense, accounts 7000, 7005, 7010 and 7015 | B5: =SUMIFS('GL TTM'!$P$5:$P$43,'GL TTM'!$C$5:$C$43,"Cash interest") -> 1033471.8 | C5: GL TTM, covenant line Cash interest
A6: Amortization of deferred financing costs, account 7018 | B6: =SUMIFS('GL TTM'!$P$5:$P$43,'GL TTM'!$C$5:$C$43,"Non-cash interest") -> 57999.96 | C6: GL TTM, covenant line Non-cash interest
A7: Less interest income, account 7050 | B7: =SUMIFS('GL TTM'!$P$5:$P$43,'GL TTM'!$C$5:$C$43,"Interest income") -> -17559.52 | C7: GL TTM, covenant line Interest income
A8: Consolidated Interest Expense, net of interest income | B8: =SUM(B5:B7) -> 1073912.3 | C8: Definition of Consolidated Interest Expense
A10: CONSOLIDATED EBITDA | B10: AMOUNT | C10: SOURCE
A11: Consolidated Net Income, Test Period | B11: =SUM('GL TTM'!$Q$5:$Q$41) -> 1175708.9 | C11: GL TTM, INCOME EFFECT of the income statement accounts
A12: (a) Consolidated Interest Expense, net | B12: =B8 -> 1073912.3 | C12: Interest detail above
A13: (b) Provision for income taxes, accounts 8000 and 8010 | B13: =SUMIFS('GL TTM'!$P$5:$P$43,'GL TTM'!$C$5:$C$43,"Income taxes") -> 535462.28 | C13: GL TTM, covenant line Income taxes
A14: (c) Depreciation and amortization, accounts 5050, 6090 and 6095 | B14: =SUMIFS('GL TTM'!$P$5:$P$43,'GL TTM'!$C$5:$C$43,"Depreciation and amortization") -> 1808911.1 | C14: GL TTM, covenant line Depreciation and amortization
A15: (d) Non-cash charges: write-off of Waupun leasehold improvements, account 7030 | B15: =SUMIFS('GL TTM'!$P$5:$P$43,'GL TTM'!$C$5:$C$43,"Non-cash write-off") -> 61238.47 | C15: GL TTM, covenant line Non-cash write-off; clause (d), not counted against the clause (e) cap
A16: (f) Acquired EBITDA, Ostrander Machine, September 2025 through February 2026 | B16: ='Ostrander PF'!$H$30 -> 434009.02 | C16: Ostrander PF tab; statements delivered March 20, 2026
A17: (g) Less gain on sale of Waupun equipment, account 7020 | B17: =SUMIFS('GL TTM'!$P$5:$P$43,'GL TTM'!$C$5:$C$43,"Gain on sale") -> -86412 | C17: GL TTM, covenant line Gain on sale (a credit, deducted)
A18: Consolidated EBITDA before clause (e) | B18: =SUM(B11:B17) -> 5002830 | C18: Base for the 10% cap in clause (e)
A19: (e) Approved non-recurring cash charges, as permitted | B19: =B27 -> 412000 | C19: Clause (e) working below
A20: Consolidated EBITDA, Test Period ended August 31, 2026 | B20: =SUM(B18:B19) -> 5414830 | C20: Definition of Consolidated EBITDA
A22: CLAUSE (e) WORKING | B22: AMOUNT | C22: SOURCE
A23: Severance and retention, Waupun consolidation, account 6100 | B23: =SUMIFS('GL TTM'!$P$5:$P$43,'GL TTM'!$C$5:$C$43,"Approved non-recurring") -> 438912.55 | C23: GL TTM, covenant line Approved non-recurring
A24: Amount approved in writing by the Agent | B24: =Parameters!$B$7 -> 412000 | C24: Yablonski email of September 8, 2026, up to $412,000 in the aggregate
A25: Add-back requested, the lesser of the expense and the approval | B25: =MIN(B23,B24) -> 412000 | C25: Expense above the approved amount stays in operating expense
A26: Cap: 10% of Consolidated EBITDA before clause (e) | B26: =ROUND(B18*Parameters!$B$6,2) -> 500283 | C26: Clause (e) proviso
A27: (e) permitted, the lesser of the request and the cap | B27: =MIN(B25,B26) -> 412000 | C27: Carried to the Consolidated EBITDA line above
A29: Not added: legal settlement, Kowalczyk matter, account 6110 | B29: =SUMIFS('GL TTM'!$P$5:$P$43,'GL TTM'!$C$5:$C$43,"Not approved") -> 287500 | C29: No written approval from the Agent as of October 13, 2026; Yablonski email of September 11, 2026
A30: Not added: severance and retention above the approved amount | B30: =B23-B25 -> 26912.55 | C30: Remains in operating expense

Sheet Funded Debt
A1: Consolidated Funded Debt as of August 31, 2026
A2: Section 1.01, definition of Consolidated Funded Debt. Balances from treasury_schedules_083126.xlsx.
A4: COMPONENT | B4: AMOUNT | C4: SOURCE
A5: Term Loan, Lakeshore Merchants Bank, balance after the 08/31/2026 scheduled payment | B5: 9050000 | C5: Term Loan tab, BALANCE AFTER on the 08/31/2026 row; clause (a)
A6: Revolving Loans outstanding at 08/31/2026 | B6: 2175000 | C6: Revolver tab, OUTSTANDING at 08/31/2026; clause (a)
A7: Seller Subordinated Note, Ostrander Machine LLC | B7: 1437500 | C7: Seller Note tab, balance after the 06/01/2026 payment; clause (b)
A8: Finance lease FL-01, Vandermolen Equipment Credit, CNC lathe cell (2) - Fond du Lac | B8: 313556.82 | C8: Leases tab, LIABILITY 08/31/2026; clause (c)
A9: Finance lease FL-02, Kessler Leasing Corp, Coordinate measuring machine - Beaver Dam | B9: 164893.83 | C9: Leases tab, LIABILITY 08/31/2026; clause (c)
A10: Finance lease FL-03, Brandt Capital LLC, 5-axis machining center - Beaver Dam | B10: 551152.58 | C10: Leases tab, LIABILITY 08/31/2026; clause (c)
A11: Standby letter of credit SBLC-2024-0117, Waukesha Mutual Casualty Company, face amount (undrawn) | B11: 350000 | C11: LCs tab, FACE AMOUNT; clause (d), whether or not drawn
A12: Standby letter of credit SBLC-2025-0203, Tri-County Natural Gas Cooperative, face amount (undrawn) | B12: 125000 | C12: LCs tab, FACE AMOUNT; clause (d), whether or not drawn
A13: Consolidated Funded Debt, August 31, 2026 | B13: =SUM(B5:B12) -> 14167103 | C13: Sum of clauses (a) through (d); no earn-out is earned and unpaid
A15: EXCLUDED FROM CONSOLIDATED FUNDED DEBT | B15: LIABILITY 08/31/2026 | C15: REASON
A16: Operating lease OL-01, Mertens Properties LLC, Warehouse and office annex - Fond du Lac | B16: 1461799.5 | C16: Operating lease liability, outside the definition
A17: Operating lease OL-02, Schaefer Business Systems, Copiers and print fleet (all plants) | B17: 77345.94 | C17: Operating lease liability, outside the definition
A18: Operating lease OL-03, D and P Ostrander Realty LLC, Shop building - Oshkosh (assumed at closing) | B18: 295903.65 | C18: Operating lease liability, outside the definition

Sheet Capex and Taxes
A1: Unfinanced Capital Expenditures and Cash Taxes, Test Period
A2: Source: treasury_schedules_083126.xlsx, Capex and Income Taxes tabs. Fiscal Year 2026 began December 1, 2025.
A4: MONTH | B4: FISCAL YEAR | C4: ADDITION | D4: AMOUNT | E4: FUNDING
A5: Sep-25 | B5: FY2025 | C5: Fixture set and gauging - Fond du Lac (Fond du Lac) | D5: 38412.6 | E5: Cash
A6: Oct-25 | B6: FY2025 | C6: Air compressor replacement (Beaver Dam) | D6: 54900 | E6: Cash
A7: Nov-25 | B7: FY2025 | C7: Beaver Dam expansion - electrical service (Beaver Dam) | D7: 287250.45 | E7: Cash
A8: Dec-25 | B8: FY2026 | C8: Beaver Dam expansion - relocation of Waupun equipment (Beaver Dam) | D8: 96318.2 | E8: Cash
A9: Jan-26 | B9: FY2026 | C9: 5-axis machining center (Brandt lease FL-03) (Beaver Dam) | D9: 612450 | E9: Finance lease
A10: Jan-26 | B10: FY2026 | C10: Tooling and workholding for 5-axis center (Beaver Dam) | D10: 41775.9 | E10: Cash
A11: Feb-26 | B11: FY2026 | C11: Forklift (Fond du Lac) | D11: 46200 | E11: Cash
A12: Mar-26 | B12: FY2026 | C12: Oshkosh shop - network and workstations (Oshkosh) | D12: 22614.33 | E12: Cash
A13: Apr-26 | B13: FY2026 | C13: Bar feeder (Fond du Lac) | D13: 78940 | E13: Cash
A14: May-26 | B14: FY2026 | C14: Roof section replacement (Fond du Lac) | D14: 152500 | E14: Cash
A15: Jun-26 | B15: FY2026 | C15: Surface grinder rebuild (Beaver Dam) | D15: 61208.75 | E15: Cash
A16: Jul-26 | B16: FY2026 | C16: Delivery van (Fond du Lac) | D16: 47315 | E16: Cash
... A18: Aug-26 | B18: FY2026 | C18: CMM software upgrade (Fond du Lac) | D18: 29650 | E18: Cash
C20: Capital Expenditures, Test Period | D20: =SUM(D5:D18) -> 1801015.8
C21: Financed under a finance lease when placed in service | D21: =SUMIFS(D5:D18,E5:E18,"Finance lease") -> 612450
C22: Unfinanced Capital Expenditures, Test Period | D22: =D20-D21 -> 1188565.8
C23: Capital Expenditures, Fiscal Year 2026 to date (December 2025 through August 2026) | D23: =SUMIFS(D5:D18,B5:B18,"FY2026") -> 1420452.8
C24: Limit per Fiscal Year, Section 6.13 (tested as of November 30 only) | D24: =Parameters!$B$8 -> 2400000
A26: DATE | B26: PAYMENT OR REFUND | C26: FEDERAL | D26: STATE
A27: 11/17/2025 | B27: Estimated payment - fourth installment FY2025 | C27: 104000 | D27: 27500
A28: 01/22/2026 | B28: Refund received - FY2024 federal return | C28: -42610 | D28: 0
A29: 02/17/2026 | B29: Payment with extension - FY2025 returns | C29: 58340 | D29: 15115
A30: 03/16/2026 | B30: Estimated payment - first installment FY2026 | C30: 109000 | D30: 28500
A31: 05/15/2026 | B31: Estimated payment - second installment FY2026 | C31: 109000 | D31: 28500
A32: 08/17/2026 | B32: Estimated payment - third installment FY2026 | C32: 116000 | D32: 30500
B33: Federal income taxes paid in cash, net of the refund | C33: =SUM(C27:C32) -> 453730
B34: State income taxes paid in cash | C34: =SUM(D27:D32) -> 130115
B35: Cash Taxes, Test Period | C35: =SUM(C33:C34) -> 583845
B36: The provision in accounts 8000 and 8010 is the accrual and is not Cash Taxes.

Sheet Fixed Charges
A1: Fixed Charges and the Fixed Charge Coverage Ratio, Test Period ended August 31, 2026
A2: Section 1.01, definitions of Consolidated Cash Interest Expense, Scheduled Principal Payments, Fixed Charges and Fixed Charge Coverage Ratio; Section 6.12.
A4: CONSOLIDATED CASH INTEREST EXPENSE | B4: AMOUNT | C4: SOURCE
A5: Interest expense, term loan, account 7000 | B5: =SUMIFS('GL TTM'!$P$5:$P$43,'GL TTM'!$A$5:$A$43,7000) -> 732037.47 | C5: GL TTM, account 7000
A6: Interest expense, revolving loans, account 7005 | B6: =SUMIFS('GL TTM'!$P$5:$P$43,'GL TTM'!$A$5:$A$43,7005) -> 197898.62 | C6: GL TTM, account 7005
A7: Interest expense, seller note, account 7010 | B7: =SUMIFS('GL TTM'!$P$5:$P$43,'GL TTM'!$A$5:$A$43,7010) -> 43812.5 | C7: GL TTM, account 7010
A8: Interest expense, finance leases, account 7015 | B8: =SUMIFS('GL TTM'!$P$5:$P$43,'GL TTM'!$A$5:$A$43,7015) -> 59723.23 | C8: GL TTM, account 7015
A9: Less interest income, account 7050 | B9: =SUMIFS('GL TTM'!$P$5:$P$43,'GL TTM'!$A$5:$A$43,7050) -> -17559.52 | C9: GL TTM; Consolidated Interest Expense is net of interest income
A10: Consolidated Cash Interest Expense | B10: =SUM(B5:B9) -> 1015912.3 | C10: Excludes the amortization of deferred financing costs in account 7018, which is not paid in cash
A12: SCHEDULED PRINCIPAL PAYMENTS | B12: AMOUNT | C12: SOURCE
A13: Term Loan scheduled principal payment, 11/30/2025 | B13: 350000 | C13: Term Loan tab
A14: Term Loan scheduled principal payment, 02/28/2026 | B14: 350000 | C14: Term Loan tab
A15: Term Loan scheduled principal payment, 05/31/2026 | B15: 350000 | C15: Term Loan tab
A16: Term Loan scheduled principal payment, 08/31/2026 | B16: 350000 | C16: Term Loan tab
A17: Seller Subordinated Note scheduled principal payment, 06/01/2026 | B17: 62500 | C17: Seller Note tab
A18: Finance lease FL-01 principal paid, Vandermolen Equipment Credit | B18: 157295.3 | C18: Leases tab, PRINCIPAL PAID TTM
A19: Finance lease FL-02 principal paid, Kessler Leasing Corp | B19: 71690.75 | C19: Leases tab, PRINCIPAL PAID TTM
A20: Finance lease FL-03 principal paid, Brandt Capital LLC | B20: 61297.42 | C20: Leases tab, PRINCIPAL PAID TTM
A21: Scheduled Principal Payments | B21: =SUM(B13:B20) -> 1752783.5 | C21: Definition of Scheduled Principal Payments
A22: Not included: voluntary prepayment of the Term Loan on 04/15/2026 | B22: 500000 | C22: Excluded by clause (a) of the definition; revolver paydowns excluded by clause (b)
A24: Fixed Charges, Test Period | B24: =SUM(B10,B21) -> 2768695.8 | C24: Consolidated Cash Interest Expense plus Scheduled Principal Payments
A26: FIXED CHARGE COVERAGE RATIO | B26: AMOUNT | C26: SOURCE
A27: Consolidated EBITDA, Test Period | B27: =EBITDA!$B$20 -> 5414830 | C27: EBITDA tab
A28: Less Unfinanced Capital Expenditures | B28: =-'Capex and Taxes'!$D$22 -> -1188565.8 | C28: Capex and Taxes tab
A29: Less Cash Taxes | B29: =-'Capex and Taxes'!$C$35 -> -583845 | C29: Capex and Taxes tab
A30: Less Restricted Payments, dividend paid December 19, 2025, account 3900 | B30: =-SUMIFS('GL TTM'!$P$5:$P$43,'GL TTM'!$C$5:$C$43,"Restricted payment") -> -437500 | C30: GL TTM, covenant line Restricted payment
A31: Numerator of the Fixed Charge Coverage Ratio | B31: =SUM(B27:B30) -> 3204919.2
A32: Fixed Charges | B32: =B24 -> 2768695.8
A33: Fixed Charge Coverage Ratio | B33: =ROUND(B31/B32,2) -> 1.16
A34: Minimum required, Section 6.12 | B34: =Parameters!$B$5 -> 1.2
A35: Section 6.12 status | B35: =IF(B33>=B34,"In compliance","Not in compliance") -> Not in compliance
A36: Numerator required at the minimum ratio | B36: =ROUND(B32*B34,2) -> 3322434.9
A37: Shortfall in the numerator, the Cure Amount required under Section 6.14 | B37: =B36-B31 -> 117515.74 | C37: Cash common equity within ten Business Days after October 15, 2026
A39: IF THE KOWALCZYK SETTLEMENT WERE APPROVED UNDER CLAUSE (e) | B39: AMOUNT | C39: SOURCE
A40: Room left under the clause (e) cap after the severance add-back | B40: =EBITDA!B26-EBITDA!B27 -> 88283 | C40: EBITDA tab, cap less the amount permitted; the settlement of $287,500.00 would be limited to this
A41: Numerator with the settlement added at the capped amount | B41: =B31+B40 -> 3293202.2
A42: Fixed Charge Coverage Ratio with the settlement approved | B42: =ROUND(B41/B32,2) -> 1.19
A43: Section 6.12 status with the settlement approved | B43: =IF(B42>=B34,"In compliance","Not in compliance") -> Not in compliance

Sheet Note to Wade
A1: To: Wade Kirchner, Chief Financial Officer
A2: Date: October 13, 2026
A3: Re: Compliance Certificate for the Fiscal Quarter ended August 31, 2026
A5: The certificate cannot go to Curtis as a clean certificate. The Total Leverage Ratio is 2.62 to 1.00 against a maximum of 2.75 to 1.00, so Section 6.11 is met. The Fixed Charge Coverage Ratio is 1.16 to 1.00 against the 1.20 to 1.00 minimum in Section 6.12, and that covenant is not met. Schedule 1 states the Event of Default, and the second certification on the front reads with the Schedule 1 exception.
A6: The leverage headroom is smaller than the 3.00 to 1.00 in your note to Curtis of September 10, 2026. Section 6.11 steps the maximum down to 2.75 to 1.00 for the Fiscal Quarter ending August 31, 2026, and Schedule 2 tests against that figure.
A7: The shortfall in the fixed charge numerator is $117,515.74, and that is the Cure Amount under Section 6.14: cash common equity contributed within ten Business Days after October 15, 2026, the day the certificate is due under Section 5.01. Section 6.14 allows a cure in no more than two Fiscal Quarters out of any four and never in consecutive quarters, so a cure now closes the option for the quarter ending November 30, 2026. The other route is a waiver or amendment, which is the Agent's decision rather than ours.
A8: Section 5.02 requires written notice of the Default to the Agent within five Business Days after a Responsible Officer has knowledge of it, and that period runs from the day you read this note. The certificate delivered on October 15 falls inside that period and can serve as the notice, since Schedule 1 states the details and the action proposed, but a short letter to Curtis this week keeps the two dates from depending on each other.
A9: The Kowalczyk settlement of $287,500.00 in account 6110 is not in the add-backs. Clause (e) allows only charges the Agent has approved in writing, and Curtis's email of September 11, 2026 says committee does not take it up until October 7. An approval would not cure the shortfall on its own. The clause (e) total is capped at $500,283.00, which is 10% of the $5,002,830.01 of Consolidated EBITDA before clause (e), so the settlement would add $88,283.00 rather than $287,500.00. The ratio would then be 1.19 to 1.00, still under the minimum.
A10: The Waupun severance and retention costs of $438,912.55 in account 6100 are added back at $412,000.00, the ceiling in Curtis's approval of September 8, 2026, and the $26,912.55 above it stays in expense. The Waupun leasehold write-off of $61,238.47 in account 7030 is a non-cash charge under clause (d), so it is added back in full and does not count against the clause (e) cap.
A11: Acquired EBITDA for Ostrander is $434,009.02 for September 2025 through February 2026, the six months before the March 2, 2026 closing, built from the statements we sent Curtis: net ordinary income plus the line of credit interest, depreciation, and Dale Ostrander's officer salary, which is the one adjustment approved. His auto and travel costs of $9,225.49 are not added. March through August is already in our ledger in the Oshkosh accounts, so nothing is added for those months.
A12: Consolidated Funded Debt is $14,167,103.23: the term loan after the August 31 scheduled payment, the revolver, the Ostrander seller note, the three finance leases, and the face amount of the two standby letters of credit, which count whether or not drawn. The three operating leases are outside the definition and are listed on the funded debt schedule as excluded.
A13: Fixed Charges are $2,768,695.77. Cash interest is the four interest accounts net of interest income, without the amortization of deferred financing costs, which is added back to EBITDA but is not paid in cash. Scheduled principal is the four quarterly term loan payments, the June seller note payment, and the principal portion of the finance lease payments. The $500,000.00 prepayment on April 15, 2026 was voluntary and is excluded, and so are the revolver paydowns.
... A16: Two things this package does not settle. Committee's answer on the Kowalczyk settlement comes after October 7, and an approval would move the ratio to 1.19 to 1.00 without curing it. The Ostrander figures are the seller's internally prepared statements, which the Agent accepted for clause (f) but which no one has audited, and the calculation rests on them as delivered.
