Workbook

Sheet Summary
A1: Recorded claims of mechanics lien, Larkspur Crossing Building B, 2210 Pleasant Grove Boulevard, Roseville: analysis for the refinance
A2: Prepared for Marguerite Okonjo for Piedmont Ridge Properties, LLC, from the recorder's copies of the fifteen claims, the owner's project file, the direct contractor's payment ledger, and the close-out file
A4: The two answers for Nadia
A5: Answer | B5: Value | C5: Read from
A6: Release bonds required, total penal sum at 125 percent | B6: =SUM(K25:K39) -> 578094.11 | C6: Claim by claim in the table below
A7: Line the surety has approved for release bonds | B7: =Parameters!$B$24 -> 575000 | C7: Nadia Ferris email of October 2, 2026
A8: Bonds required over the surety's line | B8: =ROUND(B6-B7,2) -> 3094.11 | C8: Bonds required less the line
A9: Do the bonds fit inside the surety's line | B9: =IF(B6<=B7,"Yes, the bonds are inside the line","No, the bonds are over the line") -> No, the bonds are over the line | C9: section 8424(b), 125 percent of each recorded claim
A10: Enforceable by claimants under the Dunmore-Kettle contract | B10: =Claims!D23 -> 286087.47 | C10: Every enforceable claim except the claimant that contracted with the owner itself
A11: Held by the owner on the Dunmore-Kettle contract | B11: =Parameters!$B$44 -> 283135.5 | C11: Adjusted contract sum less payments: unpaid application 8 and the retention
A12: Enforceable claims over what the owner holds | B12: =ROUND(B10-B11,2) -> 2951.97 | C12: Enforceable under the contract less the money held
A13: Does what the owner holds cover those claims | B13: =IF(B10<=B11,"Yes, the money held covers them","No, the money held falls short") -> No, the money held falls short | C13: PN-14, what the owner holds on a direct contract
A15: Totals
A16: Total | B16: Value
A17: Amount of the fifteen claims as recorded | B17: =SUM(C25:C39) -> 561561.79
A18: Amount the claimants could enforce against the property | B18: =SUM(I25:I39) -> 311167.47
A19: Claims to bond or settle | B19: =Claims!D20 -> 10
A20: Claims to demand released | B20: =Claims!D21 -> 5
A21: Recorded amount of the claims to demand released | B21: =Claims!D22 -> 99086.5
A23: The fifteen recorded claims
A24: CLAIMANT | B24: RECORDED | C24: AMOUNT_AS_RECORDED | D24: LIEN_RIGHTS | E24: TIMELY | F24: SERVED_ON_OWNER | G24: EXPIRED | H24: STANDING | I24: ENFORCEABLE_AMOUNT | J24: WHAT_WE_DO | K24: RELEASE_BOND | L24: WAIVERS_ON_FILE | M24: WHAT_DECIDES_IT
A25: =Claims!A4 -> Tallac Concrete, Inc. | B25: =Claims!B4 -> 06/26/2026 | C25: =Claims!D4 -> 33275 | D25: =Claims!F4 -> Yes | E25: =Claims!G4 -> Yes | F25: =Claims!H4 -> Yes | G25: =Claims!I4 -> Yes | H25: =Claims!J4 -> Expired | I25: =Claims!K4 -> 0 | J25: =Claims!M4 -> Demand a release under section 8482, then petition under sections 8480 to 8488 after 10 days | K25: =Claims!N4 -> 0 | L25: Progress waivers through 04/30/2026; the May letter is not a statutory form | M25: No action by 09/24/2026; the search of 10/02/2026 is later
A26: =Claims!A5 -> Foothill Ready Mix, Inc. | B26: =Claims!B5 -> 07/06/2026 | C26: =Claims!D5 -> 17204.84 | D26: =Claims!F5 -> Yes | E26: =Claims!G5 -> Yes | F26: =Claims!H5 -> Yes | G26: =Claims!I5 -> Not shown | H26: =Claims!J5 -> Enforceable | I26: =Claims!K5 -> 17204.84 | J26: =Claims!M5 -> Bond at 125 percent until a new index search shows no action, then demand a release | K26: =Claims!N5 -> 21506.05 | L26: None on file | M26: Last day to sue 10/05/2026 is after the 10/02/2026 search
A27: =Claims!A6 -> Norcal Rebar & Mesh, LLC | B27: =Claims!B6 -> 09/14/2026 | C27: =Claims!D6 -> 27640 | D27: =Claims!F6 -> No | E27: =Claims!G6 -> Yes | F27: =Claims!H6 -> Yes | G27: =Claims!I6 -> No | H27: =Claims!J6 -> No lien rights | I27: =Claims!K6 -> 0 | J27: =Claims!M6 -> Demand a recorded release, the defect being no preliminary notice to the owner | K27: =Claims!N6 -> 0 | L27: None on file | M27: Preliminary notice never given to the owner
A28: =Claims!A7 -> Hedrick & Sons Building Supply | B28: =Claims!B7 -> 09/16/2026 | C28: =Claims!D7 -> 54230.81 | D28: =Claims!F7 -> Yes | E28: =Claims!G7 -> Yes | F28: =Claims!H7 -> Yes | G28: =Claims!I7 -> No | H28: =Claims!J7 -> Enforceable | I28: =Claims!K7 -> 29091.69 | J28: =Claims!M7 -> Bond at 125 percent of the recorded claim, or take an amended claim at the enforceable amount | K28: =Claims!N7 -> 67788.51 | L28: None on file | M28: Late notice deposited 05/29/2026 reaches back to 05/09/2026
A29: =Claims!A8 -> Abrego Glass & Glazing | B29: =Claims!B8 -> 09/17/2026 | C29: =Claims!D8 -> 9345 | D29: =Claims!F8 -> Yes | E29: =Claims!G8 -> Yes | F29: =Claims!H8 -> No | G29: =Claims!I8 -> No | H29: =Claims!J8 -> Not served on the owner | I29: =Claims!K8 -> 0 | J29: =Claims!M8 -> Demand a recorded release, the defect being no service on the owner | K29: =Claims!N8 -> 0 | L29: Progress waivers through 06/30/2026; retention is saved | M29: Claim mailed to Dunmore-Kettle, not to the owner
A30: =Claims!A9 -> Kastner Mechanical Contractors, Inc. | B30: =Claims!B9 -> 09/21/2026 | C30: =Claims!D9 -> 159145 | D30: =Claims!F9 -> Yes | E30: =Claims!G9 -> Yes | F30: =Claims!H9 -> Yes | G30: =Claims!I9 -> No | H30: =Claims!J9 -> Enforceable | I30: =Claims!K9 -> 85235 | J30: =Claims!M9 -> Bond at 125 percent of the recorded claim, or take an amended claim at the enforceable amount | K30: =Claims!N9 -> 198931.25 | L30: July waiver rests on stopped check 4460; July was paid by check 4474 | M30: Replacement check 4474 paid at the bank on 09/23/2026
A31: =Claims!A10 -> Bautista Painting Co. | B31: =Claims!B10 -> 09/22/2026 | C31: =Claims!D10 -> 46600 | D31: =Claims!F10 -> Yes | E31: =Claims!G10 -> Yes | F31: =Claims!H10 -> Yes | G31: =Claims!I10 -> No | H31: =Claims!J10 -> Enforceable | I31: =Claims!K10 -> 8125 | J31: =Claims!M10 -> Bond at 125 percent of the recorded claim, or take an amended claim at the enforceable amount | K31: =Claims!N10 -> 58250 | L31: Unconditional through 07/31/2026 releases the unpaid July draw | M31: Unconditional waiver effective when signed
A32: =Claims!A11 -> Fenwick Roofing, Inc. | B32: =Claims!B11 -> 09/23/2026 | C32: =Claims!D11 -> 14937.5 | D32: =Claims!F11 -> Yes | E32: =Claims!G11 -> Yes | F32: =Claims!H11 -> Yes | G32: =Claims!I11 -> No | H32: =Claims!J11 -> Waived in full | I32: =Claims!K11 -> 0 | J32: =Claims!M11 -> Demand a recorded release, the defect being a final waiver of the whole claim | K32: =Claims!N11 -> 0 | L32: Conditional final waiver, check 4448 paid; releases the retention too | M32: A final form releases every lien right, retention included
A33: =Claims!A12 -> Lindqvist Fire Protection | B33: =Claims!B12 -> 09/24/2026 | C33: =Claims!D12 -> 16600 | D33: =Claims!F12 -> Yes | E33: =Claims!G12 -> Yes | F33: =Claims!H12 -> Yes | G33: =Claims!I12 -> No | H33: =Claims!J12 -> Enforceable | I33: =Claims!K12 -> 7132.5 | J33: =Claims!M12 -> Bond at 125 percent of the recorded claim, or take an amended claim at the enforceable amount | K33: =Claims!N12 -> 20750 | L33: Unconditional through 06/30/2026; retention saved, request 3 never approved | M33: Change order request 3 is not part of the price agreed
A34: =Claims!A13 -> Sierra Pipe & Supply, Inc. | B34: =Claims!B13 -> 09/24/2026 | C34: =Claims!D13 -> 19742.64 | D34: =Claims!F13 -> Yes | E34: =Claims!G13 -> Yes | F34: =Claims!H13 -> Yes | G34: =Claims!I13 -> No | H34: =Claims!J13 -> Enforceable | I34: =Claims!K13 -> 15426.44 | J34: =Claims!M13 -> Bond at 125 percent of the recorded claim, or take an amended claim at the enforceable amount | K34: =Claims!N13 -> 24678.3 | L34: None on file | M34: Late notice deposited 03/16/2026 reaches back to 02/24/2026
A35: =Claims!A14 -> Ostrowski Electric, Inc. | B35: =Claims!B14 -> 09/28/2026 | C35: =Claims!D14 -> 61477 | D35: =Claims!F14 -> Yes | E35: =Claims!G14 -> Yes | F35: =Claims!H14 -> Yes | G35: =Claims!I14 -> No | H35: =Claims!J14 -> Enforceable | I35: =Claims!K14 -> 61477 | J35: =Claims!M14 -> Bond at 125 percent, or pay from the money held against an unconditional final release | K35: =Claims!N14 -> 76846.25 | L35: July released on check 4461; check 4479 has not paid at the bank | M35: Recorded on the extended last day, 09/28/2026
A36: =Claims!A15 -> Calder Drywall & Plaster, LLC | B36: =Claims!B15 -> 09/29/2026 | C36: =Claims!D15 -> 38915 | D36: =Claims!F15 -> Yes | E36: =Claims!G15 -> Yes | F36: =Claims!H15 -> Yes | G36: =Claims!I15 -> No | H36: =Claims!J15 -> Enforceable | I36: =Claims!K15 -> 38915 | J36: =Claims!M15 -> Bond at 125 percent, or pay from the money held against an unconditional final release | K36: =Claims!N15 -> 48643.75 | L36: July release is on the contractor's form S-9; releases nothing | M36: No copy of the notice of completion; last day 11/09/2026
... A39: =Claims!A18 -> Capitol Wire & Lighting, Inc. | B39: =Claims!B18 -> 10/01/2026 | C39: =Claims!D18 -> 23480 | D39: =Claims!F18 -> Yes | E39: =Claims!G18 -> Yes | F39: =Claims!H18 -> Yes | G39: =Claims!I18 -> No | H39: =Claims!J18 -> Enforceable | I39: =Claims!K18 -> 23480 | J39: =Claims!M18 -> Bond at 125 percent, or pay from the money held against an unconditional final release | K39: =Claims!N18 -> 29350 | L39: None on file | M39: Copy mailed 09/09/2026, a day late; last day 11/09/2026
A41: Dates that govern every claim
A42: Date | B42: Value | C42: Read from
A43: Completion of the work of improvement | B43: =Parameters!B4 -> 08/11/2026 | C43: Completion memorandum and notice of completion item 5
A44: Notice of completion recorded | B44: =Parameters!B5 -> 08/26/2026 | C44: Document No. 2026-0081562
A45: Days from completion to recording | B45: =Parameters!B34 -> 15 | C45: The fifteenth day, the last that section 8182(a) allows
A46: Notice of completion effective | B46: =Parameters!B35 -> Yes, recorded within 15 days of completion | C46: section 8182(a)
A47: Last day to give a copy of the notice of completion | B47: =Parameters!B38 -> 09/08/2026 | C47: The tenth day, 09/05/2026, was a Saturday and the Monday was Labor Day, so section 12a runs the period to the Tuesday
A48: Last day to record, claimant given its copy in time | B48: =Parameters!B41 -> 09/28/2026 | C48: The thirtieth day, 09/25/2026, was a day the county offices were closed for the whole day, a holiday under section 12b, so section 12a runs the period to the Monday
A49: Last day to record, person not given a copy in time | B49: =Parameters!B43 -> 11/09/2026 | C49: section 8190(d), 90 days after completion
A50: Last day for Dunmore-Kettle Builders to record | B50: ='NOC Copies'!I22 -> 11/09/2026 | C50: Its copy was mailed 09/09/2026, after the last day to give it
A51: Civil index and recorder searches run | B51: =Parameters!B20 -> 10/02/2026 | C51: No action by any claimant found; no notice of pendency of action
A52: Bank's date for releases and bonds of record | B52: =Parameters!B23 -> 11/06/2026 | C52: Sutter Valley Bank counsel, per the October 2 email
A53: Refinance closing | B53: =Parameters!B22 -> 11/20/2026 | C53: October 2 email
A55: Every value on this page reads from the tabs behind it. Standing, enforceable amount, and bond are worked on the Claims tab from the Notices, NOC Copies, Deadlines, Waivers, and Amounts tabs, and the governing dates and money figures are on the Parameters tab.

Sheet Parameters
A1: Dates, rule constants, and money figures the analysis applies, with the source of each
A3: PARAMETER | B3: VALUE | C3: SERIAL | D3: SOURCE
A4: Completion of the work of improvement | B4: 08/11/2026 | C4: =DATE(VALUE(RIGHT(B4,4)),VALUE(LEFT(B4,2)),VALUE(MID(B4,4,2))) -> 46245 | D4: Completion memorandum of August 19, 2026, final inspection and last labor; notice of completion item 5
A5: Notice of completion recorded | B5: 08/26/2026 | C5: =DATE(VALUE(RIGHT(B5,4)),VALUE(LEFT(B5,2)),VALUE(MID(B5,4,2))) -> 46260 | D5: Notice of completion, Document No. 2026-0081562
A6: Holiday, Labor Day | B6: 09/07/2026 | C6: =DATE(VALUE(RIGHT(B6,4)),VALUE(LEFT(B6,2)),VALUE(MID(B6,4,2))) -> 46272 | D6: Memorandum of September 10, 2026 on the copies of the notice of completion
A7: Holiday under Code of Civil Procedure section 12b, county offices closed the whole day | B7: 09/25/2026 | C7: =DATE(VALUE(RIGHT(B7,4)),VALUE(LEFT(B7,2)),VALUE(MID(B7,4,2))) -> 46290 | D7: Close-out file, part D, civil index search
A8: Days allowed to record a notice of completion after completion | B8: 15 | D8: section 8182(a)
A9: Days allowed to give a copy of the notice of completion | B9: 10 | D9: section 8190(a)
A10: Days after the notice of completion to record, claimants other than the direct contractor | B10: 30 | D10: section 8414
A11: Days after the notice of completion to record, direct contractor | B11: 60 | D11: section 8412
A12: Days after completion to record where the notice does not shorten the time | B12: 90 | D12: section 8190(d) with sections 8412 and 8414
A13: Days after first furnishing for a timely preliminary notice | B13: 20 | D13: section 8204(a)
A14: Days a late preliminary notice reaches back | B14: 20 | D14: section 8204(b)
A15: Days after recording to commence an action | B15: 90 | D15: section 8460(a)
A16: Release bond, percent of the recorded claim | B16: 125 | D16: section 8424(b)
A17: Days between the demand for release and a petition | B17: 10 | D17: section 8482
A18: Days after completion for payment of retention | B18: 45 | D18: section 8812(a)
A19: Percent of a disputed amount the owner may withhold from retention | B19: 150 | D19: section 8812(c)
A20: Civil index and recorder searches run | B20: 10/02/2026 | C20: =DATE(VALUE(RIGHT(B20,4)),VALUE(LEFT(B20,2)),VALUE(MID(B20,4,2))) -> 46297 | D20: Close-out file, part D
A21: Date the analysis is due | B21: 10/20/2026 | C21: =DATE(VALUE(RIGHT(B21,4)),VALUE(LEFT(B21,2)),VALUE(MID(B21,4,2))) -> 46315 | D21: The handoff, Tuesday, October 20
A22: Refinance closing | B22: 11/20/2026 | C22: =DATE(VALUE(RIGHT(B22,4)),VALUE(LEFT(B22,2)),VALUE(MID(B22,4,2))) -> 46346 | D22: Nadia Ferris email of October 2, 2026
A23: Bank's date for releases and bonds of record | B23: 11/06/2026 | C23: =DATE(VALUE(RIGHT(B23,4)),VALUE(LEFT(B23,2)),VALUE(MID(B23,4,2))) -> 46332 | D23: Nadia Ferris email of October 2, 2026
A24: Line the surety has approved for release bonds | B24: 575000 | D24: Nadia Ferris email of October 2, 2026
A25: Contract sum, Dunmore-Kettle Builders, Inc., as signed | B25: 3748250 | D25: Owner Payments tab of the project file; completion memorandum of August 19, 2026
A26: Change orders 1 to 6 approved by the owner | B26: 46000 | D26: Owner Payments tab of the project file; completion memorandum of August 19, 2026
A27: Adjusted contract sum | B27: =ROUND(B25+B26,2) -> 3794250 | D27: PN-14 on what the owner holds, the contract sum as adjusted by the approved change orders
A28: Paid to the direct contractor to date | B28: 3511114.5 | D28: Owner Payments tab, applications 1 through 7; application 8 is unpaid
A29: Retention withheld from the direct contractor | B29: 189712.5 | D29: Owner Payments tab of the project file; completion memorandum
A30: Direct contractor's estimate to correct the two rooftop units | B30: 22000 | D30: Completion memorandum of August 19, 2026
A32: Derived dates and figures
A33: PARAMETER | B33: VALUE | C33: SERIAL | D33: SOURCE
A34: Days from completion to the recording of the notice of completion | B34: =Parameters!$C$5-Parameters!$C$4 -> 15 | D34: Completion and recording rows above
A35: Notice of completion effective under section 8182 | B35: =IF((Parameters!$C$5-Parameters!$C$4)<=Parameters!$B$8,"Yes, recorded within 15 days of completion","No, recorded more than 15 days after completion") -> Yes, recorded within 15 days of completion | D35: section 8182(a), the fifteenth day counted with the day of completion excluded
A36: Tenth day after the notice of completion was recorded | B36: =TEXT(C36,"mm/dd/yyyy") -> 09/05/2026 | C36: =Parameters!$C$5+Parameters!$B$9 -> 46270 | D36: section 8190(a), before the section 12a extension
A37: Weekday of the tenth day | B37: =TEXT(Parameters!$C$5+Parameters!$B$9,"dddd") -> Saturday | D37: A Saturday, followed by the Sunday and by Labor Day
A38: Last day to give a copy of the notice of completion | B38: =TEXT(C38,"mm/dd/yyyy") -> 09/08/2026 | C38: =IF(OR(WEEKDAY(Parameters!$C$5+Parameters!$B$9,2)>5,COUNTIF(Parameters!$C$6:$C$7,Parameters!$C$5+Parameters!$B$9)>0),WORKDAY(Parameters!$C$5+Parameters!$B$9,1,Parameters!$C$6:$C$7),Parameters!$C$5+Parameters!$B$9) -> 46273 | D38: section 8190(a) with the section 12a extension
A39: Thirtieth day after the notice of completion | B39: =TEXT(C39,"mm/dd/yyyy") -> 09/25/2026 | C39: =Parameters!$C$5+Parameters!$B$10 -> 46290 | D39: section 8414, before the section 12a extension
A40: Weekday of the thirtieth day | B40: =TEXT(Parameters!$C$5+Parameters!$B$10,"dddd") -> Friday | D40: A Friday on which the county offices were closed for the whole day
A41: Last day to record, claimant given its copy in time | B41: =TEXT(C41,"mm/dd/yyyy") -> 09/28/2026 | C41: =IF(OR(WEEKDAY(Parameters!$C$5+Parameters!$B$10,2)>5,COUNTIF(Parameters!$C$6:$C$7,Parameters!$C$5+Parameters!$B$10)>0),WORKDAY(Parameters!$C$5+Parameters!$B$10,1,Parameters!$C$6:$C$7),Parameters!$C$5+Parameters!$B$10) -> 46293 | D41: section 8414 with the section 12a extension
A42: Last day to record, direct contractor given its copy in time | B42: =TEXT(C42,"mm/dd/yyyy") -> 10/26/2026 | C42: =IF(OR(WEEKDAY(Parameters!$C$5+Parameters!$B$11,2)>5,COUNTIF(Parameters!$C$6:$C$7,Parameters!$C$5+Parameters!$B$11)>0),WORKDAY(Parameters!$C$5+Parameters!$B$11,1,Parameters!$C$6:$C$7),Parameters!$C$5+Parameters!$B$11) -> 46321 | D42: section 8412 with the section 12a extension
A43: Last day to record, person not given a copy in time | B43: =TEXT(C43,"mm/dd/yyyy") -> 11/09/2026 | C43: =IF(OR(WEEKDAY(Parameters!$C$4+Parameters!$B$12,2)>5,COUNTIF(Parameters!$C$6:$C$7,Parameters!$C$4+Parameters!$B$12)>0),WORKDAY(Parameters!$C$4+Parameters!$B$12,1,Parameters!$C$6:$C$7),Parameters!$C$4+Parameters!$B$12) -> 46335 | D43: section 8190(d), 90 days after completion
A44: Held by the owner on the Dunmore-Kettle contract | B44: =ROUND(Parameters!$B$27-Parameters!$B$28,2) -> 283135.5 | D44: PN-14, the adjusted contract sum less what the owner has paid on it
A45: Retention due to the direct contractor | B45: =TEXT(C45,"mm/dd/yyyy") -> 09/28/2026 | C45: =IF(OR(WEEKDAY(Parameters!$C$4+Parameters!$B$18,2)>5,COUNTIF(Parameters!$C$6:$C$7,Parameters!$C$4+Parameters!$B$18)>0),WORKDAY(Parameters!$C$4+Parameters!$B$18,1,Parameters!$C$6:$C$7),Parameters!$C$4+Parameters!$B$18) -> 46293 | D45: section 8812(a) with the section 12a extension
A46: Retention the owner may withhold for the rooftop unit correction | B46: =ROUND(Parameters!$B$30*Parameters!$B$19/100,2) -> 33000 | D46: section 8812(c), 150 percent of the disputed amount

Sheet DK Ledger
A1: Dunmore-Kettle Builders subcontractor payment ledger, dk_subcontractor_payments.csv, copied line for line
A3: ENTRY_DATE | B3: CHECK_NO | C3: TYPE | D3: PAYEE | E3: TRADE | F3: PAY_APP | G3: AMOUNT | H3: BANK_CLEARED
A4: 03/27/2026 | B4: 4390 | C4: CHK | D4: Ostrowski Electric Inc | E4: Electrical | F4: 2 | G4: 152950 | H4: 04/01/2026
A5: 03/27/2026 | B5: 4391 | C5: CHK | D5: Tallac Concrete Inc | E5: Site concrete | F5: 2 | G5: 71250 | H5: 03/31/2026
A6: 03/27/2026 | B6: 4393 | C6: CHK | D6: Petrakis Plumbing Inc | E6: Plumbing | F6: 2 | G6: 61370 | H6: 04/02/2026
A7: 04/28/2026 | B7: 4402 | C7: CHK | D7: Ostrowski Electric Inc | E7: Electrical | F7: 3 | G7: 121600 | H7: 05/01/2026
A8: 04/28/2026 | B8: 4403 | C8: CHK | D8: Tallac Concrete Inc | E8: Site concrete | F8: 3 | G8: 158650 | H8: 04/30/2026
A9: 04/28/2026 | B9: 4404 | C9: CHK | D9: R Nakamura Framing Inc | E9: Rough carpentry | F9: 3 | G9: 164730 | H9: 05/04/2026
A10: 04/28/2026 | B10: 4405 | C10: CHK | D10: Fenwick Roofing Inc | E10: Roofing | F10: 3 | G10: 95410 | H10: 05/01/2026
A11: 04/29/2026 | B11: 4407 | C11: CHK | D11: Kastner Mechanical Contractors Inc | E11: HVAC | F11: 3 | G11: 32110 | H11: 05/04/2026
A12: 04/29/2026 | B12: 4409 | C12: CHK | D12: Petrakis Plumbing Inc | E12: Plumbing | F12: 3 | G12: 48830 | H12: 05/05/2026
A13: 05/29/2026 | B13: 4418 | C13: CHK | D13: Ostrowski Electric Inc | E13: Electrical | F13: 4 | G13: 98325 | H13: 06/03/2026
A14: 05/29/2026 | B14: 4419 | C14: CHK | D14: R Nakamura Framing Inc | E14: Rough carpentry | F14: 4 | G14: 194370 | H14: 06/02/2026
A15: 05/29/2026 | B15: 4420 | C15: CHK | D15: Kastner Mechanical Contractors Inc | E15: HVAC | F15: 4 | G15: 97565 | H15: 06/03/2026
... A36: 07/30/2026 | B36: 4456 | C36: CHK | D36: Calder Drywall and Plaster LLC | E36: Drywall and plaster | F36: 6 | G36: 100515 | H36: 08/04/2026
A37: 08/18/2026 | B37: 4460 | C37: CHK | D37: Kastner Mechanical Contractors Inc | E37: HVAC | F37: 7 | G37: 73910
A38: 08/19/2026 | B38: 4461 | C38: CHK | D38: Ostrowski Electric Inc | E38: Electrical | F38: 7 | G38: 41230 | H38: 08/24/2026
A39: 08/19/2026 | B39: 4463 | C39: CHK | D39: Petrakis Plumbing Inc | E39: Plumbing | F39: 7 | G39: 37166 | H39: 08/25/2026
A40: 08/24/2026 | B40: 4460 | C40: STP | D40: Kastner Mechanical Contractors Inc | E40: HVAC | F40: 7 | G40: -73910
A41: 09/18/2026 | B41: 4474 | C41: CHK | D41: Kastner Mechanical Contractors Inc | E41: HVAC | F41: 7 | G41: 73910 | H41: 09/23/2026
A42: 09/30/2026 | B42: 4479 | C42: CHK | D42: Ostrowski Electric Inc | E42: Electrical | F42: 8 | G42: 27227

Sheet Notices
A1: Preliminary notice by claimant: whether one was owed, when it was given, what it covers, and whether the owner was given it
A3: CLAIMANT | B3: CONTRACTED_WITH | C3: CLASS | D3: FIRST_FURNISHED | E3: FIRST_SERIAL | F3: NOTICE_GIVEN | G3: NOTICE_SERIAL | H3: DAYS_TO_NOTICE | I3: GIVEN_TO_OWNER | J3: NOTICE_OWED | K3: TIMELY_NOTICE | L3: COVERAGE_FROM | M3: COVERAGE_SERIAL | N3: LIEN_RIGHTS | O3: READ_FROM
A4: Tallac Concrete, Inc. | B4: Dunmore-Kettle Builders, Inc. | C4: Other claimant | D4: 02/02/2026 | E4: =DATE(VALUE(RIGHT(D4,4)),VALUE(LEFT(D4,2)),VALUE(MID(D4,4,2))) -> 46055 | F4: 02/09/2026 | G4: =IF(F4="","",DATE(VALUE(RIGHT(F4,4)),VALUE(LEFT(F4,2)),VALUE(MID(F4,4,2)))) -> 46062 | H4: =IF(F4="","",G4-E4) -> 7 | I4: Yes, owner log entry mailed 02/09/2026 | J4: =IF(C4="Direct contractor","No","Yes") -> Yes | K4: =IF(J4="No","Not owed",IF(F4="","No notice",IF(H4<=Parameters!$B$13,"Yes","No"))) -> Yes | L4: =TEXT(M4,"mm/dd/yyyy") -> 02/02/2026 | M4: =IF(OR(J4="No",F4="",K4="Yes"),E4,G4-Parameters!$B$14) -> 46055 | N4: =IF(J4="No","Yes",IF(LEFT(I4,3)="Yes","Yes","No")) -> Yes | O4: Claim 1 item 7; Prelim Log row for Tallac Concrete
A5: Foothill Ready Mix, Inc. | B5: Tallac Concrete, Inc. | C5: Other claimant | D5: 02/05/2026 | E5: =DATE(VALUE(RIGHT(D5,4)),VALUE(LEFT(D5,2)),VALUE(MID(D5,4,2))) -> 46058 | F5: 02/11/2026 | G5: =IF(F5="","",DATE(VALUE(RIGHT(F5,4)),VALUE(LEFT(F5,2)),VALUE(MID(F5,4,2)))) -> 46064 | H5: =IF(F5="","",G5-E5) -> 6 | I5: Yes, owner log entry mailed 02/11/2026 | J5: =IF(C5="Direct contractor","No","Yes") -> Yes | K5: =IF(J5="No","Not owed",IF(F5="","No notice",IF(H5<=Parameters!$B$13,"Yes","No"))) -> Yes | L5: =TEXT(M5,"mm/dd/yyyy") -> 02/05/2026 | M5: =IF(OR(J5="No",F5="",K5="Yes"),E5,G5-Parameters!$B$14) -> 46058 | N5: =IF(J5="No","Yes",IF(LEFT(I5,3)="Yes","Yes","No")) -> Yes | O5: Claim 2 item 7; Prelim Log row for Foothill Ready Mix
A6: Norcal Rebar & Mesh, LLC | B6: Tallac Concrete, Inc. | C6: Other claimant | D6: 02/03/2026 | E6: =DATE(VALUE(RIGHT(D6,4)),VALUE(LEFT(D6,2)),VALUE(MID(D6,4,2))) -> 46056 | F6: 02/17/2026 | G6: =IF(F6="","",DATE(VALUE(RIGHT(F6,4)),VALUE(LEFT(F6,2)),VALUE(MID(F6,4,2)))) -> 46070 | H6: =IF(F6="","",G6-E6) -> 14 | I6: No, Exhibit A names Dunmore-Kettle and Tallac, and the owner log has no entry | J6: =IF(C6="Direct contractor","No","Yes") -> Yes | K6: =IF(J6="No","Not owed",IF(F6="","No notice",IF(H6<=Parameters!$B$13,"Yes","No"))) -> Yes | L6: =TEXT(M6,"mm/dd/yyyy") -> 02/03/2026 | M6: =IF(OR(J6="No",F6="",K6="Yes"),E6,G6-Parameters!$B$14) -> 46056 | N6: =IF(J6="No","Yes",IF(LEFT(I6,3)="Yes","Yes","No")) -> No | O6: Claim 3 item 7 and Exhibit A; Prelim Log, no entry
A7: Hedrick & Sons Building Supply | B7: R. Nakamura Framing, Inc. | C7: Other claimant | D7: 04/06/2026 | E7: =DATE(VALUE(RIGHT(D7,4)),VALUE(LEFT(D7,2)),VALUE(MID(D7,4,2))) -> 46118 | F7: 05/29/2026 | G7: =IF(F7="","",DATE(VALUE(RIGHT(F7,4)),VALUE(LEFT(F7,2)),VALUE(MID(F7,4,2)))) -> 46171 | H7: =IF(F7="","",G7-E7) -> 53 | I7: Yes, owner log entry mailed 05/29/2026 | J7: =IF(C7="Direct contractor","No","Yes") -> Yes | K7: =IF(J7="No","Not owed",IF(F7="","No notice",IF(H7<=Parameters!$B$13,"Yes","No"))) -> No | L7: =TEXT(M7,"mm/dd/yyyy") -> 05/09/2026 | M7: =IF(OR(J7="No",F7="",K7="Yes"),E7,G7-Parameters!$B$14) -> 46151 | N7: =IF(J7="No","Yes",IF(LEFT(I7,3)="Yes","Yes","No")) -> Yes | O7: Claim 4 item 7 and Exhibit A, first delivery 04/06/2026; Prelim Log DATE_MAILED
A8: Abrego Glass & Glazing | B8: Dunmore-Kettle Builders, Inc. | C8: Other claimant | D8: 04/27/2026 | E8: =DATE(VALUE(RIGHT(D8,4)),VALUE(LEFT(D8,2)),VALUE(MID(D8,4,2))) -> 46139 | F8: 05/04/2026 | G8: =IF(F8="","",DATE(VALUE(RIGHT(F8,4)),VALUE(LEFT(F8,2)),VALUE(MID(F8,4,2)))) -> 46146 | H8: =IF(F8="","",G8-E8) -> 7 | I8: Yes, owner log entry mailed 05/04/2026 | J8: =IF(C8="Direct contractor","No","Yes") -> Yes | K8: =IF(J8="No","Not owed",IF(F8="","No notice",IF(H8<=Parameters!$B$13,"Yes","No"))) -> Yes | L8: =TEXT(M8,"mm/dd/yyyy") -> 04/27/2026 | M8: =IF(OR(J8="No",F8="",K8="Yes"),E8,G8-Parameters!$B$14) -> 46139 | N8: =IF(J8="No","Yes",IF(LEFT(I8,3)="Yes","Yes","No")) -> Yes | O8: Claim 5 item 7; Prelim Log row for Abrego Glass & Glazing
A9: Kastner Mechanical Contractors, Inc. | B9: Dunmore-Kettle Builders, Inc. | C9: Other claimant | D9: 03/16/2026 | E9: =DATE(VALUE(RIGHT(D9,4)),VALUE(LEFT(D9,2)),VALUE(MID(D9,4,2))) -> 46097 | F9: 03/20/2026 | G9: =IF(F9="","",DATE(VALUE(RIGHT(F9,4)),VALUE(LEFT(F9,2)),VALUE(MID(F9,4,2)))) -> 46101 | H9: =IF(F9="","",G9-E9) -> 4 | I9: Yes, owner log entry mailed 03/20/2026 | J9: =IF(C9="Direct contractor","No","Yes") -> Yes | K9: =IF(J9="No","Not owed",IF(F9="","No notice",IF(H9<=Parameters!$B$13,"Yes","No"))) -> Yes | L9: =TEXT(M9,"mm/dd/yyyy") -> 03/16/2026 | M9: =IF(OR(J9="No",F9="",K9="Yes"),E9,G9-Parameters!$B$14) -> 46097 | N9: =IF(J9="No","Yes",IF(LEFT(I9,3)="Yes","Yes","No")) -> Yes | O9: Claim 6 item 7; Prelim Log row for Kastner Mechanical Contractors
A10: Bautista Painting Co. | B10: Dunmore-Kettle Builders, Inc. | C10: Other claimant | D10: 05/18/2026 | E10: =DATE(VALUE(RIGHT(D10,4)),VALUE(LEFT(D10,2)),VALUE(MID(D10,4,2))) -> 46160 | F10: 05/27/2026 | G10: =IF(F10="","",DATE(VALUE(RIGHT(F10,4)),VALUE(LEFT(F10,2)),VALUE(MID(F10,4,2)))) -> 46169 | H10: =IF(F10="","",G10-E10) -> 9 | I10: Yes, owner log entry mailed 05/27/2026 | J10: =IF(C10="Direct contractor","No","Yes") -> Yes | K10: =IF(J10="No","Not owed",IF(F10="","No notice",IF(H10<=Parameters!$B$13,"Yes","No"))) -> Yes | L10: =TEXT(M10,"mm/dd/yyyy") -> 05/18/2026 | M10: =IF(OR(J10="No",F10="",K10="Yes"),E10,G10-Parameters!$B$14) -> 46160 | N10: =IF(J10="No","Yes",IF(LEFT(I10,3)="Yes","Yes","No")) -> Yes | O10: Claim 7 item 7; Prelim Log row for Bautista Painting Co.
A11: Fenwick Roofing, Inc. | B11: Dunmore-Kettle Builders, Inc. | C11: Other claimant | D11: 03/09/2026 | E11: =DATE(VALUE(RIGHT(D11,4)),VALUE(LEFT(D11,2)),VALUE(MID(D11,4,2))) -> 46090 | F11: 03/12/2026 | G11: =IF(F11="","",DATE(VALUE(RIGHT(F11,4)),VALUE(LEFT(F11,2)),VALUE(MID(F11,4,2)))) -> 46093 | H11: =IF(F11="","",G11-E11) -> 3 | I11: Yes, owner log entry mailed 03/12/2026 | J11: =IF(C11="Direct contractor","No","Yes") -> Yes | K11: =IF(J11="No","Not owed",IF(F11="","No notice",IF(H11<=Parameters!$B$13,"Yes","No"))) -> Yes | L11: =TEXT(M11,"mm/dd/yyyy") -> 03/09/2026 | M11: =IF(OR(J11="No",F11="",K11="Yes"),E11,G11-Parameters!$B$14) -> 46090 | N11: =IF(J11="No","Yes",IF(LEFT(I11,3)="Yes","Yes","No")) -> Yes | O11: Claim 8 item 7; Prelim Log row for Fenwick Roofing
A12: Lindqvist Fire Protection | B12: Dunmore-Kettle Builders, Inc. | C12: Other claimant | D12: 03/02/2026 | E12: =DATE(VALUE(RIGHT(D12,4)),VALUE(LEFT(D12,2)),VALUE(MID(D12,4,2))) -> 46083 | F12: 03/09/2026 | G12: =IF(F12="","",DATE(VALUE(RIGHT(F12,4)),VALUE(LEFT(F12,2)),VALUE(MID(F12,4,2)))) -> 46090 | H12: =IF(F12="","",G12-E12) -> 7 | I12: Yes, owner log entry mailed 03/09/2026 | J12: =IF(C12="Direct contractor","No","Yes") -> Yes | K12: =IF(J12="No","Not owed",IF(F12="","No notice",IF(H12<=Parameters!$B$13,"Yes","No"))) -> Yes | L12: =TEXT(M12,"mm/dd/yyyy") -> 03/02/2026 | M12: =IF(OR(J12="No",F12="",K12="Yes"),E12,G12-Parameters!$B$14) -> 46083 | N12: =IF(J12="No","Yes",IF(LEFT(I12,3)="Yes","Yes","No")) -> Yes | O12: Claim 9 item 7; Prelim Log row for Lindqvist Fire Protection
A13: Sierra Pipe & Supply, Inc. | B13: Petrakis Plumbing, Inc. | C13: Other claimant | D13: 02/23/2026 | E13: =DATE(VALUE(RIGHT(D13,4)),VALUE(LEFT(D13,2)),VALUE(MID(D13,4,2))) -> 46076 | F13: 03/16/2026 | G13: =IF(F13="","",DATE(VALUE(RIGHT(F13,4)),VALUE(LEFT(F13,2)),VALUE(MID(F13,4,2)))) -> 46097 | H13: =IF(F13="","",G13-E13) -> 21 | I13: Yes, owner log entry mailed 03/16/2026 | J13: =IF(C13="Direct contractor","No","Yes") -> Yes | K13: =IF(J13="No","Not owed",IF(F13="","No notice",IF(H13<=Parameters!$B$13,"Yes","No"))) -> No | L13: =TEXT(M13,"mm/dd/yyyy") -> 02/24/2026 | M13: =IF(OR(J13="No",F13="",K13="Yes"),E13,G13-Parameters!$B$14) -> 46077 | N13: =IF(J13="No","Yes",IF(LEFT(I13,3)="Yes","Yes","No")) -> Yes | O13: Claim 10 Exhibit A, ticket R-51022 delivered 02/23/2026; Prelim Log DATE_MAILED
A14: Ostrowski Electric, Inc. | B14: Dunmore-Kettle Builders, Inc. | C14: Other claimant | D14: 01/19/2026 | E14: =DATE(VALUE(RIGHT(D14,4)),VALUE(LEFT(D14,2)),VALUE(MID(D14,4,2))) -> 46041 | F14: 01/30/2026 | G14: =IF(F14="","",DATE(VALUE(RIGHT(F14,4)),VALUE(LEFT(F14,2)),VALUE(MID(F14,4,2)))) -> 46052 | H14: =IF(F14="","",G14-E14) -> 11 | I14: Yes, owner log entry mailed 01/30/2026 | J14: =IF(C14="Direct contractor","No","Yes") -> Yes | K14: =IF(J14="No","Not owed",IF(F14="","No notice",IF(H14<=Parameters!$B$13,"Yes","No"))) -> Yes | L14: =TEXT(M14,"mm/dd/yyyy") -> 01/19/2026 | M14: =IF(OR(J14="No",F14="",K14="Yes"),E14,G14-Parameters!$B$14) -> 46041 | N14: =IF(J14="No","Yes",IF(LEFT(I14,3)="Yes","Yes","No")) -> Yes | O14: Claim 11 item 7; Prelim Log row for Ostrowski Electric
A15: Calder Drywall & Plaster, LLC | B15: Dunmore-Kettle Builders, Inc. | C15: Other claimant | D15: 04/20/2026 | E15: =DATE(VALUE(RIGHT(D15,4)),VALUE(LEFT(D15,2)),VALUE(MID(D15,4,2))) -> 46132 | F15: 04/24/2026 | G15: =IF(F15="","",DATE(VALUE(RIGHT(F15,4)),VALUE(LEFT(F15,2)),VALUE(MID(F15,4,2)))) -> 46136 | H15: =IF(F15="","",G15-E15) -> 4 | I15: Yes, owner log entry mailed 04/24/2026 | J15: =IF(C15="Direct contractor","No","Yes") -> Yes | K15: =IF(J15="No","Not owed",IF(F15="","No notice",IF(H15<=Parameters!$B$13,"Yes","No"))) -> Yes | L15: =TEXT(M15,"mm/dd/yyyy") -> 04/20/2026 | M15: =IF(OR(J15="No",F15="",K15="Yes"),E15,G15-Parameters!$B$14) -> 46132 | N15: =IF(J15="No","Yes",IF(LEFT(I15,3)="Yes","Yes","No")) -> Yes | O15: Claim 12 item 7; Prelim Log row for Calder Drywall & Plaster
A16: Petrakis Plumbing, Inc. | B16: Dunmore-Kettle Builders, Inc. | C16: Other claimant | D16: 02/09/2026 | E16: =DATE(VALUE(RIGHT(D16,4)),VALUE(LEFT(D16,2)),VALUE(MID(D16,4,2))) -> 46062 | F16: 02/12/2026 | G16: =IF(F16="","",DATE(VALUE(RIGHT(F16,4)),VALUE(LEFT(F16,2)),VALUE(MID(F16,4,2)))) -> 46065 | H16: =IF(F16="","",G16-E16) -> 3 | I16: Yes, owner log entry mailed 02/12/2026 | J16: =IF(C16="Direct contractor","No","Yes") -> Yes | K16: =IF(J16="No","Not owed",IF(F16="","No notice",IF(H16<=Parameters!$B$13,"Yes","No"))) -> Yes | L16: =TEXT(M16,"mm/dd/yyyy") -> 02/09/2026 | M16: =IF(OR(J16="No",F16="",K16="Yes"),E16,G16-Parameters!$B$14) -> 46062 | N16: =IF(J16="No","Yes",IF(LEFT(I16,3)="Yes","Yes","No")) -> Yes | O16: Claim 13 item 7; Prelim Log row for Petrakis Plumbing
A17: Sorensen Landscape Co. | B17: Piedmont Ridge Properties, LLC | C17: Direct contractor | D17: 06/08/2026 | E17: =DATE(VALUE(RIGHT(D17,4)),VALUE(LEFT(D17,2)),VALUE(MID(D17,4,2))) -> 46181 | G17: =IF(F17="","",DATE(VALUE(RIGHT(F17,4)),VALUE(LEFT(F17,2)),VALUE(MID(F17,4,2)))) | H17: =IF(F17="","",G17-E17) | I17: None given and none owed, the claimant contracted with the owner itself | J17: =IF(C17="Direct contractor","No","Yes") -> No | K17: =IF(J17="No","Not owed",IF(F17="","No notice",IF(H17<=Parameters!$B$13,"Yes","No"))) -> Not owed | L17: =TEXT(M17,"mm/dd/yyyy") -> 06/08/2026 | M17: =IF(OR(J17="No",F17="",K17="Yes"),E17,G17-Parameters!$B$14) -> 46181 | N17: =IF(J17="No","Yes",IF(LEFT(I17,3)="Yes","Yes","No")) -> Yes | O17: Claim 14 items 5, 7 and 8; Owner Payments tab, the owner's own agreements
A18: Capitol Wire & Lighting, Inc. | B18: Ostrowski Electric, Inc. | C18: Other claimant | D18: 01/27/2026 | E18: =DATE(VALUE(RIGHT(D18,4)),VALUE(LEFT(D18,2)),VALUE(MID(D18,4,2))) -> 46049 | F18: 02/16/2026 | G18: =IF(F18="","",DATE(VALUE(RIGHT(F18,4)),VALUE(LEFT(F18,2)),VALUE(MID(F18,4,2)))) -> 46069 | H18: =IF(F18="","",G18-E18) -> 20 | I18: Yes, owner log entry mailed 02/16/2026 | J18: =IF(C18="Direct contractor","No","Yes") -> Yes | K18: =IF(J18="No","Not owed",IF(F18="","No notice",IF(H18<=Parameters!$B$13,"Yes","No"))) -> Yes | L18: =TEXT(M18,"mm/dd/yyyy") -> 01/27/2026 | M18: =IF(OR(J18="No",F18="",K18="Yes"),E18,G18-Parameters!$B$14) -> 46049 | N18: =IF(J18="No","Yes",IF(LEFT(I18,3)="Yes","Yes","No")) -> Yes | O18: Claim 15 Exhibit A, ticket D-30117 delivered 01/27/2026; Prelim Log DATE_MAILED
A20: Notice given is the date of deposit (section 8116), read from DATE_MAILED on the owner's log or from the exhibit to the claim, never from the date typed on the notice, the date received, or the recital in the claim. First furnishing is read from the claim and the statement of account attached to it, never from the preliminary notice form. A late notice covers work furnished from the twentieth day before it was given, the day of giving not counted. A direct contractor owes no preliminary notice on a job with no construction lender (section 8200(e)).

Sheet NOC Copies
A1: Copy of the notice of completion by person: who was entitled to one, when it was mailed, and the last day to record that follows
A3: PERSON | B3: CLASS | C3: ENTITLED_TO_COPY | D3: ADDRESSEE_ON_MAIL_LOG | E3: COPY_MAILED | F3: MAILED_SERIAL | G3: GIVEN_IN_TIME | H3: NOTICE_SHORTENS_TIME | I3: LAST_DAY_TO_RECORD | J3: LAST_DAY_SERIAL | K3: READ_FROM
A4: Tallac Concrete, Inc. | B4: =Notices!C4 -> Other claimant | C4: =IF(OR(Notices!C4="Direct contractor",LEFT(Notices!I4,3)="Yes"),"Yes","No") -> Yes | D4: Tallac Concrete Inc | E4: 08/31/2026 | F4: =IF(E4="","",DATE(VALUE(RIGHT(E4,4)),VALUE(LEFT(E4,2)),VALUE(MID(E4,4,2)))) -> 46265 | G4: =IF(C4="No","Not entitled",IF(E4="","No",IF(F4<=Parameters!$C$38,"Yes","No"))) -> Yes | H4: =IF(G4="No","No","Yes") -> Yes | I4: =TEXT(J4,"mm/dd/yyyy") -> 09/28/2026 | J4: =IF(H4="No",Parameters!$C$43,IF(B4="Direct contractor",Parameters!$C$42,Parameters!$C$41)) -> 46293 | K4: Certified Mail tab, Tallac Concrete Inc, mailed 08/31/2026
A5: Foothill Ready Mix, Inc. | B5: =Notices!C5 -> Other claimant | C5: =IF(OR(Notices!C5="Direct contractor",LEFT(Notices!I5,3)="Yes"),"Yes","No") -> Yes | D5: Foothill Ready Mix | E5: 08/31/2026 | F5: =IF(E5="","",DATE(VALUE(RIGHT(E5,4)),VALUE(LEFT(E5,2)),VALUE(MID(E5,4,2)))) -> 46265 | G5: =IF(C5="No","Not entitled",IF(E5="","No",IF(F5<=Parameters!$C$38,"Yes","No"))) -> Yes | H5: =IF(G5="No","No","Yes") -> Yes | I5: =TEXT(J5,"mm/dd/yyyy") -> 09/28/2026 | J5: =IF(H5="No",Parameters!$C$43,IF(B5="Direct contractor",Parameters!$C$42,Parameters!$C$41)) -> 46293 | K5: Certified Mail tab, Foothill Ready Mix, mailed 08/31/2026
A6: Norcal Rebar & Mesh, LLC | B6: =Notices!C6 -> Other claimant | C6: =IF(OR(Notices!C6="Direct contractor",LEFT(Notices!I6,3)="Yes"),"Yes","No") -> No | D6: Not on the log | F6: =IF(E6="","",DATE(VALUE(RIGHT(E6,4)),VALUE(LEFT(E6,2)),VALUE(MID(E6,4,2)))) | G6: =IF(C6="No","Not entitled",IF(E6="","No",IF(F6<=Parameters!$C$38,"Yes","No"))) -> Not entitled | H6: =IF(G6="No","No","Yes") -> Yes | I6: =TEXT(J6,"mm/dd/yyyy") -> 09/28/2026 | J6: =IF(H6="No",Parameters!$C$43,IF(B6="Direct contractor",Parameters!$C$42,Parameters!$C$41)) -> 46293 | K6: Certified Mail tab, no entry; no preliminary notice to the owner, so no copy was owed
A7: Hedrick & Sons Building Supply | B7: =Notices!C7 -> Other claimant | C7: =IF(OR(Notices!C7="Direct contractor",LEFT(Notices!I7,3)="Yes"),"Yes","No") -> Yes | D7: Hedrick and Sons Bldg Supply | E7: 09/08/2026 | F7: =IF(E7="","",DATE(VALUE(RIGHT(E7,4)),VALUE(LEFT(E7,2)),VALUE(MID(E7,4,2)))) -> 46273 | G7: =IF(C7="No","Not entitled",IF(E7="","No",IF(F7<=Parameters!$C$38,"Yes","No"))) -> Yes | H7: =IF(G7="No","No","Yes") -> Yes | I7: =TEXT(J7,"mm/dd/yyyy") -> 09/28/2026 | J7: =IF(H7="No",Parameters!$C$43,IF(B7="Direct contractor",Parameters!$C$42,Parameters!$C$41)) -> 46293 | K7: Certified Mail tab, Hedrick and Sons Bldg Supply, mailed 09/08/2026
A8: Abrego Glass & Glazing | B8: =Notices!C8 -> Other claimant | C8: =IF(OR(Notices!C8="Direct contractor",LEFT(Notices!I8,3)="Yes"),"Yes","No") -> Yes | D8: Abrego Glass and Glazing | E8: 08/31/2026 | F8: =IF(E8="","",DATE(VALUE(RIGHT(E8,4)),VALUE(LEFT(E8,2)),VALUE(MID(E8,4,2)))) -> 46265 | G8: =IF(C8="No","Not entitled",IF(E8="","No",IF(F8<=Parameters!$C$38,"Yes","No"))) -> Yes | H8: =IF(G8="No","No","Yes") -> Yes | I8: =TEXT(J8,"mm/dd/yyyy") -> 09/28/2026 | J8: =IF(H8="No",Parameters!$C$43,IF(B8="Direct contractor",Parameters!$C$42,Parameters!$C$41)) -> 46293 | K8: Certified Mail tab, Abrego Glass and Glazing, mailed 08/31/2026
A9: Kastner Mechanical Contractors, Inc. | B9: =Notices!C9 -> Other claimant | C9: =IF(OR(Notices!C9="Direct contractor",LEFT(Notices!I9,3)="Yes"),"Yes","No") -> Yes | D9: Kastner Mechanical | E9: 08/31/2026 | F9: =IF(E9="","",DATE(VALUE(RIGHT(E9,4)),VALUE(LEFT(E9,2)),VALUE(MID(E9,4,2)))) -> 46265 | G9: =IF(C9="No","Not entitled",IF(E9="","No",IF(F9<=Parameters!$C$38,"Yes","No"))) -> Yes | H9: =IF(G9="No","No","Yes") -> Yes | I9: =TEXT(J9,"mm/dd/yyyy") -> 09/28/2026 | J9: =IF(H9="No",Parameters!$C$43,IF(B9="Direct contractor",Parameters!$C$42,Parameters!$C$41)) -> 46293 | K9: Certified Mail tab, Kastner Mechanical, mailed 08/31/2026
A10: Bautista Painting Co. | B10: =Notices!C10 -> Other claimant | C10: =IF(OR(Notices!C10="Direct contractor",LEFT(Notices!I10,3)="Yes"),"Yes","No") -> Yes | D10: Bautista Painting | E10: 09/08/2026 | F10: =IF(E10="","",DATE(VALUE(RIGHT(E10,4)),VALUE(LEFT(E10,2)),VALUE(MID(E10,4,2)))) -> 46273 | G10: =IF(C10="No","Not entitled",IF(E10="","No",IF(F10<=Parameters!$C$38,"Yes","No"))) -> Yes | H10: =IF(G10="No","No","Yes") -> Yes | I10: =TEXT(J10,"mm/dd/yyyy") -> 09/28/2026 | J10: =IF(H10="No",Parameters!$C$43,IF(B10="Direct contractor",Parameters!$C$42,Parameters!$C$41)) -> 46293 | K10: Certified Mail tab, Bautista Painting, mailed 09/08/2026
A11: Fenwick Roofing, Inc. | B11: =Notices!C11 -> Other claimant | C11: =IF(OR(Notices!C11="Direct contractor",LEFT(Notices!I11,3)="Yes"),"Yes","No") -> Yes | D11: Fenwick Roofing Inc | E11: 08/31/2026 | F11: =IF(E11="","",DATE(VALUE(RIGHT(E11,4)),VALUE(LEFT(E11,2)),VALUE(MID(E11,4,2)))) -> 46265 | G11: =IF(C11="No","Not entitled",IF(E11="","No",IF(F11<=Parameters!$C$38,"Yes","No"))) -> Yes | H11: =IF(G11="No","No","Yes") -> Yes | I11: =TEXT(J11,"mm/dd/yyyy") -> 09/28/2026 | J11: =IF(H11="No",Parameters!$C$43,IF(B11="Direct contractor",Parameters!$C$42,Parameters!$C$41)) -> 46293 | K11: Certified Mail tab, Fenwick Roofing Inc, mailed 08/31/2026
A12: Lindqvist Fire Protection | B12: =Notices!C12 -> Other claimant | C12: =IF(OR(Notices!C12="Direct contractor",LEFT(Notices!I12,3)="Yes"),"Yes","No") -> Yes | D12: Lindqvist Fire Protection | E12: 08/31/2026 | F12: =IF(E12="","",DATE(VALUE(RIGHT(E12,4)),VALUE(LEFT(E12,2)),VALUE(MID(E12,4,2)))) -> 46265 | G12: =IF(C12="No","Not entitled",IF(E12="","No",IF(F12<=Parameters!$C$38,"Yes","No"))) -> Yes | H12: =IF(G12="No","No","Yes") -> Yes | I12: =TEXT(J12,"mm/dd/yyyy") -> 09/28/2026 | J12: =IF(H12="No",Parameters!$C$43,IF(B12="Direct contractor",Parameters!$C$42,Parameters!$C$41)) -> 46293 | K12: Certified Mail tab, Lindqvist Fire Protection, mailed 08/31/2026
A13: Sierra Pipe & Supply, Inc. | B13: =Notices!C13 -> Other claimant | C13: =IF(OR(Notices!C13="Direct contractor",LEFT(Notices!I13,3)="Yes"),"Yes","No") -> Yes | D13: Sierra Pipe and Supply | E13: 09/08/2026 | F13: =IF(E13="","",DATE(VALUE(RIGHT(E13,4)),VALUE(LEFT(E13,2)),VALUE(MID(E13,4,2)))) -> 46273 | G13: =IF(C13="No","Not entitled",IF(E13="","No",IF(F13<=Parameters!$C$38,"Yes","No"))) -> Yes | H13: =IF(G13="No","No","Yes") -> Yes | I13: =TEXT(J13,"mm/dd/yyyy") -> 09/28/2026 | J13: =IF(H13="No",Parameters!$C$43,IF(B13="Direct contractor",Parameters!$C$42,Parameters!$C$41)) -> 46293 | K13: Certified Mail tab, Sierra Pipe and Supply, mailed 09/08/2026
A14: Ostrowski Electric, Inc. | B14: =Notices!C14 -> Other claimant | C14: =IF(OR(Notices!C14="Direct contractor",LEFT(Notices!I14,3)="Yes"),"Yes","No") -> Yes | D14: Ostrowski Electric Inc | E14: 08/31/2026 | F14: =IF(E14="","",DATE(VALUE(RIGHT(E14,4)),VALUE(LEFT(E14,2)),VALUE(MID(E14,4,2)))) -> 46265 | G14: =IF(C14="No","Not entitled",IF(E14="","No",IF(F14<=Parameters!$C$38,"Yes","No"))) -> Yes | H14: =IF(G14="No","No","Yes") -> Yes | I14: =TEXT(J14,"mm/dd/yyyy") -> 09/28/2026 | J14: =IF(H14="No",Parameters!$C$43,IF(B14="Direct contractor",Parameters!$C$42,Parameters!$C$41)) -> 46293 | K14: Certified Mail tab, Ostrowski Electric Inc, mailed 08/31/2026
A15: Calder Drywall & Plaster, LLC | B15: =Notices!C15 -> Other claimant | C15: =IF(OR(Notices!C15="Direct contractor",LEFT(Notices!I15,3)="Yes"),"Yes","No") -> Yes | D15: Not on the log | F15: =IF(E15="","",DATE(VALUE(RIGHT(E15,4)),VALUE(LEFT(E15,2)),VALUE(MID(E15,4,2)))) | G15: =IF(C15="No","Not entitled",IF(E15="","No",IF(F15<=Parameters!$C$38,"Yes","No"))) -> No | H15: =IF(G15="No","No","Yes") -> No | I15: =TEXT(J15,"mm/dd/yyyy") -> 11/09/2026 | J15: =IF(H15="No",Parameters!$C$43,IF(B15="Direct contractor",Parameters!$C$42,Parameters!$C$41)) -> 46335 | K15: Certified Mail tab, no entry for Calder Drywall & Plaster; the 08/31/2026 entry is Calder Bros Masonry of Penryn
A16: Petrakis Plumbing, Inc. | B16: =Notices!C16 -> Other claimant | C16: =IF(OR(Notices!C16="Direct contractor",LEFT(Notices!I16,3)="Yes"),"Yes","No") -> Yes | D16: Petrakis Plumbing | E16: 09/08/2026 | F16: =IF(E16="","",DATE(VALUE(RIGHT(E16,4)),VALUE(LEFT(E16,2)),VALUE(MID(E16,4,2)))) -> 46273 | G16: =IF(C16="No","Not entitled",IF(E16="","No",IF(F16<=Parameters!$C$38,"Yes","No"))) -> Yes | H16: =IF(G16="No","No","Yes") -> Yes | I16: =TEXT(J16,"mm/dd/yyyy") -> 09/28/2026 | J16: =IF(H16="No",Parameters!$C$43,IF(B16="Direct contractor",Parameters!$C$42,Parameters!$C$41)) -> 46293 | K16: Certified Mail tab, Petrakis Plumbing, mailed 09/08/2026
A17: Sorensen Landscape Co. | B17: =Notices!C17 -> Direct contractor | C17: =IF(OR(Notices!C17="Direct contractor",LEFT(Notices!I17,3)="Yes"),"Yes","No") -> Yes | D17: Not on the log | F17: =IF(E17="","",DATE(VALUE(RIGHT(E17,4)),VALUE(LEFT(E17,2)),VALUE(MID(E17,4,2)))) | G17: =IF(C17="No","Not entitled",IF(E17="","No",IF(F17<=Parameters!$C$38,"Yes","No"))) -> No | H17: =IF(G17="No","No","Yes") -> No | I17: =TEXT(J17,"mm/dd/yyyy") -> 11/09/2026 | J17: =IF(H17="No",Parameters!$C$43,IF(B17="Direct contractor",Parameters!$C$42,Parameters!$C$41)) -> 46335 | K17: Certified Mail tab, no entry; memorandum of September 10, 2026
A18: Capitol Wire & Lighting, Inc. | B18: =Notices!C18 -> Other claimant | C18: =IF(OR(Notices!C18="Direct contractor",LEFT(Notices!I18,3)="Yes"),"Yes","No") -> Yes | D18: Capitol Wire and Lighting | E18: 09/09/2026 | F18: =IF(E18="","",DATE(VALUE(RIGHT(E18,4)),VALUE(LEFT(E18,2)),VALUE(MID(E18,4,2)))) -> 46274 | G18: =IF(C18="No","Not entitled",IF(E18="","No",IF(F18<=Parameters!$C$38,"Yes","No"))) -> No | H18: =IF(G18="No","No","Yes") -> No | I18: =TEXT(J18,"mm/dd/yyyy") -> 11/09/2026 | J18: =IF(H18="No",Parameters!$C$43,IF(B18="Direct contractor",Parameters!$C$42,Parameters!$C$41)) -> 46335 | K18: Certified Mail tab, Capitol Wire and Lighting, mailed 09/09/2026
A20: The direct contractor on the notice of completion, which has not recorded a claim
A21: PERSON | B21: CLASS | C21: ENTITLED_TO_COPY | D21: ADDRESSEE_ON_MAIL_LOG | E21: COPY_MAILED | F21: MAILED_SERIAL | G21: GIVEN_IN_TIME | H21: NOTICE_SHORTENS_TIME | I21: LAST_DAY_TO_RECORD | J21: LAST_DAY_SERIAL | K21: READ_FROM
A22: Dunmore-Kettle Builders, Inc. | B22: Direct contractor | C22: Yes | D22: Dunmore-Kettle Builders | E22: 09/09/2026 | F22: =IF(E22="","",DATE(VALUE(RIGHT(E22,4)),VALUE(LEFT(E22,2)),VALUE(MID(E22,4,2)))) -> 46274 | G22: =IF(C22="No","Not entitled",IF(E22="","No",IF(F22<=Parameters!$C$38,"Yes","No"))) -> No | H22: =IF(G22="No","No","Yes") -> No | I22: =TEXT(J22,"mm/dd/yyyy") -> 11/09/2026 | J22: =IF(H22="No",Parameters!$C$43,IF(B22="Direct contractor",Parameters!$C$42,Parameters!$C$41)) -> 46335 | K22: Certified Mail tab, Dunmore-Kettle Builders, mailed 09/09/2026
A24: A copy is owed to the direct contractor and to every claimant that gave the owner a preliminary notice, within 10 days after the notice of completion was recorded (section 8190(a)). The tenth day was a Saturday and the Monday after it was Labor Day, so a copy deposited on Tuesday 09/08/2026 was given in time and one deposited on Wednesday 09/09/2026 was not. Where no copy was given in time, the notice of completion does not shorten that person's time, and the last day is 90 days after completion (section 8190(d)).

Sheet Deadlines
A1: Recording, service, and enforcement by claim, counted under Code of Civil Procedure sections 12, 12a and 12b
A3: CLAIMANT | B3: RECORDED | C3: RECORDED_SERIAL | D3: LAST_DAY_TO_RECORD | E3: TIMELY | F3: COPY_OF_CLAIM_MAILED_TO | G3: SERVED_ON_OWNER | H3: ACTION_DUE_BY | I3: ACTION_DUE_SERIAL | J3: ACTION_ON_INDEX | K3: EXPIRED | L3: DOC_NO
A4: Tallac Concrete, Inc. | B4: 06/26/2026 | C4: =DATE(VALUE(RIGHT(B4,4)),VALUE(LEFT(B4,2)),VALUE(MID(B4,4,2))) -> 46199 | D4: ='NOC Copies'!I4 -> 09/28/2026 | E4: =IF(C4<='NOC Copies'!J4,"Yes","No") -> Yes | F4: Owner, 3100 Douglas Boulevard, Roseville | G4: =IF(LEFT(F4,5)="Owner","Yes","No") -> Yes | H4: =TEXT(I4,"mm/dd/yyyy") -> 09/24/2026 | I4: =IF(OR(WEEKDAY(C4+Parameters!$B$15,2)>5,COUNTIF(Parameters!$C$6:$C$7,C4+Parameters!$B$15)>0),WORKDAY(C4+Parameters!$B$15,1,Parameters!$C$6:$C$7),C4+Parameters!$B$15) -> 46289 | J4: None | K4: =IF(J4<>"None","No",IF(Parameters!$C$20>I4,"Yes",IF(Parameters!$C$21>I4,"Not shown","No"))) -> Yes | L4: 2026-0060418
A5: Foothill Ready Mix, Inc. | B5: 07/06/2026 | C5: =DATE(VALUE(RIGHT(B5,4)),VALUE(LEFT(B5,2)),VALUE(MID(B5,4,2))) -> 46209 | D5: ='NOC Copies'!I5 -> 09/28/2026 | E5: =IF(C5<='NOC Copies'!J5,"Yes","No") -> Yes | F5: Owner, 3100 Douglas Boulevard, Roseville | G5: =IF(LEFT(F5,5)="Owner","Yes","No") -> Yes | H5: =TEXT(I5,"mm/dd/yyyy") -> 10/05/2026 | I5: =IF(OR(WEEKDAY(C5+Parameters!$B$15,2)>5,COUNTIF(Parameters!$C$6:$C$7,C5+Parameters!$B$15)>0),WORKDAY(C5+Parameters!$B$15,1,Parameters!$C$6:$C$7),C5+Parameters!$B$15) -> 46300 | J5: None | K5: =IF(J5<>"None","No",IF(Parameters!$C$20>I5,"Yes",IF(Parameters!$C$21>I5,"Not shown","No"))) -> Not shown | L5: 2026-0063905
A6: Norcal Rebar & Mesh, LLC | B6: 09/14/2026 | C6: =DATE(VALUE(RIGHT(B6,4)),VALUE(LEFT(B6,2)),VALUE(MID(B6,4,2))) -> 46279 | D6: ='NOC Copies'!I6 -> 09/28/2026 | E6: =IF(C6<='NOC Copies'!J6,"Yes","No") -> Yes | F6: Owner, 3100 Douglas Boulevard, Roseville | G6: =IF(LEFT(F6,5)="Owner","Yes","No") -> Yes | H6: =TEXT(I6,"mm/dd/yyyy") -> 12/14/2026 | I6: =IF(OR(WEEKDAY(C6+Parameters!$B$15,2)>5,COUNTIF(Parameters!$C$6:$C$7,C6+Parameters!$B$15)>0),WORKDAY(C6+Parameters!$B$15,1,Parameters!$C$6:$C$7),C6+Parameters!$B$15) -> 46370 | J6: None | K6: =IF(J6<>"None","No",IF(Parameters!$C$20>I6,"Yes",IF(Parameters!$C$21>I6,"Not shown","No"))) -> No | L6: 2026-0095207
A7: Hedrick & Sons Building Supply | B7: 09/16/2026 | C7: =DATE(VALUE(RIGHT(B7,4)),VALUE(LEFT(B7,2)),VALUE(MID(B7,4,2))) -> 46281 | D7: ='NOC Copies'!I7 -> 09/28/2026 | E7: =IF(C7<='NOC Copies'!J7,"Yes","No") -> Yes | F7: Owner, 3100 Douglas Boulevard, Roseville | G7: =IF(LEFT(F7,5)="Owner","Yes","No") -> Yes | H7: =TEXT(I7,"mm/dd/yyyy") -> 12/15/2026 | I7: =IF(OR(WEEKDAY(C7+Parameters!$B$15,2)>5,COUNTIF(Parameters!$C$6:$C$7,C7+Parameters!$B$15)>0),WORKDAY(C7+Parameters!$B$15,1,Parameters!$C$6:$C$7),C7+Parameters!$B$15) -> 46371 | J7: None | K7: =IF(J7<>"None","No",IF(Parameters!$C$20>I7,"Yes",IF(Parameters!$C$21>I7,"Not shown","No"))) -> No | L7: 2026-0096088
A8: Abrego Glass & Glazing | B8: 09/17/2026 | C8: =DATE(VALUE(RIGHT(B8,4)),VALUE(LEFT(B8,2)),VALUE(MID(B8,4,2))) -> 46282 | D8: ='NOC Copies'!I8 -> 09/28/2026 | E8: =IF(C8<='NOC Copies'!J8,"Yes","No") -> Yes | F8: Dunmore-Kettle Builders, 2140 Sunset Boulevard, Rocklin | G8: =IF(LEFT(F8,5)="Owner","Yes","No") -> No | H8: =TEXT(I8,"mm/dd/yyyy") -> 12/16/2026 | I8: =IF(OR(WEEKDAY(C8+Parameters!$B$15,2)>5,COUNTIF(Parameters!$C$6:$C$7,C8+Parameters!$B$15)>0),WORKDAY(C8+Parameters!$B$15,1,Parameters!$C$6:$C$7),C8+Parameters!$B$15) -> 46372 | J8: None | K8: =IF(J8<>"None","No",IF(Parameters!$C$20>I8,"Yes",IF(Parameters!$C$21>I8,"Not shown","No"))) -> No | L8: 2026-0096531
A9: Kastner Mechanical Contractors, Inc. | B9: 09/21/2026 | C9: =DATE(VALUE(RIGHT(B9,4)),VALUE(LEFT(B9,2)),VALUE(MID(B9,4,2))) -> 46286 | D9: ='NOC Copies'!I9 -> 09/28/2026 | E9: =IF(C9<='NOC Copies'!J9,"Yes","No") -> Yes | F9: Owner, 3100 Douglas Boulevard, Roseville | G9: =IF(LEFT(F9,5)="Owner","Yes","No") -> Yes | H9: =TEXT(I9,"mm/dd/yyyy") -> 12/21/2026 | I9: =IF(OR(WEEKDAY(C9+Parameters!$B$15,2)>5,COUNTIF(Parameters!$C$6:$C$7,C9+Parameters!$B$15)>0),WORKDAY(C9+Parameters!$B$15,1,Parameters!$C$6:$C$7),C9+Parameters!$B$15) -> 46377 | J9: None | K9: =IF(J9<>"None","No",IF(Parameters!$C$20>I9,"Yes",IF(Parameters!$C$21>I9,"Not shown","No"))) -> No | L9: 2026-0097644
A10: Bautista Painting Co. | B10: 09/22/2026 | C10: =DATE(VALUE(RIGHT(B10,4)),VALUE(LEFT(B10,2)),VALUE(MID(B10,4,2))) -> 46287 | D10: ='NOC Copies'!I10 -> 09/28/2026 | E10: =IF(C10<='NOC Copies'!J10,"Yes","No") -> Yes | F10: Owner, 3100 Douglas Boulevard, Roseville | G10: =IF(LEFT(F10,5)="Owner","Yes","No") -> Yes | H10: =TEXT(I10,"mm/dd/yyyy") -> 12/21/2026 | I10: =IF(OR(WEEKDAY(C10+Parameters!$B$15,2)>5,COUNTIF(Parameters!$C$6:$C$7,C10+Parameters!$B$15)>0),WORKDAY(C10+Parameters!$B$15,1,Parameters!$C$6:$C$7),C10+Parameters!$B$15) -> 46377 | J10: None | K10: =IF(J10<>"None","No",IF(Parameters!$C$20>I10,"Yes",IF(Parameters!$C$21>I10,"Not shown","No"))) -> No | L10: 2026-0098120
A11: Fenwick Roofing, Inc. | B11: 09/23/2026 | C11: =DATE(VALUE(RIGHT(B11,4)),VALUE(LEFT(B11,2)),VALUE(MID(B11,4,2))) -> 46288 | D11: ='NOC Copies'!I11 -> 09/28/2026 | E11: =IF(C11<='NOC Copies'!J11,"Yes","No") -> Yes | F11: Owner, 3100 Douglas Boulevard, Roseville | G11: =IF(LEFT(F11,5)="Owner","Yes","No") -> Yes | H11: =TEXT(I11,"mm/dd/yyyy") -> 12/22/2026 | I11: =IF(OR(WEEKDAY(C11+Parameters!$B$15,2)>5,COUNTIF(Parameters!$C$6:$C$7,C11+Parameters!$B$15)>0),WORKDAY(C11+Parameters!$B$15,1,Parameters!$C$6:$C$7),C11+Parameters!$B$15) -> 46378 | J11: None | K11: =IF(J11<>"None","No",IF(Parameters!$C$20>I11,"Yes",IF(Parameters!$C$21>I11,"Not shown","No"))) -> No | L11: 2026-0098577
A12: Lindqvist Fire Protection | B12: 09/24/2026 | C12: =DATE(VALUE(RIGHT(B12,4)),VALUE(LEFT(B12,2)),VALUE(MID(B12,4,2))) -> 46289 | D12: ='NOC Copies'!I12 -> 09/28/2026 | E12: =IF(C12<='NOC Copies'!J12,"Yes","No") -> Yes | F12: Owner, 1440 Eureka Road, Roseville, the address on building permit B25-1187 | G12: =IF(LEFT(F12,5)="Owner","Yes","No") -> Yes | H12: =TEXT(I12,"mm/dd/yyyy") -> 12/23/2026 | I12: =IF(OR(WEEKDAY(C12+Parameters!$B$15,2)>5,COUNTIF(Parameters!$C$6:$C$7,C12+Parameters!$B$15)>0),WORKDAY(C12+Parameters!$B$15,1,Parameters!$C$6:$C$7),C12+Parameters!$B$15) -> 46379 | J12: None | K12: =IF(J12<>"None","No",IF(Parameters!$C$20>I12,"Yes",IF(Parameters!$C$21>I12,"Not shown","No"))) -> No | L12: 2026-0098901
A13: Sierra Pipe & Supply, Inc. | B13: 09/24/2026 | C13: =DATE(VALUE(RIGHT(B13,4)),VALUE(LEFT(B13,2)),VALUE(MID(B13,4,2))) -> 46289 | D13: ='NOC Copies'!I13 -> 09/28/2026 | E13: =IF(C13<='NOC Copies'!J13,"Yes","No") -> Yes | F13: Owner, 3100 Douglas Boulevard, Roseville | G13: =IF(LEFT(F13,5)="Owner","Yes","No") -> Yes | H13: =TEXT(I13,"mm/dd/yyyy") -> 12/23/2026 | I13: =IF(OR(WEEKDAY(C13+Parameters!$B$15,2)>5,COUNTIF(Parameters!$C$6:$C$7,C13+Parameters!$B$15)>0),WORKDAY(C13+Parameters!$B$15,1,Parameters!$C$6:$C$7),C13+Parameters!$B$15) -> 46379 | J13: None | K13: =IF(J13<>"None","No",IF(Parameters!$C$20>I13,"Yes",IF(Parameters!$C$21>I13,"Not shown","No"))) -> No | L13: 2026-0098955
A14: Ostrowski Electric, Inc. | B14: 09/28/2026 | C14: =DATE(VALUE(RIGHT(B14,4)),VALUE(LEFT(B14,2)),VALUE(MID(B14,4,2))) -> 46293 | D14: ='NOC Copies'!I14 -> 09/28/2026 | E14: =IF(C14<='NOC Copies'!J14,"Yes","No") -> Yes | F14: Owner, 3100 Douglas Boulevard, Roseville | G14: =IF(LEFT(F14,5)="Owner","Yes","No") -> Yes | H14: =TEXT(I14,"mm/dd/yyyy") -> 12/28/2026 | I14: =IF(OR(WEEKDAY(C14+Parameters!$B$15,2)>5,COUNTIF(Parameters!$C$6:$C$7,C14+Parameters!$B$15)>0),WORKDAY(C14+Parameters!$B$15,1,Parameters!$C$6:$C$7),C14+Parameters!$B$15) -> 46384 | J14: None | K14: =IF(J14<>"None","No",IF(Parameters!$C$20>I14,"Yes",IF(Parameters!$C$21>I14,"Not shown","No"))) -> No | L14: 2026-0100263
A15: Calder Drywall & Plaster, LLC | B15: 09/29/2026 | C15: =DATE(VALUE(RIGHT(B15,4)),VALUE(LEFT(B15,2)),VALUE(MID(B15,4,2))) -> 46294 | D15: ='NOC Copies'!I15 -> 11/09/2026 | E15: =IF(C15<='NOC Copies'!J15,"Yes","No") -> Yes | F15: Owner, 3100 Douglas Boulevard, Roseville | G15: =IF(LEFT(F15,5)="Owner","Yes","No") -> Yes | H15: =TEXT(I15,"mm/dd/yyyy") -> 12/28/2026 | I15: =IF(OR(WEEKDAY(C15+Parameters!$B$15,2)>5,COUNTIF(Parameters!$C$6:$C$7,C15+Parameters!$B$15)>0),WORKDAY(C15+Parameters!$B$15,1,Parameters!$C$6:$C$7),C15+Parameters!$B$15) -> 46384 | J15: None | K15: =IF(J15<>"None","No",IF(Parameters!$C$20>I15,"Yes",IF(Parameters!$C$21>I15,"Not shown","No"))) -> No | L15: 2026-0100719
... A18: Capitol Wire & Lighting, Inc. | B18: 10/01/2026 | C18: =DATE(VALUE(RIGHT(B18,4)),VALUE(LEFT(B18,2)),VALUE(MID(B18,4,2))) -> 46296 | D18: ='NOC Copies'!I18 -> 11/09/2026 | E18: =IF(C18<='NOC Copies'!J18,"Yes","No") -> Yes | F18: Owner, 3100 Douglas Boulevard, Roseville | G18: =IF(LEFT(F18,5)="Owner","Yes","No") -> Yes | H18: =TEXT(I18,"mm/dd/yyyy") -> 12/30/2026 | I18: =IF(OR(WEEKDAY(C18+Parameters!$B$15,2)>5,COUNTIF(Parameters!$C$6:$C$7,C18+Parameters!$B$15)>0),WORKDAY(C18+Parameters!$B$15,1,Parameters!$C$6:$C$7),C18+Parameters!$B$15) -> 46386 | J18: None | K18: =IF(J18<>"None","No",IF(Parameters!$C$20>I18,"Yes",IF(Parameters!$C$21>I18,"Not shown","No"))) -> No | L18: 2026-0101655
A20: LAST_DAY_TO_RECORD is read from the NOC Copies tab. A claim is served on the owner when its copy was mailed to the owner at its place of business or at the address the building permit shows for it (section 8416(c)(1)); a copy mailed to the direct contractor alone is no service. ACTION_ON_INDEX is read from the civil index search of 10/02/2026, which found no action by any claimant. A lien is expired only where that search was run after its ACTION_DUE_BY date (section 8460(a) and PN-14). Not shown marks a lien whose last day to sue has passed since the search, so that the search cannot show whether an action was filed in time.

Sheet Waivers
A1: Every waiver on file from a claimant, read against the payment ledger
A3: CLAIMANT | B3: FORM_TITLE | C3: THROUGH_DATE | D3: THROUGH_SERIAL | E3: AMOUNT | F3: EXCEPTIONS | G3: CHECK_REF | H3: CHECK_NO | I3: CHECK_AT_THE_BANK | J3: STATUTORY_FORM | K3: FORM_KIND | L3: EFFECTIVE | M3: WHY
A4: Tallac Concrete, Inc. | B4: Unconditional Waiver and Release on Progress Payment | C4: 02/28/2026 | D4: =IF(C4="","",DATE(VALUE(RIGHT(C4,4)),VALUE(LEFT(C4,2)),VALUE(MID(C4,4,2)))) -> 46081 | E4: 71250 | F4: None | H4: =IF(G4="","",VALUE(RIGHT(G4,4))) | I4: =IF(G4="","No check named",IF(COUNTIFS('DK Ledger'!$B$4:$B$42,H4,'DK Ledger'!$C$4:$C$42,"STP")>0,"Stopped",IF(INDEX('DK Ledger'!$H$4:$H$42,MATCH(H4,'DK Ledger'!$B$4:$B$42,0))="","Not paid by the bank","Paid "&INDEX('DK Ledger'!$H$4:$H$42,MATCH(H4,'DK Ledger'!$B$4:$B$42,0))))) -> No check named | J4: =IF(OR(LEFT(B4,32)="Unconditional Waiver and Release",LEFT(B4,30)="Conditional Waiver and Release"),"Yes","No") -> Yes | K4: =IF(J4="No","None",IF(ISNUMBER(SEARCH("Final Payment",B4)),"Final","Progress")) -> Progress | L4: =IF(J4="No","No",IF(LEFT(B4,13)="Unconditional","Yes",IF(LEFT(I4,4)="Paid","Yes","No"))) -> Yes | M4: =IF(J4="No","Not one of the four statutory forms, releases nothing",IF(LEFT(B4,13)="Unconditional",IF(K4="Final","Effective when signed whether or not paid, section 8138","Effective when signed whether or not paid, section 8134"),IF(LEFT(I4,4)="Paid","Check paid by the bank, effective under section 8124(b)","No evidence of payment under section 8124(b), releases nothing until payment is shown"))) -> Effective when signed whether or not paid, section 8134
A5: Tallac Concrete, Inc. | B5: Unconditional Waiver and Release on Progress Payment | C5: 03/31/2026 | D5: =IF(C5="","",DATE(VALUE(RIGHT(C5,4)),VALUE(LEFT(C5,2)),VALUE(MID(C5,4,2)))) -> 46112 | E5: 158650 | F5: None | H5: =IF(G5="","",VALUE(RIGHT(G5,4))) | I5: =IF(G5="","No check named",IF(COUNTIFS('DK Ledger'!$B$4:$B$42,H5,'DK Ledger'!$C$4:$C$42,"STP")>0,"Stopped",IF(INDEX('DK Ledger'!$H$4:$H$42,MATCH(H5,'DK Ledger'!$B$4:$B$42,0))="","Not paid by the bank","Paid "&INDEX('DK Ledger'!$H$4:$H$42,MATCH(H5,'DK Ledger'!$B$4:$B$42,0))))) -> No check named | J5: =IF(OR(LEFT(B5,32)="Unconditional Waiver and Release",LEFT(B5,30)="Conditional Waiver and Release"),"Yes","No") -> Yes | K5: =IF(J5="No","None",IF(ISNUMBER(SEARCH("Final Payment",B5)),"Final","Progress")) -> Progress | L5: =IF(J5="No","No",IF(LEFT(B5,13)="Unconditional","Yes",IF(LEFT(I5,4)="Paid","Yes","No"))) -> Yes | M5: =IF(J5="No","Not one of the four statutory forms, releases nothing",IF(LEFT(B5,13)="Unconditional",IF(K5="Final","Effective when signed whether or not paid, section 8138","Effective when signed whether or not paid, section 8134"),IF(LEFT(I5,4)="Paid","Check paid by the bank, effective under section 8124(b)","No evidence of payment under section 8124(b), releases nothing until payment is shown"))) -> Effective when signed whether or not paid, section 8134
A6: Tallac Concrete, Inc. | B6: Unconditional Waiver and Release on Progress Payment | C6: 04/30/2026 | D6: =IF(C6="","",DATE(VALUE(RIGHT(C6,4)),VALUE(LEFT(C6,2)),VALUE(MID(C6,4,2)))) -> 46142 | E6: 143710 | F6: None | H6: =IF(G6="","",VALUE(RIGHT(G6,4))) | I6: =IF(G6="","No check named",IF(COUNTIFS('DK Ledger'!$B$4:$B$42,H6,'DK Ledger'!$C$4:$C$42,"STP")>0,"Stopped",IF(INDEX('DK Ledger'!$H$4:$H$42,MATCH(H6,'DK Ledger'!$B$4:$B$42,0))="","Not paid by the bank","Paid "&INDEX('DK Ledger'!$H$4:$H$42,MATCH(H6,'DK Ledger'!$B$4:$B$42,0))))) -> No check named | J6: =IF(OR(LEFT(B6,32)="Unconditional Waiver and Release",LEFT(B6,30)="Conditional Waiver and Release"),"Yes","No") -> Yes | K6: =IF(J6="No","None",IF(ISNUMBER(SEARCH("Final Payment",B6)),"Final","Progress")) -> Progress | L6: =IF(J6="No","No",IF(LEFT(B6,13)="Unconditional","Yes",IF(LEFT(I6,4)="Paid","Yes","No"))) -> Yes | M6: =IF(J6="No","Not one of the four statutory forms, releases nothing",IF(LEFT(B6,13)="Unconditional",IF(K6="Final","Effective when signed whether or not paid, section 8138","Effective when signed whether or not paid, section 8134"),IF(LEFT(I6,4)="Paid","Check paid by the bank, effective under section 8124(b)","No evidence of payment under section 8124(b), releases nothing until payment is shown"))) -> Effective when signed whether or not paid, section 8134
A7: Tallac Concrete, Inc. | B7: Lien release letter on Tallac Concrete letterhead | C7: 05/08/2026 | D7: =IF(C7="","",DATE(VALUE(RIGHT(C7,4)),VALUE(LEFT(C7,2)),VALUE(MID(C7,4,2)))) -> 46150 | E7: 12675 | F7: Letter says all claims for the May billing and retention are released on payment of the balance | H7: =IF(G7="","",VALUE(RIGHT(G7,4))) | I7: =IF(G7="","No check named",IF(COUNTIFS('DK Ledger'!$B$4:$B$42,H7,'DK Ledger'!$C$4:$C$42,"STP")>0,"Stopped",IF(INDEX('DK Ledger'!$H$4:$H$42,MATCH(H7,'DK Ledger'!$B$4:$B$42,0))="","Not paid by the bank","Paid "&INDEX('DK Ledger'!$H$4:$H$42,MATCH(H7,'DK Ledger'!$B$4:$B$42,0))))) -> No check named | J7: =IF(OR(LEFT(B7,32)="Unconditional Waiver and Release",LEFT(B7,30)="Conditional Waiver and Release"),"Yes","No") -> No | K7: =IF(J7="No","None",IF(ISNUMBER(SEARCH("Final Payment",B7)),"Final","Progress")) -> None | L7: =IF(J7="No","No",IF(LEFT(B7,13)="Unconditional","Yes",IF(LEFT(I7,4)="Paid","Yes","No"))) -> No | M7: =IF(J7="No","Not one of the four statutory forms, releases nothing",IF(LEFT(B7,13)="Unconditional",IF(K7="Final","Effective when signed whether or not paid, section 8138","Effective when signed whether or not paid, section 8134"),IF(LEFT(I7,4)="Paid","Check paid by the bank, effective under section 8124(b)","No evidence of payment under section 8124(b), releases nothing until payment is shown"))) -> Not one of the four statutory forms, releases nothing
A8: Abrego Glass & Glazing | B8: Unconditional Waiver and Release on Progress Payment | C8: 05/31/2026 | D8: =IF(C8="","",DATE(VALUE(RIGHT(C8,4)),VALUE(LEFT(C8,2)),VALUE(MID(C8,4,2)))) -> 46173 | E8: 112765 | F8: None | H8: =IF(G8="","",VALUE(RIGHT(G8,4))) | I8: =IF(G8="","No check named",IF(COUNTIFS('DK Ledger'!$B$4:$B$42,H8,'DK Ledger'!$C$4:$C$42,"STP")>0,"Stopped",IF(INDEX('DK Ledger'!$H$4:$H$42,MATCH(H8,'DK Ledger'!$B$4:$B$42,0))="","Not paid by the bank","Paid "&INDEX('DK Ledger'!$H$4:$H$42,MATCH(H8,'DK Ledger'!$B$4:$B$42,0))))) -> No check named | J8: =IF(OR(LEFT(B8,32)="Unconditional Waiver and Release",LEFT(B8,30)="Conditional Waiver and Release"),"Yes","No") -> Yes | K8: =IF(J8="No","None",IF(ISNUMBER(SEARCH("Final Payment",B8)),"Final","Progress")) -> Progress | L8: =IF(J8="No","No",IF(LEFT(B8,13)="Unconditional","Yes",IF(LEFT(I8,4)="Paid","Yes","No"))) -> Yes | M8: =IF(J8="No","Not one of the four statutory forms, releases nothing",IF(LEFT(B8,13)="Unconditional",IF(K8="Final","Effective when signed whether or not paid, section 8138","Effective when signed whether or not paid, section 8134"),IF(LEFT(I8,4)="Paid","Check paid by the bank, effective under section 8124(b)","No evidence of payment under section 8124(b), releases nothing until payment is shown"))) -> Effective when signed whether or not paid, section 8134
A9: Abrego Glass & Glazing | B9: Unconditional Waiver and Release on Progress Payment | C9: 06/30/2026 | D9: =IF(C9="","",DATE(VALUE(RIGHT(C9,4)),VALUE(LEFT(C9,2)),VALUE(MID(C9,4,2)))) -> 46203 | E9: 64790 | F9: None | H9: =IF(G9="","",VALUE(RIGHT(G9,4))) | I9: =IF(G9="","No check named",IF(COUNTIFS('DK Ledger'!$B$4:$B$42,H9,'DK Ledger'!$C$4:$C$42,"STP")>0,"Stopped",IF(INDEX('DK Ledger'!$H$4:$H$42,MATCH(H9,'DK Ledger'!$B$4:$B$42,0))="","Not paid by the bank","Paid "&INDEX('DK Ledger'!$H$4:$H$42,MATCH(H9,'DK Ledger'!$B$4:$B$42,0))))) -> No check named | J9: =IF(OR(LEFT(B9,32)="Unconditional Waiver and Release",LEFT(B9,30)="Conditional Waiver and Release"),"Yes","No") -> Yes | K9: =IF(J9="No","None",IF(ISNUMBER(SEARCH("Final Payment",B9)),"Final","Progress")) -> Progress | L9: =IF(J9="No","No",IF(LEFT(B9,13)="Unconditional","Yes",IF(LEFT(I9,4)="Paid","Yes","No"))) -> Yes | M9: =IF(J9="No","Not one of the four statutory forms, releases nothing",IF(LEFT(B9,13)="Unconditional",IF(K9="Final","Effective when signed whether or not paid, section 8138","Effective when signed whether or not paid, section 8134"),IF(LEFT(I9,4)="Paid","Check paid by the bank, effective under section 8124(b)","No evidence of payment under section 8124(b), releases nothing until payment is shown"))) -> Effective when signed whether or not paid, section 8134
A10: Kastner Mechanical Contractors, Inc. | B10: Unconditional Waiver and Release on Progress Payment | C10: 03/31/2026 | D10: =IF(C10="","",DATE(VALUE(RIGHT(C10,4)),VALUE(LEFT(C10,2)),VALUE(MID(C10,4,2)))) -> 46112 | E10: 32110 | F10: None | H10: =IF(G10="","",VALUE(RIGHT(G10,4))) | I10: =IF(G10="","No check named",IF(COUNTIFS('DK Ledger'!$B$4:$B$42,H10,'DK Ledger'!$C$4:$C$42,"STP")>0,"Stopped",IF(INDEX('DK Ledger'!$H$4:$H$42,MATCH(H10,'DK Ledger'!$B$4:$B$42,0))="","Not paid by the bank","Paid "&INDEX('DK Ledger'!$H$4:$H$42,MATCH(H10,'DK Ledger'!$B$4:$B$42,0))))) -> No check named | J10: =IF(OR(LEFT(B10,32)="Unconditional Waiver and Release",LEFT(B10,30)="Conditional Waiver and Release"),"Yes","No") -> Yes | K10: =IF(J10="No","None",IF(ISNUMBER(SEARCH("Final Payment",B10)),"Final","Progress")) -> Progress | L10: =IF(J10="No","No",IF(LEFT(B10,13)="Unconditional","Yes",IF(LEFT(I10,4)="Paid","Yes","No"))) -> Yes | M10: =IF(J10="No","Not one of the four statutory forms, releases nothing",IF(LEFT(B10,13)="Unconditional",IF(K10="Final","Effective when signed whether or not paid, section 8138","Effective when signed whether or not paid, section 8134"),IF(LEFT(I10,4)="Paid","Check paid by the bank, effective under section 8124(b)","No evidence of payment under section 8124(b), releases nothing until payment is shown"))) -> Effective when signed whether or not paid, section 8134
A11: Kastner Mechanical Contractors, Inc. | B11: Unconditional Waiver and Release on Progress Payment | C11: 04/30/2026 | D11: =IF(C11="","",DATE(VALUE(RIGHT(C11,4)),VALUE(LEFT(C11,2)),VALUE(MID(C11,4,2)))) -> 46142 | E11: 97565 | F11: None | H11: =IF(G11="","",VALUE(RIGHT(G11,4))) | I11: =IF(G11="","No check named",IF(COUNTIFS('DK Ledger'!$B$4:$B$42,H11,'DK Ledger'!$C$4:$C$42,"STP")>0,"Stopped",IF(INDEX('DK Ledger'!$H$4:$H$42,MATCH(H11,'DK Ledger'!$B$4:$B$42,0))="","Not paid by the bank","Paid "&INDEX('DK Ledger'!$H$4:$H$42,MATCH(H11,'DK Ledger'!$B$4:$B$42,0))))) -> No check named | J11: =IF(OR(LEFT(B11,32)="Unconditional Waiver and Release",LEFT(B11,30)="Conditional Waiver and Release"),"Yes","No") -> Yes | K11: =IF(J11="No","None",IF(ISNUMBER(SEARCH("Final Payment",B11)),"Final","Progress")) -> Progress | L11: =IF(J11="No","No",IF(LEFT(B11,13)="Unconditional","Yes",IF(LEFT(I11,4)="Paid","Yes","No"))) -> Yes | M11: =IF(J11="No","Not one of the four statutory forms, releases nothing",IF(LEFT(B11,13)="Unconditional",IF(K11="Final","Effective when signed whether or not paid, section 8138","Effective when signed whether or not paid, section 8134"),IF(LEFT(I11,4)="Paid","Check paid by the bank, effective under section 8124(b)","No evidence of payment under section 8124(b), releases nothing until payment is shown"))) -> Effective when signed whether or not paid, section 8134
A12: Kastner Mechanical Contractors, Inc. | B12: Unconditional Waiver and Release on Progress Payment | C12: 05/31/2026 | D12: =IF(C12="","",DATE(VALUE(RIGHT(C12,4)),VALUE(LEFT(C12,2)),VALUE(MID(C12,4,2)))) -> 46173 | E12: 66860 | F12: None | H12: =IF(G12="","",VALUE(RIGHT(G12,4))) | I12: =IF(G12="","No check named",IF(COUNTIFS('DK Ledger'!$B$4:$B$42,H12,'DK Ledger'!$C$4:$C$42,"STP")>0,"Stopped",IF(INDEX('DK Ledger'!$H$4:$H$42,MATCH(H12,'DK Ledger'!$B$4:$B$42,0))="","Not paid by the bank","Paid "&INDEX('DK Ledger'!$H$4:$H$42,MATCH(H12,'DK Ledger'!$B$4:$B$42,0))))) -> No check named | J12: =IF(OR(LEFT(B12,32)="Unconditional Waiver and Release",LEFT(B12,30)="Conditional Waiver and Release"),"Yes","No") -> Yes | K12: =IF(J12="No","None",IF(ISNUMBER(SEARCH("Final Payment",B12)),"Final","Progress")) -> Progress | L12: =IF(J12="No","No",IF(LEFT(B12,13)="Unconditional","Yes",IF(LEFT(I12,4)="Paid","Yes","No"))) -> Yes | M12: =IF(J12="No","Not one of the four statutory forms, releases nothing",IF(LEFT(B12,13)="Unconditional",IF(K12="Final","Effective when signed whether or not paid, section 8138","Effective when signed whether or not paid, section 8134"),IF(LEFT(I12,4)="Paid","Check paid by the bank, effective under section 8124(b)","No evidence of payment under section 8124(b), releases nothing until payment is shown"))) -> Effective when signed whether or not paid, section 8134
A13: Kastner Mechanical Contractors, Inc. | B13: Unconditional Waiver and Release on Progress Payment | C13: 06/30/2026 | D13: =IF(C13="","",DATE(VALUE(RIGHT(C13,4)),VALUE(LEFT(C13,2)),VALUE(MID(C13,4,2)))) -> 46203 | E13: 88920 | F13: None | H13: =IF(G13="","",VALUE(RIGHT(G13,4))) | I13: =IF(G13="","No check named",IF(COUNTIFS('DK Ledger'!$B$4:$B$42,H13,'DK Ledger'!$C$4:$C$42,"STP")>0,"Stopped",IF(INDEX('DK Ledger'!$H$4:$H$42,MATCH(H13,'DK Ledger'!$B$4:$B$42,0))="","Not paid by the bank","Paid "&INDEX('DK Ledger'!$H$4:$H$42,MATCH(H13,'DK Ledger'!$B$4:$B$42,0))))) -> No check named | J13: =IF(OR(LEFT(B13,32)="Unconditional Waiver and Release",LEFT(B13,30)="Conditional Waiver and Release"),"Yes","No") -> Yes | K13: =IF(J13="No","None",IF(ISNUMBER(SEARCH("Final Payment",B13)),"Final","Progress")) -> Progress | L13: =IF(J13="No","No",IF(LEFT(B13,13)="Unconditional","Yes",IF(LEFT(I13,4)="Paid","Yes","No"))) -> Yes | M13: =IF(J13="No","Not one of the four statutory forms, releases nothing",IF(LEFT(B13,13)="Unconditional",IF(K13="Final","Effective when signed whether or not paid, section 8138","Effective when signed whether or not paid, section 8134"),IF(LEFT(I13,4)="Paid","Check paid by the bank, effective under section 8124(b)","No evidence of payment under section 8124(b), releases nothing until payment is shown"))) -> Effective when signed whether or not paid, section 8134
A14: Kastner Mechanical Contractors, Inc. | B14: Conditional Waiver and Release on Progress Payment | C14: 07/31/2026 | D14: =IF(C14="","",DATE(VALUE(RIGHT(C14,4)),VALUE(LEFT(C14,2)),VALUE(MID(C14,4,2)))) -> 46234 | E14: 73910 | F14: None | G14: Dunmore-Kettle Builders check 4460 | H14: =IF(G14="","",VALUE(RIGHT(G14,4))) -> 4460 | I14: =IF(G14="","No check named",IF(COUNTIFS('DK Ledger'!$B$4:$B$42,H14,'DK Ledger'!$C$4:$C$42,"STP")>0,"Stopped",IF(INDEX('DK Ledger'!$H$4:$H$42,MATCH(H14,'DK Ledger'!$B$4:$B$42,0))="","Not paid by the bank","Paid "&INDEX('DK Ledger'!$H$4:$H$42,MATCH(H14,'DK Ledger'!$B$4:$B$42,0))))) -> Stopped | J14: =IF(OR(LEFT(B14,32)="Unconditional Waiver and Release",LEFT(B14,30)="Conditional Waiver and Release"),"Yes","No") -> Yes | K14: =IF(J14="No","None",IF(ISNUMBER(SEARCH("Final Payment",B14)),"Final","Progress")) -> Progress | L14: =IF(J14="No","No",IF(LEFT(B14,13)="Unconditional","Yes",IF(LEFT(I14,4)="Paid","Yes","No"))) -> No | M14: =IF(J14="No","Not one of the four statutory forms, releases nothing",IF(LEFT(B14,13)="Unconditional",IF(K14="Final","Effective when signed whether or not paid, section 8138","Effective when signed whether or not paid, section 8134"),IF(LEFT(I14,4)="Paid","Check paid by the bank, effective under section 8124(b)","No evidence of payment under section 8124(b), releases nothing until payment is shown"))) -> No evidence of payment under section 8124(b), releases nothing until payment is shown
A15: Bautista Painting Co. | B15: Unconditional Waiver and Release on Progress Payment | C15: 05/31/2026 | D15: =IF(C15="","",DATE(VALUE(RIGHT(C15,4)),VALUE(LEFT(C15,2)),VALUE(MID(C15,4,2)))) -> 46173 | E15: 12825 | F15: None | H15: =IF(G15="","",VALUE(RIGHT(G15,4))) | I15: =IF(G15="","No check named",IF(COUNTIFS('DK Ledger'!$B$4:$B$42,H15,'DK Ledger'!$C$4:$C$42,"STP")>0,"Stopped",IF(INDEX('DK Ledger'!$H$4:$H$42,MATCH(H15,'DK Ledger'!$B$4:$B$42,0))="","Not paid by the bank","Paid "&INDEX('DK Ledger'!$H$4:$H$42,MATCH(H15,'DK Ledger'!$B$4:$B$42,0))))) -> No check named | J15: =IF(OR(LEFT(B15,32)="Unconditional Waiver and Release",LEFT(B15,30)="Conditional Waiver and Release"),"Yes","No") -> Yes | K15: =IF(J15="No","None",IF(ISNUMBER(SEARCH("Final Payment",B15)),"Final","Progress")) -> Progress | L15: =IF(J15="No","No",IF(LEFT(B15,13)="Unconditional","Yes",IF(LEFT(I15,4)="Paid","Yes","No"))) -> Yes | M15: =IF(J15="No","Not one of the four statutory forms, releases nothing",IF(LEFT(B15,13)="Unconditional",IF(K15="Final","Effective when signed whether or not paid, section 8138","Effective when signed whether or not paid, section 8134"),IF(LEFT(I15,4)="Paid","Check paid by the bank, effective under section 8124(b)","No evidence of payment under section 8124(b), releases nothing until payment is shown"))) -> Effective when signed whether or not paid, section 8134
A16: Bautista Painting Co. | B16: Unconditional Waiver and Release on Progress Payment | C16: 06/30/2026 | D16: =IF(C16="","",DATE(VALUE(RIGHT(C16,4)),VALUE(LEFT(C16,2)),VALUE(MID(C16,4,2)))) -> 46203 | E16: 21755 | F16: None | H16: =IF(G16="","",VALUE(RIGHT(G16,4))) | I16: =IF(G16="","No check named",IF(COUNTIFS('DK Ledger'!$B$4:$B$42,H16,'DK Ledger'!$C$4:$C$42,"STP")>0,"Stopped",IF(INDEX('DK Ledger'!$H$4:$H$42,MATCH(H16,'DK Ledger'!$B$4:$B$42,0))="","Not paid by the bank","Paid "&INDEX('DK Ledger'!$H$4:$H$42,MATCH(H16,'DK Ledger'!$B$4:$B$42,0))))) -> No check named | J16: =IF(OR(LEFT(B16,32)="Unconditional Waiver and Release",LEFT(B16,30)="Conditional Waiver and Release"),"Yes","No") -> Yes | K16: =IF(J16="No","None",IF(ISNUMBER(SEARCH("Final Payment",B16)),"Final","Progress")) -> Progress | L16: =IF(J16="No","No",IF(LEFT(B16,13)="Unconditional","Yes",IF(LEFT(I16,4)="Paid","Yes","No"))) -> Yes | M16: =IF(J16="No","Not one of the four statutory forms, releases nothing",IF(LEFT(B16,13)="Unconditional",IF(K16="Final","Effective when signed whether or not paid, section 8138","Effective when signed whether or not paid, section 8134"),IF(LEFT(I16,4)="Paid","Check paid by the bank, effective under section 8124(b)","No evidence of payment under section 8124(b), releases nothing until payment is shown"))) -> Effective when signed whether or not paid, section 8134
A17: Bautista Painting Co. | B17: Unconditional Waiver and Release on Progress Payment | C17: 07/31/2026 | D17: =IF(C17="","",DATE(VALUE(RIGHT(C17,4)),VALUE(LEFT(C17,2)),VALUE(MID(C17,4,2)))) -> 46234 | E17: 38475 | F17: None | H17: =IF(G17="","",VALUE(RIGHT(G17,4))) | I17: =IF(G17="","No check named",IF(COUNTIFS('DK Ledger'!$B$4:$B$42,H17,'DK Ledger'!$C$4:$C$42,"STP")>0,"Stopped",IF(INDEX('DK Ledger'!$H$4:$H$42,MATCH(H17,'DK Ledger'!$B$4:$B$42,0))="","Not paid by the bank","Paid "&INDEX('DK Ledger'!$H$4:$H$42,MATCH(H17,'DK Ledger'!$B$4:$B$42,0))))) -> No check named | J17: =IF(OR(LEFT(B17,32)="Unconditional Waiver and Release",LEFT(B17,30)="Conditional Waiver and Release"),"Yes","No") -> Yes | K17: =IF(J17="No","None",IF(ISNUMBER(SEARCH("Final Payment",B17)),"Final","Progress")) -> Progress | L17: =IF(J17="No","No",IF(LEFT(B17,13)="Unconditional","Yes",IF(LEFT(I17,4)="Paid","Yes","No"))) -> Yes | M17: =IF(J17="No","Not one of the four statutory forms, releases nothing",IF(LEFT(B17,13)="Unconditional",IF(K17="Final","Effective when signed whether or not paid, section 8138","Effective when signed whether or not paid, section 8134"),IF(LEFT(I17,4)="Paid","Check paid by the bank, effective under section 8124(b)","No evidence of payment under section 8124(b), releases nothing until payment is shown"))) -> Effective when signed whether or not paid, section 8134
A18: Fenwick Roofing, Inc. | B18: Unconditional Waiver and Release on Progress Payment | C18: 03/31/2026 | D18: =IF(C18="","",DATE(VALUE(RIGHT(C18,4)),VALUE(LEFT(C18,2)),VALUE(MID(C18,4,2)))) -> 46112 | E18: 95410 | F18: None | H18: =IF(G18="","",VALUE(RIGHT(G18,4))) | I18: =IF(G18="","No check named",IF(COUNTIFS('DK Ledger'!$B$4:$B$42,H18,'DK Ledger'!$C$4:$C$42,"STP")>0,"Stopped",IF(INDEX('DK Ledger'!$H$4:$H$42,MATCH(H18,'DK Ledger'!$B$4:$B$42,0))="","Not paid by the bank","Paid "&INDEX('DK Ledger'!$H$4:$H$42,MATCH(H18,'DK Ledger'!$B$4:$B$42,0))))) -> No check named | J18: =IF(OR(LEFT(B18,32)="Unconditional Waiver and Release",LEFT(B18,30)="Conditional Waiver and Release"),"Yes","No") -> Yes | K18: =IF(J18="No","None",IF(ISNUMBER(SEARCH("Final Payment",B18)),"Final","Progress")) -> Progress | L18: =IF(J18="No","No",IF(LEFT(B18,13)="Unconditional","Yes",IF(LEFT(I18,4)="Paid","Yes","No"))) -> Yes | M18: =IF(J18="No","Not one of the four statutory forms, releases nothing",IF(LEFT(B18,13)="Unconditional",IF(K18="Final","Effective when signed whether or not paid, section 8138","Effective when signed whether or not paid, section 8134"),IF(LEFT(I18,4)="Paid","Check paid by the bank, effective under section 8124(b)","No evidence of payment under section 8124(b), releases nothing until payment is shown"))) -> Effective when signed whether or not paid, section 8134
A19: Fenwick Roofing, Inc. | B19: Unconditional Waiver and Release on Progress Payment | C19: 04/30/2026 | D19: =IF(C19="","",DATE(VALUE(RIGHT(C19,4)),VALUE(LEFT(C19,2)),VALUE(MID(C19,4,2)))) -> 46142 | E19: 173465 | F19: None | H19: =IF(G19="","",VALUE(RIGHT(G19,4))) | I19: =IF(G19="","No check named",IF(COUNTIFS('DK Ledger'!$B$4:$B$42,H19,'DK Ledger'!$C$4:$C$42,"STP")>0,"Stopped",IF(INDEX('DK Ledger'!$H$4:$H$42,MATCH(H19,'DK Ledger'!$B$4:$B$42,0))="","Not paid by the bank","Paid "&INDEX('DK Ledger'!$H$4:$H$42,MATCH(H19,'DK Ledger'!$B$4:$B$42,0))))) -> No check named | J19: =IF(OR(LEFT(B19,32)="Unconditional Waiver and Release",LEFT(B19,30)="Conditional Waiver and Release"),"Yes","No") -> Yes | K19: =IF(J19="No","None",IF(ISNUMBER(SEARCH("Final Payment",B19)),"Final","Progress")) -> Progress | L19: =IF(J19="No","No",IF(LEFT(B19,13)="Unconditional","Yes",IF(LEFT(I19,4)="Paid","Yes","No"))) -> Yes | M19: =IF(J19="No","Not one of the four statutory forms, releases nothing",IF(LEFT(B19,13)="Unconditional",IF(K19="Final","Effective when signed whether or not paid, section 8138","Effective when signed whether or not paid, section 8134"),IF(LEFT(I19,4)="Paid","Check paid by the bank, effective under section 8124(b)","No evidence of payment under section 8124(b), releases nothing until payment is shown"))) -> Effective when signed whether or not paid, section 8134
A20: Fenwick Roofing, Inc. | B20: Conditional Waiver and Release on Final Payment | D20: =IF(C20="","",DATE(VALUE(RIGHT(C20,4)),VALUE(LEFT(C20,2)),VALUE(MID(C20,4,2)))) | E20: 14937.5 | F20: Disputed claims for extras: $0.00 | G20: Dunmore-Kettle Builders check 4448 | H20: =IF(G20="","",VALUE(RIGHT(G20,4))) -> 4448 | I20: =IF(G20="","No check named",IF(COUNTIFS('DK Ledger'!$B$4:$B$42,H20,'DK Ledger'!$C$4:$C$42,"STP")>0,"Stopped",IF(INDEX('DK Ledger'!$H$4:$H$42,MATCH(H20,'DK Ledger'!$B$4:$B$42,0))="","Not paid by the bank","Paid "&INDEX('DK Ledger'!$H$4:$H$42,MATCH(H20,'DK Ledger'!$B$4:$B$42,0))))) -> Paid 08/03/2026 | J20: =IF(OR(LEFT(B20,32)="Unconditional Waiver and Release",LEFT(B20,30)="Conditional Waiver and Release"),"Yes","No") -> Yes | K20: =IF(J20="No","None",IF(ISNUMBER(SEARCH("Final Payment",B20)),"Final","Progress")) -> Final | L20: =IF(J20="No","No",IF(LEFT(B20,13)="Unconditional","Yes",IF(LEFT(I20,4)="Paid","Yes","No"))) -> Yes | M20: =IF(J20="No","Not one of the four statutory forms, releases nothing",IF(LEFT(B20,13)="Unconditional",IF(K20="Final","Effective when signed whether or not paid, section 8138","Effective when signed whether or not paid, section 8134"),IF(LEFT(I20,4)="Paid","Check paid by the bank, effective under section 8124(b)","No evidence of payment under section 8124(b), releases nothing until payment is shown"))) -> Check paid by the bank, effective under section 8124(b)
A21: Lindqvist Fire Protection | B21: Unconditional Waiver and Release on Progress Payment | C21: 04/30/2026 | D21: =IF(C21="","",DATE(VALUE(RIGHT(C21,4)),VALUE(LEFT(C21,2)),VALUE(MID(C21,4,2)))) -> 46142 | E21: 69501.5 | F21: None | H21: =IF(G21="","",VALUE(RIGHT(G21,4))) | I21: =IF(G21="","No check named",IF(COUNTIFS('DK Ledger'!$B$4:$B$42,H21,'DK Ledger'!$C$4:$C$42,"STP")>0,"Stopped",IF(INDEX('DK Ledger'!$H$4:$H$42,MATCH(H21,'DK Ledger'!$B$4:$B$42,0))="","Not paid by the bank","Paid "&INDEX('DK Ledger'!$H$4:$H$42,MATCH(H21,'DK Ledger'!$B$4:$B$42,0))))) -> No check named | J21: =IF(OR(LEFT(B21,32)="Unconditional Waiver and Release",LEFT(B21,30)="Conditional Waiver and Release"),"Yes","No") -> Yes | K21: =IF(J21="No","None",IF(ISNUMBER(SEARCH("Final Payment",B21)),"Final","Progress")) -> Progress | L21: =IF(J21="No","No",IF(LEFT(B21,13)="Unconditional","Yes",IF(LEFT(I21,4)="Paid","Yes","No"))) -> Yes | M21: =IF(J21="No","Not one of the four statutory forms, releases nothing",IF(LEFT(B21,13)="Unconditional",IF(K21="Final","Effective when signed whether or not paid, section 8138","Effective when signed whether or not paid, section 8134"),IF(LEFT(I21,4)="Paid","Check paid by the bank, effective under section 8124(b)","No evidence of payment under section 8124(b), releases nothing until payment is shown"))) -> Effective when signed whether or not paid, section 8134
A22: Lindqvist Fire Protection | B22: Unconditional Waiver and Release on Progress Payment | C22: 06/30/2026 | D22: =IF(C22="","",DATE(VALUE(RIGHT(C22,4)),VALUE(LEFT(C22,2)),VALUE(MID(C22,4,2)))) -> 46203 | E22: 66016 | F22: None | H22: =IF(G22="","",VALUE(RIGHT(G22,4))) | I22: =IF(G22="","No check named",IF(COUNTIFS('DK Ledger'!$B$4:$B$42,H22,'DK Ledger'!$C$4:$C$42,"STP")>0,"Stopped",IF(INDEX('DK Ledger'!$H$4:$H$42,MATCH(H22,'DK Ledger'!$B$4:$B$42,0))="","Not paid by the bank","Paid "&INDEX('DK Ledger'!$H$4:$H$42,MATCH(H22,'DK Ledger'!$B$4:$B$42,0))))) -> No check named | J22: =IF(OR(LEFT(B22,32)="Unconditional Waiver and Release",LEFT(B22,30)="Conditional Waiver and Release"),"Yes","No") -> Yes | K22: =IF(J22="No","None",IF(ISNUMBER(SEARCH("Final Payment",B22)),"Final","Progress")) -> Progress | L22: =IF(J22="No","No",IF(LEFT(B22,13)="Unconditional","Yes",IF(LEFT(I22,4)="Paid","Yes","No"))) -> Yes | M22: =IF(J22="No","Not one of the four statutory forms, releases nothing",IF(LEFT(B22,13)="Unconditional",IF(K22="Final","Effective when signed whether or not paid, section 8138","Effective when signed whether or not paid, section 8134"),IF(LEFT(I22,4)="Paid","Check paid by the bank, effective under section 8124(b)","No evidence of payment under section 8124(b), releases nothing until payment is shown"))) -> Effective when signed whether or not paid, section 8134
A23: Ostrowski Electric, Inc. | B23: Unconditional Waiver and Release on Progress Payment | C23: 02/28/2026 | D23: =IF(C23="","",DATE(VALUE(RIGHT(C23,4)),VALUE(LEFT(C23,2)),VALUE(MID(C23,4,2)))) -> 46081 | E23: 152950 | F23: None | H23: =IF(G23="","",VALUE(RIGHT(G23,4))) | I23: =IF(G23="","No check named",IF(COUNTIFS('DK Ledger'!$B$4:$B$42,H23,'DK Ledger'!$C$4:$C$42,"STP")>0,"Stopped",IF(INDEX('DK Ledger'!$H$4:$H$42,MATCH(H23,'DK Ledger'!$B$4:$B$42,0))="","Not paid by the bank","Paid "&INDEX('DK Ledger'!$H$4:$H$42,MATCH(H23,'DK Ledger'!$B$4:$B$42,0))))) -> No check named | J23: =IF(OR(LEFT(B23,32)="Unconditional Waiver and Release",LEFT(B23,30)="Conditional Waiver and Release"),"Yes","No") -> Yes | K23: =IF(J23="No","None",IF(ISNUMBER(SEARCH("Final Payment",B23)),"Final","Progress")) -> Progress | L23: =IF(J23="No","No",IF(LEFT(B23,13)="Unconditional","Yes",IF(LEFT(I23,4)="Paid","Yes","No"))) -> Yes | M23: =IF(J23="No","Not one of the four statutory forms, releases nothing",IF(LEFT(B23,13)="Unconditional",IF(K23="Final","Effective when signed whether or not paid, section 8138","Effective when signed whether or not paid, section 8134"),IF(LEFT(I23,4)="Paid","Check paid by the bank, effective under section 8124(b)","No evidence of payment under section 8124(b), releases nothing until payment is shown"))) -> Effective when signed whether or not paid, section 8134
A24: Ostrowski Electric, Inc. | B24: Unconditional Waiver and Release on Progress Payment | C24: 03/31/2026 | D24: =IF(C24="","",DATE(VALUE(RIGHT(C24,4)),VALUE(LEFT(C24,2)),VALUE(MID(C24,4,2)))) -> 46112 | E24: 121600 | F24: None | H24: =IF(G24="","",VALUE(RIGHT(G24,4))) | I24: =IF(G24="","No check named",IF(COUNTIFS('DK Ledger'!$B$4:$B$42,H24,'DK Ledger'!$C$4:$C$42,"STP")>0,"Stopped",IF(INDEX('DK Ledger'!$H$4:$H$42,MATCH(H24,'DK Ledger'!$B$4:$B$42,0))="","Not paid by the bank","Paid "&INDEX('DK Ledger'!$H$4:$H$42,MATCH(H24,'DK Ledger'!$B$4:$B$42,0))))) -> No check named | J24: =IF(OR(LEFT(B24,32)="Unconditional Waiver and Release",LEFT(B24,30)="Conditional Waiver and Release"),"Yes","No") -> Yes | K24: =IF(J24="No","None",IF(ISNUMBER(SEARCH("Final Payment",B24)),"Final","Progress")) -> Progress | L24: =IF(J24="No","No",IF(LEFT(B24,13)="Unconditional","Yes",IF(LEFT(I24,4)="Paid","Yes","No"))) -> Yes | M24: =IF(J24="No","Not one of the four statutory forms, releases nothing",IF(LEFT(B24,13)="Unconditional",IF(K24="Final","Effective when signed whether or not paid, section 8138","Effective when signed whether or not paid, section 8134"),IF(LEFT(I24,4)="Paid","Check paid by the bank, effective under section 8124(b)","No evidence of payment under section 8124(b), releases nothing until payment is shown"))) -> Effective when signed whether or not paid, section 8134
A25: Ostrowski Electric, Inc. | B25: Unconditional Waiver and Release on Progress Payment | C25: 04/30/2026 | D25: =IF(C25="","",DATE(VALUE(RIGHT(C25,4)),VALUE(LEFT(C25,2)),VALUE(MID(C25,4,2)))) -> 46142 | E25: 98325 | F25: None | H25: =IF(G25="","",VALUE(RIGHT(G25,4))) | I25: =IF(G25="","No check named",IF(COUNTIFS('DK Ledger'!$B$4:$B$42,H25,'DK Ledger'!$C$4:$C$42,"STP")>0,"Stopped",IF(INDEX('DK Ledger'!$H$4:$H$42,MATCH(H25,'DK Ledger'!$B$4:$B$42,0))="","Not paid by the bank","Paid "&INDEX('DK Ledger'!$H$4:$H$42,MATCH(H25,'DK Ledger'!$B$4:$B$42,0))))) -> No check named | J25: =IF(OR(LEFT(B25,32)="Unconditional Waiver and Release",LEFT(B25,30)="Conditional Waiver and Release"),"Yes","No") -> Yes | K25: =IF(J25="No","None",IF(ISNUMBER(SEARCH("Final Payment",B25)),"Final","Progress")) -> Progress | L25: =IF(J25="No","No",IF(LEFT(B25,13)="Unconditional","Yes",IF(LEFT(I25,4)="Paid","Yes","No"))) -> Yes | M25: =IF(J25="No","Not one of the four statutory forms, releases nothing",IF(LEFT(B25,13)="Unconditional",IF(K25="Final","Effective when signed whether or not paid, section 8138","Effective when signed whether or not paid, section 8134"),IF(LEFT(I25,4)="Paid","Check paid by the bank, effective under section 8124(b)","No evidence of payment under section 8124(b), releases nothing until payment is shown"))) -> Effective when signed whether or not paid, section 8134
A26: Ostrowski Electric, Inc. | B26: Unconditional Waiver and Release on Progress Payment | C26: 05/31/2026 | D26: =IF(C26="","",DATE(VALUE(RIGHT(C26,4)),VALUE(LEFT(C26,2)),VALUE(MID(C26,4,2)))) -> 46173 | E26: 89305 | F26: None | H26: =IF(G26="","",VALUE(RIGHT(G26,4))) | I26: =IF(G26="","No check named",IF(COUNTIFS('DK Ledger'!$B$4:$B$42,H26,'DK Ledger'!$C$4:$C$42,"STP")>0,"Stopped",IF(INDEX('DK Ledger'!$H$4:$H$42,MATCH(H26,'DK Ledger'!$B$4:$B$42,0))="","Not paid by the bank","Paid "&INDEX('DK Ledger'!$H$4:$H$42,MATCH(H26,'DK Ledger'!$B$4:$B$42,0))))) -> No check named | J26: =IF(OR(LEFT(B26,32)="Unconditional Waiver and Release",LEFT(B26,30)="Conditional Waiver and Release"),"Yes","No") -> Yes | K26: =IF(J26="No","None",IF(ISNUMBER(SEARCH("Final Payment",B26)),"Final","Progress")) -> Progress | L26: =IF(J26="No","No",IF(LEFT(B26,13)="Unconditional","Yes",IF(LEFT(I26,4)="Paid","Yes","No"))) -> Yes | M26: =IF(J26="No","Not one of the four statutory forms, releases nothing",IF(LEFT(B26,13)="Unconditional",IF(K26="Final","Effective when signed whether or not paid, section 8138","Effective when signed whether or not paid, section 8134"),IF(LEFT(I26,4)="Paid","Check paid by the bank, effective under section 8124(b)","No evidence of payment under section 8124(b), releases nothing until payment is shown"))) -> Effective when signed whether or not paid, section 8134
A27: Ostrowski Electric, Inc. | B27: Unconditional Waiver and Release on Progress Payment | C27: 06/30/2026 | D27: =IF(C27="","",DATE(VALUE(RIGHT(C27,4)),VALUE(LEFT(C27,2)),VALUE(MID(C27,4,2)))) -> 46203 | E27: 120113 | F27: None | H27: =IF(G27="","",VALUE(RIGHT(G27,4))) | I27: =IF(G27="","No check named",IF(COUNTIFS('DK Ledger'!$B$4:$B$42,H27,'DK Ledger'!$C$4:$C$42,"STP")>0,"Stopped",IF(INDEX('DK Ledger'!$H$4:$H$42,MATCH(H27,'DK Ledger'!$B$4:$B$42,0))="","Not paid by the bank","Paid "&INDEX('DK Ledger'!$H$4:$H$42,MATCH(H27,'DK Ledger'!$B$4:$B$42,0))))) -> No check named | J27: =IF(OR(LEFT(B27,32)="Unconditional Waiver and Release",LEFT(B27,30)="Conditional Waiver and Release"),"Yes","No") -> Yes | K27: =IF(J27="No","None",IF(ISNUMBER(SEARCH("Final Payment",B27)),"Final","Progress")) -> Progress | L27: =IF(J27="No","No",IF(LEFT(B27,13)="Unconditional","Yes",IF(LEFT(I27,4)="Paid","Yes","No"))) -> Yes | M27: =IF(J27="No","Not one of the four statutory forms, releases nothing",IF(LEFT(B27,13)="Unconditional",IF(K27="Final","Effective when signed whether or not paid, section 8138","Effective when signed whether or not paid, section 8134"),IF(LEFT(I27,4)="Paid","Check paid by the bank, effective under section 8124(b)","No evidence of payment under section 8124(b), releases nothing until payment is shown"))) -> Effective when signed whether or not paid, section 8134
A28: Ostrowski Electric, Inc. | B28: Conditional Waiver and Release on Progress Payment | C28: 07/31/2026 | D28: =IF(C28="","",DATE(VALUE(RIGHT(C28,4)),VALUE(LEFT(C28,2)),VALUE(MID(C28,4,2)))) -> 46234 | E28: 41230 | F28: None | G28: Dunmore-Kettle Builders check 4461 | H28: =IF(G28="","",VALUE(RIGHT(G28,4))) -> 4461 | I28: =IF(G28="","No check named",IF(COUNTIFS('DK Ledger'!$B$4:$B$42,H28,'DK Ledger'!$C$4:$C$42,"STP")>0,"Stopped",IF(INDEX('DK Ledger'!$H$4:$H$42,MATCH(H28,'DK Ledger'!$B$4:$B$42,0))="","Not paid by the bank","Paid "&INDEX('DK Ledger'!$H$4:$H$42,MATCH(H28,'DK Ledger'!$B$4:$B$42,0))))) -> Paid 08/24/2026 | J28: =IF(OR(LEFT(B28,32)="Unconditional Waiver and Release",LEFT(B28,30)="Conditional Waiver and Release"),"Yes","No") -> Yes | K28: =IF(J28="No","None",IF(ISNUMBER(SEARCH("Final Payment",B28)),"Final","Progress")) -> Progress | L28: =IF(J28="No","No",IF(LEFT(B28,13)="Unconditional","Yes",IF(LEFT(I28,4)="Paid","Yes","No"))) -> Yes | M28: =IF(J28="No","Not one of the four statutory forms, releases nothing",IF(LEFT(B28,13)="Unconditional",IF(K28="Final","Effective when signed whether or not paid, section 8138","Effective when signed whether or not paid, section 8134"),IF(LEFT(I28,4)="Paid","Check paid by the bank, effective under section 8124(b)","No evidence of payment under section 8124(b), releases nothing until payment is shown"))) -> Check paid by the bank, effective under section 8124(b)
A29: Ostrowski Electric, Inc. | B29: Conditional Waiver and Release on Progress Payment | C29: 08/11/2026 | D29: =IF(C29="","",DATE(VALUE(RIGHT(C29,4)),VALUE(LEFT(C29,2)),VALUE(MID(C29,4,2)))) -> 46245 | E29: 27227 | F29: None | G29: Dunmore-Kettle Builders check 4479 | H29: =IF(G29="","",VALUE(RIGHT(G29,4))) -> 4479 | I29: =IF(G29="","No check named",IF(COUNTIFS('DK Ledger'!$B$4:$B$42,H29,'DK Ledger'!$C$4:$C$42,"STP")>0,"Stopped",IF(INDEX('DK Ledger'!$H$4:$H$42,MATCH(H29,'DK Ledger'!$B$4:$B$42,0))="","Not paid by the bank","Paid "&INDEX('DK Ledger'!$H$4:$H$42,MATCH(H29,'DK Ledger'!$B$4:$B$42,0))))) -> Not paid by the bank | J29: =IF(OR(LEFT(B29,32)="Unconditional Waiver and Release",LEFT(B29,30)="Conditional Waiver and Release"),"Yes","No") -> Yes | K29: =IF(J29="No","None",IF(ISNUMBER(SEARCH("Final Payment",B29)),"Final","Progress")) -> Progress | L29: =IF(J29="No","No",IF(LEFT(B29,13)="Unconditional","Yes",IF(LEFT(I29,4)="Paid","Yes","No"))) -> No | M29: =IF(J29="No","Not one of the four statutory forms, releases nothing",IF(LEFT(B29,13)="Unconditional",IF(K29="Final","Effective when signed whether or not paid, section 8138","Effective when signed whether or not paid, section 8134"),IF(LEFT(I29,4)="Paid","Check paid by the bank, effective under section 8124(b)","No evidence of payment under section 8124(b), releases nothing until payment is shown"))) -> No evidence of payment under section 8124(b), releases nothing until payment is shown
A30: Calder Drywall & Plaster, LLC | B30: Unconditional Waiver and Release on Progress Payment | C30: 04/30/2026 | D30: =IF(C30="","",DATE(VALUE(RIGHT(C30,4)),VALUE(LEFT(C30,2)),VALUE(MID(C30,4,2)))) -> 46142 | E30: 8700 | F30: None | H30: =IF(G30="","",VALUE(RIGHT(G30,4))) | I30: =IF(G30="","No check named",IF(COUNTIFS('DK Ledger'!$B$4:$B$42,H30,'DK Ledger'!$C$4:$C$42,"STP")>0,"Stopped",IF(INDEX('DK Ledger'!$H$4:$H$42,MATCH(H30,'DK Ledger'!$B$4:$B$42,0))="","Not paid by the bank","Paid "&INDEX('DK Ledger'!$H$4:$H$42,MATCH(H30,'DK Ledger'!$B$4:$B$42,0))))) -> No check named | J30: =IF(OR(LEFT(B30,32)="Unconditional Waiver and Release",LEFT(B30,30)="Conditional Waiver and Release"),"Yes","No") -> Yes | K30: =IF(J30="No","None",IF(ISNUMBER(SEARCH("Final Payment",B30)),"Final","Progress")) -> Progress | L30: =IF(J30="No","No",IF(LEFT(B30,13)="Unconditional","Yes",IF(LEFT(I30,4)="Paid","Yes","No"))) -> Yes | M30: =IF(J30="No","Not one of the four statutory forms, releases nothing",IF(LEFT(B30,13)="Unconditional",IF(K30="Final","Effective when signed whether or not paid, section 8138","Effective when signed whether or not paid, section 8134"),IF(LEFT(I30,4)="Paid","Check paid by the bank, effective under section 8124(b)","No evidence of payment under section 8124(b), releases nothing until payment is shown"))) -> Effective when signed whether or not paid, section 8134
A31: Calder Drywall & Plaster, LLC | B31: Unconditional Waiver and Release on Progress Payment | C31: 05/31/2026 | D31: =IF(C31="","",DATE(VALUE(RIGHT(C31,4)),VALUE(LEFT(C31,2)),VALUE(MID(C31,4,2)))) -> 46173 | E31: 46170 | F31: None | H31: =IF(G31="","",VALUE(RIGHT(G31,4))) | I31: =IF(G31="","No check named",IF(COUNTIFS('DK Ledger'!$B$4:$B$42,H31,'DK Ledger'!$C$4:$C$42,"STP")>0,"Stopped",IF(INDEX('DK Ledger'!$H$4:$H$42,MATCH(H31,'DK Ledger'!$B$4:$B$42,0))="","Not paid by the bank","Paid "&INDEX('DK Ledger'!$H$4:$H$42,MATCH(H31,'DK Ledger'!$B$4:$B$42,0))))) -> No check named | J31: =IF(OR(LEFT(B31,32)="Unconditional Waiver and Release",LEFT(B31,30)="Conditional Waiver and Release"),"Yes","No") -> Yes | K31: =IF(J31="No","None",IF(ISNUMBER(SEARCH("Final Payment",B31)),"Final","Progress")) -> Progress | L31: =IF(J31="No","No",IF(LEFT(B31,13)="Unconditional","Yes",IF(LEFT(I31,4)="Paid","Yes","No"))) -> Yes | M31: =IF(J31="No","Not one of the four statutory forms, releases nothing",IF(LEFT(B31,13)="Unconditional",IF(K31="Final","Effective when signed whether or not paid, section 8138","Effective when signed whether or not paid, section 8134"),IF(LEFT(I31,4)="Paid","Check paid by the bank, effective under section 8124(b)","No evidence of payment under section 8124(b), releases nothing until payment is shown"))) -> Effective when signed whether or not paid, section 8134
A32: Calder Drywall & Plaster, LLC | B32: Unconditional Waiver and Release on Progress Payment | C32: 06/30/2026 | D32: =IF(C32="","",DATE(VALUE(RIGHT(C32,4)),VALUE(LEFT(C32,2)),VALUE(MID(C32,4,2)))) -> 46203 | E32: 100515 | F32: None | H32: =IF(G32="","",VALUE(RIGHT(G32,4))) | I32: =IF(G32="","No check named",IF(COUNTIFS('DK Ledger'!$B$4:$B$42,H32,'DK Ledger'!$C$4:$C$42,"STP")>0,"Stopped",IF(INDEX('DK Ledger'!$H$4:$H$42,MATCH(H32,'DK Ledger'!$B$4:$B$42,0))="","Not paid by the bank","Paid "&INDEX('DK Ledger'!$H$4:$H$42,MATCH(H32,'DK Ledger'!$B$4:$B$42,0))))) -> No check named | J32: =IF(OR(LEFT(B32,32)="Unconditional Waiver and Release",LEFT(B32,30)="Conditional Waiver and Release"),"Yes","No") -> Yes | K32: =IF(J32="No","None",IF(ISNUMBER(SEARCH("Final Payment",B32)),"Final","Progress")) -> Progress | L32: =IF(J32="No","No",IF(LEFT(B32,13)="Unconditional","Yes",IF(LEFT(I32,4)="Paid","Yes","No"))) -> Yes | M32: =IF(J32="No","Not one of the four statutory forms, releases nothing",IF(LEFT(B32,13)="Unconditional",IF(K32="Final","Effective when signed whether or not paid, section 8138","Effective when signed whether or not paid, section 8134"),IF(LEFT(I32,4)="Paid","Check paid by the bank, effective under section 8124(b)","No evidence of payment under section 8124(b), releases nothing until payment is shown"))) -> Effective when signed whether or not paid, section 8134
A33: Calder Drywall & Plaster, LLC | B33: Subcontractor's Release and Affidavit, Dunmore-Kettle form S-9 | C33: 07/31/2026 | D33: =IF(C33="","",DATE(VALUE(RIGHT(C33,4)),VALUE(LEFT(C33,2)),VALUE(MID(C33,4,2)))) -> 46234 | E33: 29200 | F33: None stated | H33: =IF(G33="","",VALUE(RIGHT(G33,4))) | I33: =IF(G33="","No check named",IF(COUNTIFS('DK Ledger'!$B$4:$B$42,H33,'DK Ledger'!$C$4:$C$42,"STP")>0,"Stopped",IF(INDEX('DK Ledger'!$H$4:$H$42,MATCH(H33,'DK Ledger'!$B$4:$B$42,0))="","Not paid by the bank","Paid "&INDEX('DK Ledger'!$H$4:$H$42,MATCH(H33,'DK Ledger'!$B$4:$B$42,0))))) -> No check named | J33: =IF(OR(LEFT(B33,32)="Unconditional Waiver and Release",LEFT(B33,30)="Conditional Waiver and Release"),"Yes","No") -> No | K33: =IF(J33="No","None",IF(ISNUMBER(SEARCH("Final Payment",B33)),"Final","Progress")) -> None | L33: =IF(J33="No","No",IF(LEFT(B33,13)="Unconditional","Yes",IF(LEFT(I33,4)="Paid","Yes","No"))) -> No | M33: =IF(J33="No","Not one of the four statutory forms, releases nothing",IF(LEFT(B33,13)="Unconditional",IF(K33="Final","Effective when signed whether or not paid, section 8138","Effective when signed whether or not paid, section 8134"),IF(LEFT(I33,4)="Paid","Check paid by the bank, effective under section 8124(b)","No evidence of payment under section 8124(b), releases nothing until payment is shown"))) -> Not one of the four statutory forms, releases nothing
A34: Petrakis Plumbing, Inc. | B34: Unconditional Waiver and Release on Progress Payment | C34: 02/28/2026 | D34: =IF(C34="","",DATE(VALUE(RIGHT(C34,4)),VALUE(LEFT(C34,2)),VALUE(MID(C34,4,2)))) -> 46081 | E34: 61370 | F34: None | H34: =IF(G34="","",VALUE(RIGHT(G34,4))) | I34: =IF(G34="","No check named",IF(COUNTIFS('DK Ledger'!$B$4:$B$42,H34,'DK Ledger'!$C$4:$C$42,"STP")>0,"Stopped",IF(INDEX('DK Ledger'!$H$4:$H$42,MATCH(H34,'DK Ledger'!$B$4:$B$42,0))="","Not paid by the bank","Paid "&INDEX('DK Ledger'!$H$4:$H$42,MATCH(H34,'DK Ledger'!$B$4:$B$42,0))))) -> No check named | J34: =IF(OR(LEFT(B34,32)="Unconditional Waiver and Release",LEFT(B34,30)="Conditional Waiver and Release"),"Yes","No") -> Yes | K34: =IF(J34="No","None",IF(ISNUMBER(SEARCH("Final Payment",B34)),"Final","Progress")) -> Progress | L34: =IF(J34="No","No",IF(LEFT(B34,13)="Unconditional","Yes",IF(LEFT(I34,4)="Paid","Yes","No"))) -> Yes | M34: =IF(J34="No","Not one of the four statutory forms, releases nothing",IF(LEFT(B34,13)="Unconditional",IF(K34="Final","Effective when signed whether or not paid, section 8138","Effective when signed whether or not paid, section 8134"),IF(LEFT(I34,4)="Paid","Check paid by the bank, effective under section 8124(b)","No evidence of payment under section 8124(b), releases nothing until payment is shown"))) -> Effective when signed whether or not paid, section 8134
A35: Petrakis Plumbing, Inc. | B35: Unconditional Waiver and Release on Progress Payment | C35: 03/31/2026 | D35: =IF(C35="","",DATE(VALUE(RIGHT(C35,4)),VALUE(LEFT(C35,2)),VALUE(MID(C35,4,2)))) -> 46112 | E35: 48830 | F35: None | H35: =IF(G35="","",VALUE(RIGHT(G35,4))) | I35: =IF(G35="","No check named",IF(COUNTIFS('DK Ledger'!$B$4:$B$42,H35,'DK Ledger'!$C$4:$C$42,"STP")>0,"Stopped",IF(INDEX('DK Ledger'!$H$4:$H$42,MATCH(H35,'DK Ledger'!$B$4:$B$42,0))="","Not paid by the bank","Paid "&INDEX('DK Ledger'!$H$4:$H$42,MATCH(H35,'DK Ledger'!$B$4:$B$42,0))))) -> No check named | J35: =IF(OR(LEFT(B35,32)="Unconditional Waiver and Release",LEFT(B35,30)="Conditional Waiver and Release"),"Yes","No") -> Yes | K35: =IF(J35="No","None",IF(ISNUMBER(SEARCH("Final Payment",B35)),"Final","Progress")) -> Progress | L35: =IF(J35="No","No",IF(LEFT(B35,13)="Unconditional","Yes",IF(LEFT(I35,4)="Paid","Yes","No"))) -> Yes | M35: =IF(J35="No","Not one of the four statutory forms, releases nothing",IF(LEFT(B35,13)="Unconditional",IF(K35="Final","Effective when signed whether or not paid, section 8138","Effective when signed whether or not paid, section 8134"),IF(LEFT(I35,4)="Paid","Check paid by the bank, effective under section 8124(b)","No evidence of payment under section 8124(b), releases nothing until payment is shown"))) -> Effective when signed whether or not paid, section 8134
A36: Petrakis Plumbing, Inc. | B36: Unconditional Waiver and Release on Progress Payment | C36: 06/30/2026 | D36: =IF(C36="","",DATE(VALUE(RIGHT(C36,4)),VALUE(LEFT(C36,2)),VALUE(MID(C36,4,2)))) -> 46203 | E36: 116525 | F36: None | H36: =IF(G36="","",VALUE(RIGHT(G36,4))) | I36: =IF(G36="","No check named",IF(COUNTIFS('DK Ledger'!$B$4:$B$42,H36,'DK Ledger'!$C$4:$C$42,"STP")>0,"Stopped",IF(INDEX('DK Ledger'!$H$4:$H$42,MATCH(H36,'DK Ledger'!$B$4:$B$42,0))="","Not paid by the bank","Paid "&INDEX('DK Ledger'!$H$4:$H$42,MATCH(H36,'DK Ledger'!$B$4:$B$42,0))))) -> No check named | J36: =IF(OR(LEFT(B36,32)="Unconditional Waiver and Release",LEFT(B36,30)="Conditional Waiver and Release"),"Yes","No") -> Yes | K36: =IF(J36="No","None",IF(ISNUMBER(SEARCH("Final Payment",B36)),"Final","Progress")) -> Progress | L36: =IF(J36="No","No",IF(LEFT(B36,13)="Unconditional","Yes",IF(LEFT(I36,4)="Paid","Yes","No"))) -> Yes | M36: =IF(J36="No","Not one of the four statutory forms, releases nothing",IF(LEFT(B36,13)="Unconditional",IF(K36="Final","Effective when signed whether or not paid, section 8138","Effective when signed whether or not paid, section 8134"),IF(LEFT(I36,4)="Paid","Check paid by the bank, effective under section 8124(b)","No evidence of payment under section 8124(b), releases nothing until payment is shown"))) -> Effective when signed whether or not paid, section 8134
A37: Petrakis Plumbing, Inc. | B37: Unconditional Waiver and Release on Progress Payment | C37: 07/31/2026 | D37: =IF(C37="","",DATE(VALUE(RIGHT(C37,4)),VALUE(LEFT(C37,2)),VALUE(MID(C37,4,2)))) -> 46234 | E37: 37166 | F37: None | H37: =IF(G37="","",VALUE(RIGHT(G37,4))) | I37: =IF(G37="","No check named",IF(COUNTIFS('DK Ledger'!$B$4:$B$42,H37,'DK Ledger'!$C$4:$C$42,"STP")>0,"Stopped",IF(INDEX('DK Ledger'!$H$4:$H$42,MATCH(H37,'DK Ledger'!$B$4:$B$42,0))="","Not paid by the bank","Paid "&INDEX('DK Ledger'!$H$4:$H$42,MATCH(H37,'DK Ledger'!$B$4:$B$42,0))))) -> No check named | J37: =IF(OR(LEFT(B37,32)="Unconditional Waiver and Release",LEFT(B37,30)="Conditional Waiver and Release"),"Yes","No") -> Yes | K37: =IF(J37="No","None",IF(ISNUMBER(SEARCH("Final Payment",B37)),"Final","Progress")) -> Progress | L37: =IF(J37="No","No",IF(LEFT(B37,13)="Unconditional","Yes",IF(LEFT(I37,4)="Paid","Yes","No"))) -> Yes | M37: =IF(J37="No","Not one of the four statutory forms, releases nothing",IF(LEFT(B37,13)="Unconditional",IF(K37="Final","Effective when signed whether or not paid, section 8138","Effective when signed whether or not paid, section 8134"),IF(LEFT(I37,4)="Paid","Check paid by the bank, effective under section 8124(b)","No evidence of payment under section 8124(b), releases nothing until payment is shown"))) -> Effective when signed whether or not paid, section 8134
A38: Sorensen Landscape Co. | B38: Unconditional Waiver and Release on Progress Payment | C38: 07/31/2026 | D38: =IF(C38="","",DATE(VALUE(RIGHT(C38,4)),VALUE(LEFT(C38,2)),VALUE(MID(C38,4,2)))) -> 46234 | E38: 63320 | F38: None | H38: =IF(G38="","",VALUE(RIGHT(G38,4))) | I38: =IF(G38="","No check named",IF(COUNTIFS('DK Ledger'!$B$4:$B$42,H38,'DK Ledger'!$C$4:$C$42,"STP")>0,"Stopped",IF(INDEX('DK Ledger'!$H$4:$H$42,MATCH(H38,'DK Ledger'!$B$4:$B$42,0))="","Not paid by the bank","Paid "&INDEX('DK Ledger'!$H$4:$H$42,MATCH(H38,'DK Ledger'!$B$4:$B$42,0))))) -> No check named | J38: =IF(OR(LEFT(B38,32)="Unconditional Waiver and Release",LEFT(B38,30)="Conditional Waiver and Release"),"Yes","No") -> Yes | K38: =IF(J38="No","None",IF(ISNUMBER(SEARCH("Final Payment",B38)),"Final","Progress")) -> Progress | L38: =IF(J38="No","No",IF(LEFT(B38,13)="Unconditional","Yes",IF(LEFT(I38,4)="Paid","Yes","No"))) -> Yes | M38: =IF(J38="No","Not one of the four statutory forms, releases nothing",IF(LEFT(B38,13)="Unconditional",IF(K38="Final","Effective when signed whether or not paid, section 8138","Effective when signed whether or not paid, section 8134"),IF(LEFT(I38,4)="Paid","Check paid by the bank, effective under section 8124(b)","No evidence of payment under section 8124(b), releases nothing until payment is shown"))) -> Effective when signed whether or not paid, section 8134
A40: Hedrick & Sons, Foothill Ready Mix, Norcal Rebar, Sierra Pipe & Supply, Inc., and Capitol Wire & Lighting, Inc. have no waiver on file. The Sorensen row is read from the owner's own agreements on the Owner Payments tab, and every other row from the Waiver Log. CHECK_AT_THE_BANK is read from the ledger by check number: a stop payment line against the check, a blank BANK_CLEARED, or the date the check paid. A progress form releases work through its through date and saves retention and unpaid extras, and a final form releases every lien right on the job, retention included (sections 8132 to 8138).

Sheet Amounts
A1: The recorded claims built up from each claimant's own statement, with the part of each the claimant could enforce
A3: CLAIMANT | B3: COMPONENT | C3: KIND | D3: FURNISHED_THROUGH | E3: FURNISHED_SERIAL | F3: AMOUNT | G3: SECURED_BY_THE_LIEN | H3: RELEASED_BY_WAIVER | I3: ENFORCEABLE_PART | J3: READ_FROM | K3: LATER_CHECK | L3: LATER_CHECK_AT_THE_BANK
A4: Tallac Concrete, Inc. | B4: Retention withheld, 5 percent of the $412,000.00 subcontract | C4: Retention | D4: 05/08/2026 | E4: =DATE(VALUE(RIGHT(D4,4)),VALUE(LEFT(D4,2)),VALUE(MID(D4,4,2))) -> 46150 | F4: 20600 | G4: =IF(C4="Charges","No, not work furnished",IF(C4="Request","No, not in the price agreed",IF(E4>=INDEX(Notices!$M$4:$M$18,MATCH(A4,Notices!$A$4:$A$18,0)),"Yes","No, before the notice window"))) -> Yes | H4: =IF(COUNTIFS(Waivers!$A$4:$A$38,A4,Waivers!$L$4:$L$38,"Yes",Waivers!$K$4:$K$38,"Final")>0,"Yes, final form",IF(OR(C4="Retention",C4="Extra",C4="Request"),"No, saved by the progress form",IF(COUNTIFS(Waivers!$A$4:$A$38,A4,Waivers!$L$4:$L$38,"Yes",Waivers!$K$4:$K$38,"Progress",Waivers!$D$4:$D$38,">="&E4)>0,"Yes","No"))) -> No, saved by the progress form | I4: =IF(AND(G4="Yes",LEFT(H4,2)="No",LEFT(L4,4)<>"Paid"),F4,0) -> 20600 | J4: Subcontractors tab; claim 1 item 2 | L4: =IF(K4="","None",IF(COUNTIFS('DK Ledger'!$B$4:$B$42,K4,'DK Ledger'!$C$4:$C$42,"STP")>0,"Stopped",IF(INDEX('DK Ledger'!$H$4:$H$42,MATCH(K4,'DK Ledger'!$B$4:$B$42,0))="","Not paid by the bank","Paid "&INDEX('DK Ledger'!$H$4:$H$42,MATCH(K4,'DK Ledger'!$B$4:$B$42,0))))) -> None
A5: Tallac Concrete, Inc. | B5: Balance of the May 2026 billing after the short payment on check 4436 | C5: Progress | D5: 05/08/2026 | E5: =DATE(VALUE(RIGHT(D5,4)),VALUE(LEFT(D5,2)),VALUE(MID(D5,4,2))) -> 46150 | F5: 12675 | G5: =IF(C5="Charges","No, not work furnished",IF(C5="Request","No, not in the price agreed",IF(E5>=INDEX(Notices!$M$4:$M$18,MATCH(A5,Notices!$A$4:$A$18,0)),"Yes","No, before the notice window"))) -> Yes | H5: =IF(COUNTIFS(Waivers!$A$4:$A$38,A5,Waivers!$L$4:$L$38,"Yes",Waivers!$K$4:$K$38,"Final")>0,"Yes, final form",IF(OR(C5="Retention",C5="Extra",C5="Request"),"No, saved by the progress form",IF(COUNTIFS(Waivers!$A$4:$A$38,A5,Waivers!$L$4:$L$38,"Yes",Waivers!$K$4:$K$38,"Progress",Waivers!$D$4:$D$38,">="&E5)>0,"Yes","No"))) -> No | I5: =IF(AND(G5="Yes",LEFT(H5,2)="No",LEFT(L5,4)<>"Paid"),F5,0) -> 12675 | J5: Claim 1 item 2; lien release letter amount; Reid Castellano email | L5: =IF(K5="","None",IF(COUNTIFS('DK Ledger'!$B$4:$B$42,K5,'DK Ledger'!$C$4:$C$42,"STP")>0,"Stopped",IF(INDEX('DK Ledger'!$H$4:$H$42,MATCH(K5,'DK Ledger'!$B$4:$B$42,0))="","Not paid by the bank","Paid "&INDEX('DK Ledger'!$H$4:$H$42,MATCH(K5,'DK Ledger'!$B$4:$B$42,0))))) -> None
A6: Foothill Ready Mix, Inc. | B6: Ready mixed concrete delivered to Tallac Concrete, April 14 to May 6, 2026 | C6: Materials | D6: 05/06/2026 | E6: =DATE(VALUE(RIGHT(D6,4)),VALUE(LEFT(D6,2)),VALUE(MID(D6,4,2))) -> 46148 | F6: 17204.84 | G6: =IF(C6="Charges","No, not work furnished",IF(C6="Request","No, not in the price agreed",IF(E6>=INDEX(Notices!$M$4:$M$18,MATCH(A6,Notices!$A$4:$A$18,0)),"Yes","No, before the notice window"))) -> Yes | H6: =IF(COUNTIFS(Waivers!$A$4:$A$38,A6,Waivers!$L$4:$L$38,"Yes",Waivers!$K$4:$K$38,"Final")>0,"Yes, final form",IF(OR(C6="Retention",C6="Extra",C6="Request"),"No, saved by the progress form",IF(COUNTIFS(Waivers!$A$4:$A$38,A6,Waivers!$L$4:$L$38,"Yes",Waivers!$K$4:$K$38,"Progress",Waivers!$D$4:$D$38,">="&E6)>0,"Yes","No"))) -> No | I6: =IF(AND(G6="Yes",LEFT(H6,2)="No",LEFT(L6,4)<>"Paid"),F6,0) -> 17204.84 | J6: Claim 2 items 2, 6 and 7 | L6: =IF(K6="","None",IF(COUNTIFS('DK Ledger'!$B$4:$B$42,K6,'DK Ledger'!$C$4:$C$42,"STP")>0,"Stopped",IF(INDEX('DK Ledger'!$H$4:$H$42,MATCH(K6,'DK Ledger'!$B$4:$B$42,0))="","Not paid by the bank","Paid "&INDEX('DK Ledger'!$H$4:$H$42,MATCH(K6,'DK Ledger'!$B$4:$B$42,0))))) -> None
A7: Norcal Rebar & Mesh, LLC | B7: Reinforcing steel and mesh delivered to Tallac Concrete, February 3 to April 21, 2026 | C7: Materials | D7: 04/21/2026 | E7: =DATE(VALUE(RIGHT(D7,4)),VALUE(LEFT(D7,2)),VALUE(MID(D7,4,2))) -> 46133 | F7: 27640 | G7: =IF(C7="Charges","No, not work furnished",IF(C7="Request","No, not in the price agreed",IF(E7>=INDEX(Notices!$M$4:$M$18,MATCH(A7,Notices!$A$4:$A$18,0)),"Yes","No, before the notice window"))) -> Yes | H7: =IF(COUNTIFS(Waivers!$A$4:$A$38,A7,Waivers!$L$4:$L$38,"Yes",Waivers!$K$4:$K$38,"Final")>0,"Yes, final form",IF(OR(C7="Retention",C7="Extra",C7="Request"),"No, saved by the progress form",IF(COUNTIFS(Waivers!$A$4:$A$38,A7,Waivers!$L$4:$L$38,"Yes",Waivers!$K$4:$K$38,"Progress",Waivers!$D$4:$D$38,">="&E7)>0,"Yes","No"))) -> No | I7: =IF(AND(G7="Yes",LEFT(H7,2)="No",LEFT(L7,4)<>"Paid"),F7,0) -> 27640 | J7: Claim 3 items 2 and 7 | L7: =IF(K7="","None",IF(COUNTIFS('DK Ledger'!$B$4:$B$42,K7,'DK Ledger'!$C$4:$C$42,"STP")>0,"Stopped",IF(INDEX('DK Ledger'!$H$4:$H$42,MATCH(K7,'DK Ledger'!$B$4:$B$42,0))="","Not paid by the bank","Paid "&INDEX('DK Ledger'!$H$4:$H$42,MATCH(K7,'DK Ledger'!$B$4:$B$42,0))))) -> None
A8: Hedrick & Sons Building Supply | B8: Invoice S-40702, ticket T-88717, framing lumber, second floor package | C8: Materials | D8: 04/28/2026 | E8: =DATE(VALUE(RIGHT(D8,4)),VALUE(LEFT(D8,2)),VALUE(MID(D8,4,2))) -> 46140 | F8: 11406.25 | G8: =IF(C8="Charges","No, not work furnished",IF(C8="Request","No, not in the price agreed",IF(E8>=INDEX(Notices!$M$4:$M$18,MATCH(A8,Notices!$A$4:$A$18,0)),"Yes","No, before the notice window"))) -> No, before the notice window | H8: =IF(COUNTIFS(Waivers!$A$4:$A$38,A8,Waivers!$L$4:$L$38,"Yes",Waivers!$K$4:$K$38,"Final")>0,"Yes, final form",IF(OR(C8="Retention",C8="Extra",C8="Request"),"No, saved by the progress form",IF(COUNTIFS(Waivers!$A$4:$A$38,A8,Waivers!$L$4:$L$38,"Yes",Waivers!$K$4:$K$38,"Progress",Waivers!$D$4:$D$38,">="&E8)>0,"Yes","No"))) -> No | I8: =IF(AND(G8="Yes",LEFT(H8,2)="No",LEFT(L8,4)<>"Paid"),F8,0) -> 0 | J8: Claim 4 Exhibit A, the Delivered column | L8: =IF(K8="","None",IF(COUNTIFS('DK Ledger'!$B$4:$B$42,K8,'DK Ledger'!$C$4:$C$42,"STP")>0,"Stopped",IF(INDEX('DK Ledger'!$H$4:$H$42,MATCH(K8,'DK Ledger'!$B$4:$B$42,0))="","Not paid by the bank","Paid "&INDEX('DK Ledger'!$H$4:$H$42,MATCH(K8,'DK Ledger'!$B$4:$B$42,0))))) -> None
A9: Hedrick & Sons Building Supply | B9: Invoice S-40915, ticket T-88960, roof trusses, lot 1 | C9: Materials | D9: 05/05/2026 | E9: =DATE(VALUE(RIGHT(D9,4)),VALUE(LEFT(D9,2)),VALUE(MID(D9,4,2))) -> 46147 | F9: 6930 | G9: =IF(C9="Charges","No, not work furnished",IF(C9="Request","No, not in the price agreed",IF(E9>=INDEX(Notices!$M$4:$M$18,MATCH(A9,Notices!$A$4:$A$18,0)),"Yes","No, before the notice window"))) -> No, before the notice window | H9: =IF(COUNTIFS(Waivers!$A$4:$A$38,A9,Waivers!$L$4:$L$38,"Yes",Waivers!$K$4:$K$38,"Final")>0,"Yes, final form",IF(OR(C9="Retention",C9="Extra",C9="Request"),"No, saved by the progress form",IF(COUNTIFS(Waivers!$A$4:$A$38,A9,Waivers!$L$4:$L$38,"Yes",Waivers!$K$4:$K$38,"Progress",Waivers!$D$4:$D$38,">="&E9)>0,"Yes","No"))) -> No | I9: =IF(AND(G9="Yes",LEFT(H9,2)="No",LEFT(L9,4)<>"Paid"),F9,0) -> 0 | J9: Claim 4 Exhibit A, the Delivered column | L9: =IF(K9="","None",IF(COUNTIFS('DK Ledger'!$B$4:$B$42,K9,'DK Ledger'!$C$4:$C$42,"STP")>0,"Stopped",IF(INDEX('DK Ledger'!$H$4:$H$42,MATCH(K9,'DK Ledger'!$B$4:$B$42,0))="","Not paid by the bank","Paid "&INDEX('DK Ledger'!$H$4:$H$42,MATCH(K9,'DK Ledger'!$B$4:$B$42,0))))) -> None
A10: Hedrick & Sons Building Supply | B10: Invoice S-41188, ticket T-89074, roof trusses, lot 2 | C10: Materials | D10: 05/08/2026 | E10: =DATE(VALUE(RIGHT(D10,4)),VALUE(LEFT(D10,2)),VALUE(MID(D10,4,2))) -> 46150 | F10: 4890.5 | G10: =IF(C10="Charges","No, not work furnished",IF(C10="Request","No, not in the price agreed",IF(E10>=INDEX(Notices!$M$4:$M$18,MATCH(A10,Notices!$A$4:$A$18,0)),"Yes","No, before the notice window"))) -> No, before the notice window | H10: =IF(COUNTIFS(Waivers!$A$4:$A$38,A10,Waivers!$L$4:$L$38,"Yes",Waivers!$K$4:$K$38,"Final")>0,"Yes, final form",IF(OR(C10="Retention",C10="Extra",C10="Request"),"No, saved by the progress form",IF(COUNTIFS(Waivers!$A$4:$A$38,A10,Waivers!$L$4:$L$38,"Yes",Waivers!$K$4:$K$38,"Progress",Waivers!$D$4:$D$38,">="&E10)>0,"Yes","No"))) -> No | I10: =IF(AND(G10="Yes",LEFT(H10,2)="No",LEFT(L10,4)<>"Paid"),F10,0) -> 0 | J10: Claim 4 Exhibit A, the Delivered column | L10: =IF(K10="","None",IF(COUNTIFS('DK Ledger'!$B$4:$B$42,K10,'DK Ledger'!$C$4:$C$42,"STP")>0,"Stopped",IF(INDEX('DK Ledger'!$H$4:$H$42,MATCH(K10,'DK Ledger'!$B$4:$B$42,0))="","Not paid by the bank","Paid "&INDEX('DK Ledger'!$H$4:$H$42,MATCH(K10,'DK Ledger'!$B$4:$B$42,0))))) -> None
A11: Hedrick & Sons Building Supply | B11: Invoice S-41188, ticket T-89131, roof sheathing | C11: Materials | D11: 05/12/2026 | E11: =DATE(VALUE(RIGHT(D11,4)),VALUE(LEFT(D11,2)),VALUE(MID(D11,4,2))) -> 46154 | F11: 3228.25 | G11: =IF(C11="Charges","No, not work furnished",IF(C11="Request","No, not in the price agreed",IF(E11>=INDEX(Notices!$M$4:$M$18,MATCH(A11,Notices!$A$4:$A$18,0)),"Yes","No, before the notice window"))) -> Yes | H11: =IF(COUNTIFS(Waivers!$A$4:$A$38,A11,Waivers!$L$4:$L$38,"Yes",Waivers!$K$4:$K$38,"Final")>0,"Yes, final form",IF(OR(C11="Retention",C11="Extra",C11="Request"),"No, saved by the progress form",IF(COUNTIFS(Waivers!$A$4:$A$38,A11,Waivers!$L$4:$L$38,"Yes",Waivers!$K$4:$K$38,"Progress",Waivers!$D$4:$D$38,">="&E11)>0,"Yes","No"))) -> No | I11: =IF(AND(G11="Yes",LEFT(H11,2)="No",LEFT(L11,4)<>"Paid"),F11,0) -> 3228.25 | J11: Claim 4 Exhibit A, the Delivered column | L11: =IF(K11="","None",IF(COUNTIFS('DK Ledger'!$B$4:$B$42,K11,'DK Ledger'!$C$4:$C$42,"STP")>0,"Stopped",IF(INDEX('DK Ledger'!$H$4:$H$42,MATCH(K11,'DK Ledger'!$B$4:$B$42,0))="","Not paid by the bank","Paid "&INDEX('DK Ledger'!$H$4:$H$42,MATCH(K11,'DK Ledger'!$B$4:$B$42,0))))) -> None
A12: Hedrick & Sons Building Supply | B12: Invoice S-41420, ticket T-89466, sheathing and blocking, roof | C12: Materials | D12: 05/26/2026 | E12: =DATE(VALUE(RIGHT(D12,4)),VALUE(LEFT(D12,2)),VALUE(MID(D12,4,2))) -> 46168 | F12: 9447.2 | G12: =IF(C12="Charges","No, not work furnished",IF(C12="Request","No, not in the price agreed",IF(E12>=INDEX(Notices!$M$4:$M$18,MATCH(A12,Notices!$A$4:$A$18,0)),"Yes","No, before the notice window"))) -> Yes | H12: =IF(COUNTIFS(Waivers!$A$4:$A$38,A12,Waivers!$L$4:$L$38,"Yes",Waivers!$K$4:$K$38,"Final")>0,"Yes, final form",IF(OR(C12="Retention",C12="Extra",C12="Request"),"No, saved by the progress form",IF(COUNTIFS(Waivers!$A$4:$A$38,A12,Waivers!$L$4:$L$38,"Yes",Waivers!$K$4:$K$38,"Progress",Waivers!$D$4:$D$38,">="&E12)>0,"Yes","No"))) -> No | I12: =IF(AND(G12="Yes",LEFT(H12,2)="No",LEFT(L12,4)<>"Paid"),F12,0) -> 9447.2 | J12: Claim 4 Exhibit A, the Delivered column | L12: =IF(K12="","None",IF(COUNTIFS('DK Ledger'!$B$4:$B$42,K12,'DK Ledger'!$C$4:$C$42,"STP")>0,"Stopped",IF(INDEX('DK Ledger'!$H$4:$H$42,MATCH(K12,'DK Ledger'!$B$4:$B$42,0))="","Not paid by the bank","Paid "&INDEX('DK Ledger'!$H$4:$H$42,MATCH(K12,'DK Ledger'!$B$4:$B$42,0))))) -> None
A13: Hedrick & Sons Building Supply | B13: Invoice S-41733, ticket T-89802, exterior sheathing and weather barrier | C13: Materials | D13: 06/09/2026 | E13: =DATE(VALUE(RIGHT(D13,4)),VALUE(LEFT(D13,2)),VALUE(MID(D13,4,2))) -> 46182 | F13: 10220.4 | G13: =IF(C13="Charges","No, not work furnished",IF(C13="Request","No, not in the price agreed",IF(E13>=INDEX(Notices!$M$4:$M$18,MATCH(A13,Notices!$A$4:$A$18,0)),"Yes","No, before the notice window"))) -> Yes | H13: =IF(COUNTIFS(Waivers!$A$4:$A$38,A13,Waivers!$L$4:$L$38,"Yes",Waivers!$K$4:$K$38,"Final")>0,"Yes, final form",IF(OR(C13="Retention",C13="Extra",C13="Request"),"No, saved by the progress form",IF(COUNTIFS(Waivers!$A$4:$A$38,A13,Waivers!$L$4:$L$38,"Yes",Waivers!$K$4:$K$38,"Progress",Waivers!$D$4:$D$38,">="&E13)>0,"Yes","No"))) -> No | I13: =IF(AND(G13="Yes",LEFT(H13,2)="No",LEFT(L13,4)<>"Paid"),F13,0) -> 10220.4 | J13: Claim 4 Exhibit A, the Delivered column | L13: =IF(K13="","None",IF(COUNTIFS('DK Ledger'!$B$4:$B$42,K13,'DK Ledger'!$C$4:$C$42,"STP")>0,"Stopped",IF(INDEX('DK Ledger'!$H$4:$H$42,MATCH(K13,'DK Ledger'!$B$4:$B$42,0))="","Not paid by the bank","Paid "&INDEX('DK Ledger'!$H$4:$H$42,MATCH(K13,'DK Ledger'!$B$4:$B$42,0))))) -> None
A14: Hedrick & Sons Building Supply | B14: Invoice S-41990, ticket T-90155, backing, blocking, and fastener package | C14: Materials | D14: 06/23/2026 | E14: =DATE(VALUE(RIGHT(D14,4)),VALUE(LEFT(D14,2)),VALUE(MID(D14,4,2))) -> 46196 | F14: 6195.84 | G14: =IF(C14="Charges","No, not work furnished",IF(C14="Request","No, not in the price agreed",IF(E14>=INDEX(Notices!$M$4:$M$18,MATCH(A14,Notices!$A$4:$A$18,0)),"Yes","No, before the notice window"))) -> Yes | H14: =IF(COUNTIFS(Waivers!$A$4:$A$38,A14,Waivers!$L$4:$L$38,"Yes",Waivers!$K$4:$K$38,"Final")>0,"Yes, final form",IF(OR(C14="Retention",C14="Extra",C14="Request"),"No, saved by the progress form",IF(COUNTIFS(Waivers!$A$4:$A$38,A14,Waivers!$L$4:$L$38,"Yes",Waivers!$K$4:$K$38,"Progress",Waivers!$D$4:$D$38,">="&E14)>0,"Yes","No"))) -> No | I14: =IF(AND(G14="Yes",LEFT(H14,2)="No",LEFT(L14,4)<>"Paid"),F14,0) -> 6195.84 | J14: Claim 4 Exhibit A, the Delivered column | L14: =IF(K14="","None",IF(COUNTIFS('DK Ledger'!$B$4:$B$42,K14,'DK Ledger'!$C$4:$C$42,"STP")>0,"Stopped",IF(INDEX('DK Ledger'!$H$4:$H$42,MATCH(K14,'DK Ledger'!$B$4:$B$42,0))="","Not paid by the bank","Paid "&INDEX('DK Ledger'!$H$4:$H$42,MATCH(K14,'DK Ledger'!$B$4:$B$42,0))))) -> None
A15: Hedrick & Sons Building Supply | B15: Finance charges at 1.5 percent per month through 08/31/2026 | C15: Charges | D15: 08/31/2026 | E15: =DATE(VALUE(RIGHT(D15,4)),VALUE(LEFT(D15,2)),VALUE(MID(D15,4,2))) -> 46265 | F15: 1912.37 | G15: =IF(C15="Charges","No, not work furnished",IF(C15="Request","No, not in the price agreed",IF(E15>=INDEX(Notices!$M$4:$M$18,MATCH(A15,Notices!$A$4:$A$18,0)),"Yes","No, before the notice window"))) -> No, not work furnished | H15: =IF(COUNTIFS(Waivers!$A$4:$A$38,A15,Waivers!$L$4:$L$38,"Yes",Waivers!$K$4:$K$38,"Final")>0,"Yes, final form",IF(OR(C15="Retention",C15="Extra",C15="Request"),"No, saved by the progress form",IF(COUNTIFS(Waivers!$A$4:$A$38,A15,Waivers!$L$4:$L$38,"Yes",Waivers!$K$4:$K$38,"Progress",Waivers!$D$4:$D$38,">="&E15)>0,"Yes","No"))) -> No | I15: =IF(AND(G15="Yes",LEFT(H15,2)="No",LEFT(L15,4)<>"Paid"),F15,0) -> 0 | J15: Claim 4 Exhibit A, line FC-0831 | L15: =IF(K15="","None",IF(COUNTIFS('DK Ledger'!$B$4:$B$42,K15,'DK Ledger'!$C$4:$C$42,"STP")>0,"Stopped",IF(INDEX('DK Ledger'!$H$4:$H$42,MATCH(K15,'DK Ledger'!$B$4:$B$42,0))="","Not paid by the bank","Paid "&INDEX('DK Ledger'!$H$4:$H$42,MATCH(K15,'DK Ledger'!$B$4:$B$42,0))))) -> None
A16: Abrego Glass & Glazing | B16: Retention withheld, 5 percent of the $186,900.00 subcontract | C16: Retention | D16: 07/17/2026 | E16: =DATE(VALUE(RIGHT(D16,4)),VALUE(LEFT(D16,2)),VALUE(MID(D16,4,2))) -> 46220 | F16: 9345 | G16: =IF(C16="Charges","No, not work furnished",IF(C16="Request","No, not in the price agreed",IF(E16>=INDEX(Notices!$M$4:$M$18,MATCH(A16,Notices!$A$4:$A$18,0)),"Yes","No, before the notice window"))) -> Yes | H16: =IF(COUNTIFS(Waivers!$A$4:$A$38,A16,Waivers!$L$4:$L$38,"Yes",Waivers!$K$4:$K$38,"Final")>0,"Yes, final form",IF(OR(C16="Retention",C16="Extra",C16="Request"),"No, saved by the progress form",IF(COUNTIFS(Waivers!$A$4:$A$38,A16,Waivers!$L$4:$L$38,"Yes",Waivers!$K$4:$K$38,"Progress",Waivers!$D$4:$D$38,">="&E16)>0,"Yes","No"))) -> No, saved by the progress form | I16: =IF(AND(G16="Yes",LEFT(H16,2)="No",LEFT(L16,4)<>"Paid"),F16,0) -> 9345 | J16: Claim 5 item 6; Subcontractors tab | L16: =IF(K16="","None",IF(COUNTIFS('DK Ledger'!$B$4:$B$42,K16,'DK Ledger'!$C$4:$C$42,"STP")>0,"Stopped",IF(INDEX('DK Ledger'!$H$4:$H$42,MATCH(K16,'DK Ledger'!$B$4:$B$42,0))="","Not paid by the bank","Paid "&INDEX('DK Ledger'!$H$4:$H$42,MATCH(K16,'DK Ledger'!$B$4:$B$42,0))))) -> None
A17: Kastner Mechanical Contractors, Inc. | B17: Progress payment for the period ending July 31, 2026 | C17: Progress | D17: 07/31/2026 | E17: =DATE(VALUE(RIGHT(D17,4)),VALUE(LEFT(D17,2)),VALUE(MID(D17,4,2))) -> 46234 | F17: 73910 | G17: =IF(C17="Charges","No, not work furnished",IF(C17="Request","No, not in the price agreed",IF(E17>=INDEX(Notices!$M$4:$M$18,MATCH(A17,Notices!$A$4:$A$18,0)),"Yes","No, before the notice window"))) -> Yes | H17: =IF(COUNTIFS(Waivers!$A$4:$A$38,A17,Waivers!$L$4:$L$38,"Yes",Waivers!$K$4:$K$38,"Final")>0,"Yes, final form",IF(OR(C17="Retention",C17="Extra",C17="Request"),"No, saved by the progress form",IF(COUNTIFS(Waivers!$A$4:$A$38,A17,Waivers!$L$4:$L$38,"Yes",Waivers!$K$4:$K$38,"Progress",Waivers!$D$4:$D$38,">="&E17)>0,"Yes","No"))) -> No | I17: =IF(AND(G17="Yes",LEFT(H17,2)="No",LEFT(L17,4)<>"Paid"),F17,0) -> 0 | J17: Claim 6 item 6; DK Ledger checks 4460 and 4474 | K17: 4474 | L17: =IF(K17="","None",IF(COUNTIFS('DK Ledger'!$B$4:$B$42,K17,'DK Ledger'!$C$4:$C$42,"STP")>0,"Stopped",IF(INDEX('DK Ledger'!$H$4:$H$42,MATCH(K17,'DK Ledger'!$B$4:$B$42,0))="","Not paid by the bank","Paid "&INDEX('DK Ledger'!$H$4:$H$42,MATCH(K17,'DK Ledger'!$B$4:$B$42,0))))) -> Paid 09/23/2026
A18: Kastner Mechanical Contractors, Inc. | B18: Final billing for the period ending August 11, 2026 | C18: Progress | D18: 08/11/2026 | E18: =DATE(VALUE(RIGHT(D18,4)),VALUE(LEFT(D18,2)),VALUE(MID(D18,4,2))) -> 46245 | F18: 63005 | G18: =IF(C18="Charges","No, not work furnished",IF(C18="Request","No, not in the price agreed",IF(E18>=INDEX(Notices!$M$4:$M$18,MATCH(A18,Notices!$A$4:$A$18,0)),"Yes","No, before the notice window"))) -> Yes | H18: =IF(COUNTIFS(Waivers!$A$4:$A$38,A18,Waivers!$L$4:$L$38,"Yes",Waivers!$K$4:$K$38,"Final")>0,"Yes, final form",IF(OR(C18="Retention",C18="Extra",C18="Request"),"No, saved by the progress form",IF(COUNTIFS(Waivers!$A$4:$A$38,A18,Waivers!$L$4:$L$38,"Yes",Waivers!$K$4:$K$38,"Progress",Waivers!$D$4:$D$38,">="&E18)>0,"Yes","No"))) -> No | I18: =IF(AND(G18="Yes",LEFT(H18,2)="No",LEFT(L18,4)<>"Paid"),F18,0) -> 63005 | J18: Claim 6 item 6 | L18: =IF(K18="","None",IF(COUNTIFS('DK Ledger'!$B$4:$B$42,K18,'DK Ledger'!$C$4:$C$42,"STP")>0,"Stopped",IF(INDEX('DK Ledger'!$H$4:$H$42,MATCH(K18,'DK Ledger'!$B$4:$B$42,0))="","Not paid by the bank","Paid "&INDEX('DK Ledger'!$H$4:$H$42,MATCH(K18,'DK Ledger'!$B$4:$B$42,0))))) -> None
A19: Kastner Mechanical Contractors, Inc. | B19: Retention withheld, 5 percent of the $444,600.00 subcontract | C19: Retention | D19: 08/10/2026 | E19: =DATE(VALUE(RIGHT(D19,4)),VALUE(LEFT(D19,2)),VALUE(MID(D19,4,2))) -> 46244 | F19: 22230 | G19: =IF(C19="Charges","No, not work furnished",IF(C19="Request","No, not in the price agreed",IF(E19>=INDEX(Notices!$M$4:$M$18,MATCH(A19,Notices!$A$4:$A$18,0)),"Yes","No, before the notice window"))) -> Yes | H19: =IF(COUNTIFS(Waivers!$A$4:$A$38,A19,Waivers!$L$4:$L$38,"Yes",Waivers!$K$4:$K$38,"Final")>0,"Yes, final form",IF(OR(C19="Retention",C19="Extra",C19="Request"),"No, saved by the progress form",IF(COUNTIFS(Waivers!$A$4:$A$38,A19,Waivers!$L$4:$L$38,"Yes",Waivers!$K$4:$K$38,"Progress",Waivers!$D$4:$D$38,">="&E19)>0,"Yes","No"))) -> No, saved by the progress form | I19: =IF(AND(G19="Yes",LEFT(H19,2)="No",LEFT(L19,4)<>"Paid"),F19,0) -> 22230 | J19: Claim 6 item 6; Subcontractors tab | L19: =IF(K19="","None",IF(COUNTIFS('DK Ledger'!$B$4:$B$42,K19,'DK Ledger'!$C$4:$C$42,"STP")>0,"Stopped",IF(INDEX('DK Ledger'!$H$4:$H$42,MATCH(K19,'DK Ledger'!$B$4:$B$42,0))="","Not paid by the bank","Paid "&INDEX('DK Ledger'!$H$4:$H$42,MATCH(K19,'DK Ledger'!$B$4:$B$42,0))))) -> None
A20: Bautista Painting Co. | B20: Progress payment for the period ending July 31, 2026, no check issued | C20: Progress | D20: 07/31/2026 | E20: =DATE(VALUE(RIGHT(D20,4)),VALUE(LEFT(D20,2)),VALUE(MID(D20,4,2))) -> 46234 | F20: 38475 | G20: =IF(C20="Charges","No, not work furnished",IF(C20="Request","No, not in the price agreed",IF(E20>=INDEX(Notices!$M$4:$M$18,MATCH(A20,Notices!$A$4:$A$18,0)),"Yes","No, before the notice window"))) -> Yes | H20: =IF(COUNTIFS(Waivers!$A$4:$A$38,A20,Waivers!$L$4:$L$38,"Yes",Waivers!$K$4:$K$38,"Final")>0,"Yes, final form",IF(OR(C20="Retention",C20="Extra",C20="Request"),"No, saved by the progress form",IF(COUNTIFS(Waivers!$A$4:$A$38,A20,Waivers!$L$4:$L$38,"Yes",Waivers!$K$4:$K$38,"Progress",Waivers!$D$4:$D$38,">="&E20)>0,"Yes","No"))) -> Yes | I20: =IF(AND(G20="Yes",LEFT(H20,2)="No",LEFT(L20,4)<>"Paid"),F20,0) -> 0 | J20: Claim 7 item 6; Reid Castellano email | L20: =IF(K20="","None",IF(COUNTIFS('DK Ledger'!$B$4:$B$42,K20,'DK Ledger'!$C$4:$C$42,"STP")>0,"Stopped",IF(INDEX('DK Ledger'!$H$4:$H$42,MATCH(K20,'DK Ledger'!$B$4:$B$42,0))="","Not paid by the bank","Paid "&INDEX('DK Ledger'!$H$4:$H$42,MATCH(K20,'DK Ledger'!$B$4:$B$42,0))))) -> None
A21: Bautista Painting Co. | B21: Retention withheld, 5 percent of the $76,900.00 subcontract | C21: Retention | D21: 08/07/2026 | E21: =DATE(VALUE(RIGHT(D21,4)),VALUE(LEFT(D21,2)),VALUE(MID(D21,4,2))) -> 46241 | F21: 3845 | G21: =IF(C21="Charges","No, not work furnished",IF(C21="Request","No, not in the price agreed",IF(E21>=INDEX(Notices!$M$4:$M$18,MATCH(A21,Notices!$A$4:$A$18,0)),"Yes","No, before the notice window"))) -> Yes | H21: =IF(COUNTIFS(Waivers!$A$4:$A$38,A21,Waivers!$L$4:$L$38,"Yes",Waivers!$K$4:$K$38,"Final")>0,"Yes, final form",IF(OR(C21="Retention",C21="Extra",C21="Request"),"No, saved by the progress form",IF(COUNTIFS(Waivers!$A$4:$A$38,A21,Waivers!$L$4:$L$38,"Yes",Waivers!$K$4:$K$38,"Progress",Waivers!$D$4:$D$38,">="&E21)>0,"Yes","No"))) -> No, saved by the progress form | I21: =IF(AND(G21="Yes",LEFT(H21,2)="No",LEFT(L21,4)<>"Paid"),F21,0) -> 3845 | J21: Claim 7 item 6; Subcontractors tab | L21: =IF(K21="","None",IF(COUNTIFS('DK Ledger'!$B$4:$B$42,K21,'DK Ledger'!$C$4:$C$42,"STP")>0,"Stopped",IF(INDEX('DK Ledger'!$H$4:$H$42,MATCH(K21,'DK Ledger'!$B$4:$B$42,0))="","Not paid by the bank","Paid "&INDEX('DK Ledger'!$H$4:$H$42,MATCH(K21,'DK Ledger'!$B$4:$B$42,0))))) -> None
A22: Bautista Painting Co. | B22: Invoice BP-2262, change order 1 punch list work August 1 to August 7, 2026 | C22: Extra | D22: 08/07/2026 | E22: =DATE(VALUE(RIGHT(D22,4)),VALUE(LEFT(D22,2)),VALUE(MID(D22,4,2))) -> 46241 | F22: 4280 | G22: =IF(C22="Charges","No, not work furnished",IF(C22="Request","No, not in the price agreed",IF(E22>=INDEX(Notices!$M$4:$M$18,MATCH(A22,Notices!$A$4:$A$18,0)),"Yes","No, before the notice window"))) -> Yes | H22: =IF(COUNTIFS(Waivers!$A$4:$A$38,A22,Waivers!$L$4:$L$38,"Yes",Waivers!$K$4:$K$38,"Final")>0,"Yes, final form",IF(OR(C22="Retention",C22="Extra",C22="Request"),"No, saved by the progress form",IF(COUNTIFS(Waivers!$A$4:$A$38,A22,Waivers!$L$4:$L$38,"Yes",Waivers!$K$4:$K$38,"Progress",Waivers!$D$4:$D$38,">="&E22)>0,"Yes","No"))) -> No, saved by the progress form | I22: =IF(AND(G22="Yes",LEFT(H22,2)="No",LEFT(L22,4)<>"Paid"),F22,0) -> 4280 | J22: Claim 7 item 6; Subcontractors tab, change order approved | L22: =IF(K22="","None",IF(COUNTIFS('DK Ledger'!$B$4:$B$42,K22,'DK Ledger'!$C$4:$C$42,"STP")>0,"Stopped",IF(INDEX('DK Ledger'!$H$4:$H$42,MATCH(K22,'DK Ledger'!$B$4:$B$42,0))="","Not paid by the bank","Paid "&INDEX('DK Ledger'!$H$4:$H$42,MATCH(K22,'DK Ledger'!$B$4:$B$42,0))))) -> None
A23: Fenwick Roofing, Inc. | B23: Retention withheld, 5 percent of the $298,750.00 subcontract | C23: Retention | D23: 07/10/2026 | E23: =DATE(VALUE(RIGHT(D23,4)),VALUE(LEFT(D23,2)),VALUE(MID(D23,4,2))) -> 46213 | F23: 14937.5 | G23: =IF(C23="Charges","No, not work furnished",IF(C23="Request","No, not in the price agreed",IF(E23>=INDEX(Notices!$M$4:$M$18,MATCH(A23,Notices!$A$4:$A$18,0)),"Yes","No, before the notice window"))) -> Yes | H23: =IF(COUNTIFS(Waivers!$A$4:$A$38,A23,Waivers!$L$4:$L$38,"Yes",Waivers!$K$4:$K$38,"Final")>0,"Yes, final form",IF(OR(C23="Retention",C23="Extra",C23="Request"),"No, saved by the progress form",IF(COUNTIFS(Waivers!$A$4:$A$38,A23,Waivers!$L$4:$L$38,"Yes",Waivers!$K$4:$K$38,"Progress",Waivers!$D$4:$D$38,">="&E23)>0,"Yes","No"))) -> Yes, final form | I23: =IF(AND(G23="Yes",LEFT(H23,2)="No",LEFT(L23,4)<>"Paid"),F23,0) -> 0 | J23: Claim 8 item 6; Subcontractors tab | L23: =IF(K23="","None",IF(COUNTIFS('DK Ledger'!$B$4:$B$42,K23,'DK Ledger'!$C$4:$C$42,"STP")>0,"Stopped",IF(INDEX('DK Ledger'!$H$4:$H$42,MATCH(K23,'DK Ledger'!$B$4:$B$42,0))="","Not paid by the bank","Paid "&INDEX('DK Ledger'!$H$4:$H$42,MATCH(K23,'DK Ledger'!$B$4:$B$42,0))))) -> None
A24: Lindqvist Fire Protection | B24: Retention withheld, 5 percent of the $142,650.00 subcontract | C24: Retention | D24: 06/30/2026 | E24: =DATE(VALUE(RIGHT(D24,4)),VALUE(LEFT(D24,2)),VALUE(MID(D24,4,2))) -> 46203 | F24: 7132.5 | G24: =IF(C24="Charges","No, not work furnished",IF(C24="Request","No, not in the price agreed",IF(E24>=INDEX(Notices!$M$4:$M$18,MATCH(A24,Notices!$A$4:$A$18,0)),"Yes","No, before the notice window"))) -> Yes | H24: =IF(COUNTIFS(Waivers!$A$4:$A$38,A24,Waivers!$L$4:$L$38,"Yes",Waivers!$K$4:$K$38,"Final")>0,"Yes, final form",IF(OR(C24="Retention",C24="Extra",C24="Request"),"No, saved by the progress form",IF(COUNTIFS(Waivers!$A$4:$A$38,A24,Waivers!$L$4:$L$38,"Yes",Waivers!$K$4:$K$38,"Progress",Waivers!$D$4:$D$38,">="&E24)>0,"Yes","No"))) -> No, saved by the progress form | I24: =IF(AND(G24="Yes",LEFT(H24,2)="No",LEFT(L24,4)<>"Paid"),F24,0) -> 7132.5 | J24: Claim 9 item 6; Subcontractors tab | L24: =IF(K24="","None",IF(COUNTIFS('DK Ledger'!$B$4:$B$42,K24,'DK Ledger'!$C$4:$C$42,"STP")>0,"Stopped",IF(INDEX('DK Ledger'!$H$4:$H$42,MATCH(K24,'DK Ledger'!$B$4:$B$42,0))="","Not paid by the bank","Paid "&INDEX('DK Ledger'!$H$4:$H$42,MATCH(K24,'DK Ledger'!$B$4:$B$42,0))))) -> None
A25: Lindqvist Fire Protection | B25: Change order request 3, fourteen added heads on the tenant side, June 22 to June 30, 2026, never approved | C25: Request | D25: 06/30/2026 | E25: =DATE(VALUE(RIGHT(D25,4)),VALUE(LEFT(D25,2)),VALUE(MID(D25,4,2))) -> 46203 | F25: 9467.5 | G25: =IF(C25="Charges","No, not work furnished",IF(C25="Request","No, not in the price agreed",IF(E25>=INDEX(Notices!$M$4:$M$18,MATCH(A25,Notices!$A$4:$A$18,0)),"Yes","No, before the notice window"))) -> No, not in the price agreed | H25: =IF(COUNTIFS(Waivers!$A$4:$A$38,A25,Waivers!$L$4:$L$38,"Yes",Waivers!$K$4:$K$38,"Final")>0,"Yes, final form",IF(OR(C25="Retention",C25="Extra",C25="Request"),"No, saved by the progress form",IF(COUNTIFS(Waivers!$A$4:$A$38,A25,Waivers!$L$4:$L$38,"Yes",Waivers!$K$4:$K$38,"Progress",Waivers!$D$4:$D$38,">="&E25)>0,"Yes","No"))) -> No, saved by the progress form | I25: =IF(AND(G25="Yes",LEFT(H25,2)="No",LEFT(L25,4)<>"Paid"),F25,0) -> 0 | J25: Claim 9 item 6; Subcontractors tab, no change order; Reid Castellano email | L25: =IF(K25="","None",IF(COUNTIFS('DK Ledger'!$B$4:$B$42,K25,'DK Ledger'!$C$4:$C$42,"STP")>0,"Stopped",IF(INDEX('DK Ledger'!$H$4:$H$42,MATCH(K25,'DK Ledger'!$B$4:$B$42,0))="","Not paid by the bank","Paid "&INDEX('DK Ledger'!$H$4:$H$42,MATCH(K25,'DK Ledger'!$B$4:$B$42,0))))) -> None
A26: Sierra Pipe & Supply, Inc. | B26: Invoice F-20318, ticket R-51022, underground DWV pipe and fittings | C26: Materials | D26: 02/23/2026 | E26: =DATE(VALUE(RIGHT(D26,4)),VALUE(LEFT(D26,2)),VALUE(MID(D26,4,2))) -> 46076 | F26: 4316.2 | G26: =IF(C26="Charges","No, not work furnished",IF(C26="Request","No, not in the price agreed",IF(E26>=INDEX(Notices!$M$4:$M$18,MATCH(A26,Notices!$A$4:$A$18,0)),"Yes","No, before the notice window"))) -> No, before the notice window | H26: =IF(COUNTIFS(Waivers!$A$4:$A$38,A26,Waivers!$L$4:$L$38,"Yes",Waivers!$K$4:$K$38,"Final")>0,"Yes, final form",IF(OR(C26="Retention",C26="Extra",C26="Request"),"No, saved by the progress form",IF(COUNTIFS(Waivers!$A$4:$A$38,A26,Waivers!$L$4:$L$38,"Yes",Waivers!$K$4:$K$38,"Progress",Waivers!$D$4:$D$38,">="&E26)>0,"Yes","No"))) -> No | I26: =IF(AND(G26="Yes",LEFT(H26,2)="No",LEFT(L26,4)<>"Paid"),F26,0) -> 0 | J26: Claim 10 Exhibit A, the Delivered column | L26: =IF(K26="","None",IF(COUNTIFS('DK Ledger'!$B$4:$B$42,K26,'DK Ledger'!$C$4:$C$42,"STP")>0,"Stopped",IF(INDEX('DK Ledger'!$H$4:$H$42,MATCH(K26,'DK Ledger'!$B$4:$B$42,0))="","Not paid by the bank","Paid "&INDEX('DK Ledger'!$H$4:$H$42,MATCH(K26,'DK Ledger'!$B$4:$B$42,0))))) -> None
A27: Sierra Pipe & Supply, Inc. | B27: Invoice F-22315, ticket R-53240, plumbing fixtures, first release | C27: Materials | D27: 07/14/2026 | E27: =DATE(VALUE(RIGHT(D27,4)),VALUE(LEFT(D27,2)),VALUE(MID(D27,4,2))) -> 46217 | F27: 6842.3 | G27: =IF(C27="Charges","No, not work furnished",IF(C27="Request","No, not in the price agreed",IF(E27>=INDEX(Notices!$M$4:$M$18,MATCH(A27,Notices!$A$4:$A$18,0)),"Yes","No, before the notice window"))) -> Yes | H27: =IF(COUNTIFS(Waivers!$A$4:$A$38,A27,Waivers!$L$4:$L$38,"Yes",Waivers!$K$4:$K$38,"Final")>0,"Yes, final form",IF(OR(C27="Retention",C27="Extra",C27="Request"),"No, saved by the progress form",IF(COUNTIFS(Waivers!$A$4:$A$38,A27,Waivers!$L$4:$L$38,"Yes",Waivers!$K$4:$K$38,"Progress",Waivers!$D$4:$D$38,">="&E27)>0,"Yes","No"))) -> No | I27: =IF(AND(G27="Yes",LEFT(H27,2)="No",LEFT(L27,4)<>"Paid"),F27,0) -> 6842.3 | J27: Claim 10 Exhibit A, the Delivered column | L27: =IF(K27="","None",IF(COUNTIFS('DK Ledger'!$B$4:$B$42,K27,'DK Ledger'!$C$4:$C$42,"STP")>0,"Stopped",IF(INDEX('DK Ledger'!$H$4:$H$42,MATCH(K27,'DK Ledger'!$B$4:$B$42,0))="","Not paid by the bank","Paid "&INDEX('DK Ledger'!$H$4:$H$42,MATCH(K27,'DK Ledger'!$B$4:$B$42,0))))) -> None
A28: Sierra Pipe & Supply, Inc. | B28: Invoice F-22488, ticket R-53411, plumbing fixtures, second release, and trim | C28: Materials | D28: 07/27/2026 | E28: =DATE(VALUE(RIGHT(D28,4)),VALUE(LEFT(D28,2)),VALUE(MID(D28,4,2))) -> 46230 | F28: 5120.64 | G28: =IF(C28="Charges","No, not work furnished",IF(C28="Request","No, not in the price agreed",IF(E28>=INDEX(Notices!$M$4:$M$18,MATCH(A28,Notices!$A$4:$A$18,0)),"Yes","No, before the notice window"))) -> Yes | H28: =IF(COUNTIFS(Waivers!$A$4:$A$38,A28,Waivers!$L$4:$L$38,"Yes",Waivers!$K$4:$K$38,"Final")>0,"Yes, final form",IF(OR(C28="Retention",C28="Extra",C28="Request"),"No, saved by the progress form",IF(COUNTIFS(Waivers!$A$4:$A$38,A28,Waivers!$L$4:$L$38,"Yes",Waivers!$K$4:$K$38,"Progress",Waivers!$D$4:$D$38,">="&E28)>0,"Yes","No"))) -> No | I28: =IF(AND(G28="Yes",LEFT(H28,2)="No",LEFT(L28,4)<>"Paid"),F28,0) -> 5120.64 | J28: Claim 10 Exhibit A, the Delivered column | L28: =IF(K28="","None",IF(COUNTIFS('DK Ledger'!$B$4:$B$42,K28,'DK Ledger'!$C$4:$C$42,"STP")>0,"Stopped",IF(INDEX('DK Ledger'!$H$4:$H$42,MATCH(K28,'DK Ledger'!$B$4:$B$42,0))="","Not paid by the bank","Paid "&INDEX('DK Ledger'!$H$4:$H$42,MATCH(K28,'DK Ledger'!$B$4:$B$42,0))))) -> None
A29: Sierra Pipe & Supply, Inc. | B29: Invoice F-22540, ticket R-53467, closeout fittings, escutcheons, and stops | C29: Materials | D29: 07/31/2026 | E29: =DATE(VALUE(RIGHT(D29,4)),VALUE(LEFT(D29,2)),VALUE(MID(D29,4,2))) -> 46234 | F29: 3463.5 | G29: =IF(C29="Charges","No, not work furnished",IF(C29="Request","No, not in the price agreed",IF(E29>=INDEX(Notices!$M$4:$M$18,MATCH(A29,Notices!$A$4:$A$18,0)),"Yes","No, before the notice window"))) -> Yes | H29: =IF(COUNTIFS(Waivers!$A$4:$A$38,A29,Waivers!$L$4:$L$38,"Yes",Waivers!$K$4:$K$38,"Final")>0,"Yes, final form",IF(OR(C29="Retention",C29="Extra",C29="Request"),"No, saved by the progress form",IF(COUNTIFS(Waivers!$A$4:$A$38,A29,Waivers!$L$4:$L$38,"Yes",Waivers!$K$4:$K$38,"Progress",Waivers!$D$4:$D$38,">="&E29)>0,"Yes","No"))) -> No | I29: =IF(AND(G29="Yes",LEFT(H29,2)="No",LEFT(L29,4)<>"Paid"),F29,0) -> 3463.5 | J29: Claim 10 Exhibit A, the Delivered column | L29: =IF(K29="","None",IF(COUNTIFS('DK Ledger'!$B$4:$B$42,K29,'DK Ledger'!$C$4:$C$42,"STP")>0,"Stopped",IF(INDEX('DK Ledger'!$H$4:$H$42,MATCH(K29,'DK Ledger'!$B$4:$B$42,0))="","Not paid by the bank","Paid "&INDEX('DK Ledger'!$H$4:$H$42,MATCH(K29,'DK Ledger'!$B$4:$B$42,0))))) -> None
... A41: Capitol Wire & Lighting, Inc. | B41: Invoice C-14519, ticket D-33120, lamps, cover plates, and closeout items | C41: Materials | D41: 08/10/2026 | E41: =DATE(VALUE(RIGHT(D41,4)),VALUE(LEFT(D41,2)),VALUE(MID(D41,4,2))) -> 46244 | F41: 2100 | G41: =IF(C41="Charges","No, not work furnished",IF(C41="Request","No, not in the price agreed",IF(E41>=INDEX(Notices!$M$4:$M$18,MATCH(A41,Notices!$A$4:$A$18,0)),"Yes","No, before the notice window"))) -> Yes | H41: =IF(COUNTIFS(Waivers!$A$4:$A$38,A41,Waivers!$L$4:$L$38,"Yes",Waivers!$K$4:$K$38,"Final")>0,"Yes, final form",IF(OR(C41="Retention",C41="Extra",C41="Request"),"No, saved by the progress form",IF(COUNTIFS(Waivers!$A$4:$A$38,A41,Waivers!$L$4:$L$38,"Yes",Waivers!$K$4:$K$38,"Progress",Waivers!$D$4:$D$38,">="&E41)>0,"Yes","No"))) -> No | I41: =IF(AND(G41="Yes",LEFT(H41,2)="No",LEFT(L41,4)<>"Paid"),F41,0) -> 2100 | J41: Claim 15 Exhibit A, the Delivered column | L41: =IF(K41="","None",IF(COUNTIFS('DK Ledger'!$B$4:$B$42,K41,'DK Ledger'!$C$4:$C$42,"STP")>0,"Stopped",IF(INDEX('DK Ledger'!$H$4:$H$42,MATCH(K41,'DK Ledger'!$B$4:$B$42,0))="","Not paid by the bank","Paid "&INDEX('DK Ledger'!$H$4:$H$42,MATCH(K41,'DK Ledger'!$B$4:$B$42,0))))) -> None
A43: Each claimant's components sum to the amount of its claim of lien as recorded, which the claimant states after deducting payments received (section 8430(a)). A component is secured when it was furnished inside the period the claimant's preliminary notice covers, is work furnished rather than a charge on the account, and is part of the price agreed, which is the contract price with the change orders that were approved: Bautista's change order 1 is on the subcontractor list and Lindqvist's request 3 is not. It is enforceable when no effective waiver releases it. Hedrick's, Sierra Pipe's, and Capitol Wire's deliveries are dated by the delivery ticket, not by the invoice. LATER_CHECK is a check the ledger shows to the claimant for the component that no waiver on file names, and a component the bank has paid is no longer enforceable (section 8430(a)). Whether the claimant can enforce anything at all is decided on the Claims tab.

Sheet Claims
A1: Standing of each recorded claim and what the owner does about it
A3: CLAIMANT | B3: RECORDED | C3: DOC_NO | D3: AMOUNT_AS_RECORDED | E3: CLASS | F3: LIEN_RIGHTS | G3: TIMELY | H3: SERVED_ON_OWNER | I3: EXPIRED | J3: STANDING | K3: ENFORCEABLE_AMOUNT | L3: OVERSTATED_BY | M3: ACTION | N3: RELEASE_BOND | O3: UNDER_THE_DIRECT_CONTRACT
A4: Tallac Concrete, Inc. | B4: =Deadlines!B4 -> 06/26/2026 | C4: =Deadlines!L4 -> 2026-0060418 | D4: 33275 | E4: =Notices!C4 -> Other claimant | F4: =Notices!N4 -> Yes | G4: =Deadlines!E4 -> Yes | H4: =Deadlines!G4 -> Yes | I4: =Deadlines!K4 -> Yes | J4: =IF(F4="No","No lien rights",IF(G4="No","Untimely",IF(H4="No","Not served on the owner",IF(I4="Yes","Expired",IF(SUMIFS(Amounts!$I$4:$I$41,Amounts!$A$4:$A$41,A4)=0,"Waived in full","Enforceable"))))) -> Expired | K4: =IF(J4="Enforceable",SUMIFS(Amounts!$I$4:$I$41,Amounts!$A$4:$A$41,A4),0) -> 0 | L4: =D4-K4 -> 33275 | M4: =IF(J4="Expired","Demand a release under section 8482, then petition under sections 8480 to 8488 after 10 days",IF(J4="No lien rights","Demand a recorded release, the defect being no preliminary notice to the owner",IF(J4="Untimely","Demand a recorded release, the defect being a recording after the last day",IF(J4="Not served on the owner","Demand a recorded release, the defect being no service on the owner",IF(J4="Waived in full","Demand a recorded release, the defect being a final waiver of the whole claim",IF(I4="Not shown","Bond at 125 percent until a new index search shows no action, then demand a release",IF(O4="No","Bond at 125 percent, or pay the owner's own balance against an unconditional final release",IF(K4<D4,"Bond at 125 percent of the recorded claim, or take an amended claim at the enforceable amount","Bond at 125 percent, or pay from the money held against an unconditional final release")))))))) -> Demand a release under section 8482, then petition under sections 8480 to 8488 after 10 days | N4: =IF(J4="Enforceable",ROUND(D4*Parameters!$B$16/100,2),0) -> 0 | O4: =IF(E4="Direct contractor","No","Yes") -> Yes
A5: Foothill Ready Mix, Inc. | B5: =Deadlines!B5 -> 07/06/2026 | C5: =Deadlines!L5 -> 2026-0063905 | D5: 17204.84 | E5: =Notices!C5 -> Other claimant | F5: =Notices!N5 -> Yes | G5: =Deadlines!E5 -> Yes | H5: =Deadlines!G5 -> Yes | I5: =Deadlines!K5 -> Not shown | J5: =IF(F5="No","No lien rights",IF(G5="No","Untimely",IF(H5="No","Not served on the owner",IF(I5="Yes","Expired",IF(SUMIFS(Amounts!$I$4:$I$41,Amounts!$A$4:$A$41,A5)=0,"Waived in full","Enforceable"))))) -> Enforceable | K5: =IF(J5="Enforceable",SUMIFS(Amounts!$I$4:$I$41,Amounts!$A$4:$A$41,A5),0) -> 17204.84 | L5: =D5-K5 -> 0 | M5: =IF(J5="Expired","Demand a release under section 8482, then petition under sections 8480 to 8488 after 10 days",IF(J5="No lien rights","Demand a recorded release, the defect being no preliminary notice to the owner",IF(J5="Untimely","Demand a recorded release, the defect being a recording after the last day",IF(J5="Not served on the owner","Demand a recorded release, the defect being no service on the owner",IF(J5="Waived in full","Demand a recorded release, the defect being a final waiver of the whole claim",IF(I5="Not shown","Bond at 125 percent until a new index search shows no action, then demand a release",IF(O5="No","Bond at 125 percent, or pay the owner's own balance against an unconditional final release",IF(K5<D5,"Bond at 125 percent of the recorded claim, or take an amended claim at the enforceable amount","Bond at 125 percent, or pay from the money held against an unconditional final release")))))))) -> Bond at 125 percent until a new index search shows no action, then demand a release | N5: =IF(J5="Enforceable",ROUND(D5*Parameters!$B$16/100,2),0) -> 21506.05 | O5: =IF(E5="Direct contractor","No","Yes") -> Yes
A6: Norcal Rebar & Mesh, LLC | B6: =Deadlines!B6 -> 09/14/2026 | C6: =Deadlines!L6 -> 2026-0095207 | D6: 27640 | E6: =Notices!C6 -> Other claimant | F6: =Notices!N6 -> No | G6: =Deadlines!E6 -> Yes | H6: =Deadlines!G6 -> Yes | I6: =Deadlines!K6 -> No | J6: =IF(F6="No","No lien rights",IF(G6="No","Untimely",IF(H6="No","Not served on the owner",IF(I6="Yes","Expired",IF(SUMIFS(Amounts!$I$4:$I$41,Amounts!$A$4:$A$41,A6)=0,"Waived in full","Enforceable"))))) -> No lien rights | K6: =IF(J6="Enforceable",SUMIFS(Amounts!$I$4:$I$41,Amounts!$A$4:$A$41,A6),0) -> 0 | L6: =D6-K6 -> 27640 | M6: =IF(J6="Expired","Demand a release under section 8482, then petition under sections 8480 to 8488 after 10 days",IF(J6="No lien rights","Demand a recorded release, the defect being no preliminary notice to the owner",IF(J6="Untimely","Demand a recorded release, the defect being a recording after the last day",IF(J6="Not served on the owner","Demand a recorded release, the defect being no service on the owner",IF(J6="Waived in full","Demand a recorded release, the defect being a final waiver of the whole claim",IF(I6="Not shown","Bond at 125 percent until a new index search shows no action, then demand a release",IF(O6="No","Bond at 125 percent, or pay the owner's own balance against an unconditional final release",IF(K6<D6,"Bond at 125 percent of the recorded claim, or take an amended claim at the enforceable amount","Bond at 125 percent, or pay from the money held against an unconditional final release")))))))) -> Demand a recorded release, the defect being no preliminary notice to the owner | N6: =IF(J6="Enforceable",ROUND(D6*Parameters!$B$16/100,2),0) -> 0 | O6: =IF(E6="Direct contractor","No","Yes") -> Yes
A7: Hedrick & Sons Building Supply | B7: =Deadlines!B7 -> 09/16/2026 | C7: =Deadlines!L7 -> 2026-0096088 | D7: 54230.81 | E7: =Notices!C7 -> Other claimant | F7: =Notices!N7 -> Yes | G7: =Deadlines!E7 -> Yes | H7: =Deadlines!G7 -> Yes | I7: =Deadlines!K7 -> No | J7: =IF(F7="No","No lien rights",IF(G7="No","Untimely",IF(H7="No","Not served on the owner",IF(I7="Yes","Expired",IF(SUMIFS(Amounts!$I$4:$I$41,Amounts!$A$4:$A$41,A7)=0,"Waived in full","Enforceable"))))) -> Enforceable | K7: =IF(J7="Enforceable",SUMIFS(Amounts!$I$4:$I$41,Amounts!$A$4:$A$41,A7),0) -> 29091.69 | L7: =D7-K7 -> 25139.12 | M7: =IF(J7="Expired","Demand a release under section 8482, then petition under sections 8480 to 8488 after 10 days",IF(J7="No lien rights","Demand a recorded release, the defect being no preliminary notice to the owner",IF(J7="Untimely","Demand a recorded release, the defect being a recording after the last day",IF(J7="Not served on the owner","Demand a recorded release, the defect being no service on the owner",IF(J7="Waived in full","Demand a recorded release, the defect being a final waiver of the whole claim",IF(I7="Not shown","Bond at 125 percent until a new index search shows no action, then demand a release",IF(O7="No","Bond at 125 percent, or pay the owner's own balance against an unconditional final release",IF(K7<D7,"Bond at 125 percent of the recorded claim, or take an amended claim at the enforceable amount","Bond at 125 percent, or pay from the money held against an unconditional final release")))))))) -> Bond at 125 percent of the recorded claim, or take an amended claim at the enforceable amount | N7: =IF(J7="Enforceable",ROUND(D7*Parameters!$B$16/100,2),0) -> 67788.51 | O7: =IF(E7="Direct contractor","No","Yes") -> Yes
A8: Abrego Glass & Glazing | B8: =Deadlines!B8 -> 09/17/2026 | C8: =Deadlines!L8 -> 2026-0096531 | D8: 9345 | E8: =Notices!C8 -> Other claimant | F8: =Notices!N8 -> Yes | G8: =Deadlines!E8 -> Yes | H8: =Deadlines!G8 -> No | I8: =Deadlines!K8 -> No | J8: =IF(F8="No","No lien rights",IF(G8="No","Untimely",IF(H8="No","Not served on the owner",IF(I8="Yes","Expired",IF(SUMIFS(Amounts!$I$4:$I$41,Amounts!$A$4:$A$41,A8)=0,"Waived in full","Enforceable"))))) -> Not served on the owner | K8: =IF(J8="Enforceable",SUMIFS(Amounts!$I$4:$I$41,Amounts!$A$4:$A$41,A8),0) -> 0 | L8: =D8-K8 -> 9345 | M8: =IF(J8="Expired","Demand a release under section 8482, then petition under sections 8480 to 8488 after 10 days",IF(J8="No lien rights","Demand a recorded release, the defect being no preliminary notice to the owner",IF(J8="Untimely","Demand a recorded release, the defect being a recording after the last day",IF(J8="Not served on the owner","Demand a recorded release, the defect being no service on the owner",IF(J8="Waived in full","Demand a recorded release, the defect being a final waiver of the whole claim",IF(I8="Not shown","Bond at 125 percent until a new index search shows no action, then demand a release",IF(O8="No","Bond at 125 percent, or pay the owner's own balance against an unconditional final release",IF(K8<D8,"Bond at 125 percent of the recorded claim, or take an amended claim at the enforceable amount","Bond at 125 percent, or pay from the money held against an unconditional final release")))))))) -> Demand a recorded release, the defect being no service on the owner | N8: =IF(J8="Enforceable",ROUND(D8*Parameters!$B$16/100,2),0) -> 0 | O8: =IF(E8="Direct contractor","No","Yes") -> Yes
A9: Kastner Mechanical Contractors, Inc. | B9: =Deadlines!B9 -> 09/21/2026 | C9: =Deadlines!L9 -> 2026-0097644 | D9: 159145 | E9: =Notices!C9 -> Other claimant | F9: =Notices!N9 -> Yes | G9: =Deadlines!E9 -> Yes | H9: =Deadlines!G9 -> Yes | I9: =Deadlines!K9 -> No | J9: =IF(F9="No","No lien rights",IF(G9="No","Untimely",IF(H9="No","Not served on the owner",IF(I9="Yes","Expired",IF(SUMIFS(Amounts!$I$4:$I$41,Amounts!$A$4:$A$41,A9)=0,"Waived in full","Enforceable"))))) -> Enforceable | K9: =IF(J9="Enforceable",SUMIFS(Amounts!$I$4:$I$41,Amounts!$A$4:$A$41,A9),0) -> 85235 | L9: =D9-K9 -> 73910 | M9: =IF(J9="Expired","Demand a release under section 8482, then petition under sections 8480 to 8488 after 10 days",IF(J9="No lien rights","Demand a recorded release, the defect being no preliminary notice to the owner",IF(J9="Untimely","Demand a recorded release, the defect being a recording after the last day",IF(J9="Not served on the owner","Demand a recorded release, the defect being no service on the owner",IF(J9="Waived in full","Demand a recorded release, the defect being a final waiver of the whole claim",IF(I9="Not shown","Bond at 125 percent until a new index search shows no action, then demand a release",IF(O9="No","Bond at 125 percent, or pay the owner's own balance against an unconditional final release",IF(K9<D9,"Bond at 125 percent of the recorded claim, or take an amended claim at the enforceable amount","Bond at 125 percent, or pay from the money held against an unconditional final release")))))))) -> Bond at 125 percent of the recorded claim, or take an amended claim at the enforceable amount | N9: =IF(J9="Enforceable",ROUND(D9*Parameters!$B$16/100,2),0) -> 198931.25 | O9: =IF(E9="Direct contractor","No","Yes") -> Yes
A10: Bautista Painting Co. | B10: =Deadlines!B10 -> 09/22/2026 | C10: =Deadlines!L10 -> 2026-0098120 | D10: 46600 | E10: =Notices!C10 -> Other claimant | F10: =Notices!N10 -> Yes | G10: =Deadlines!E10 -> Yes | H10: =Deadlines!G10 -> Yes | I10: =Deadlines!K10 -> No | J10: =IF(F10="No","No lien rights",IF(G10="No","Untimely",IF(H10="No","Not served on the owner",IF(I10="Yes","Expired",IF(SUMIFS(Amounts!$I$4:$I$41,Amounts!$A$4:$A$41,A10)=0,"Waived in full","Enforceable"))))) -> Enforceable | K10: =IF(J10="Enforceable",SUMIFS(Amounts!$I$4:$I$41,Amounts!$A$4:$A$41,A10),0) -> 8125 | L10: =D10-K10 -> 38475 | M10: =IF(J10="Expired","Demand a release under section 8482, then petition under sections 8480 to 8488 after 10 days",IF(J10="No lien rights","Demand a recorded release, the defect being no preliminary notice to the owner",IF(J10="Untimely","Demand a recorded release, the defect being a recording after the last day",IF(J10="Not served on the owner","Demand a recorded release, the defect being no service on the owner",IF(J10="Waived in full","Demand a recorded release, the defect being a final waiver of the whole claim",IF(I10="Not shown","Bond at 125 percent until a new index search shows no action, then demand a release",IF(O10="No","Bond at 125 percent, or pay the owner's own balance against an unconditional final release",IF(K10<D10,"Bond at 125 percent of the recorded claim, or take an amended claim at the enforceable amount","Bond at 125 percent, or pay from the money held against an unconditional final release")))))))) -> Bond at 125 percent of the recorded claim, or take an amended claim at the enforceable amount | N10: =IF(J10="Enforceable",ROUND(D10*Parameters!$B$16/100,2),0) -> 58250 | O10: =IF(E10="Direct contractor","No","Yes") -> Yes
A11: Fenwick Roofing, Inc. | B11: =Deadlines!B11 -> 09/23/2026 | C11: =Deadlines!L11 -> 2026-0098577 | D11: 14937.5 | E11: =Notices!C11 -> Other claimant | F11: =Notices!N11 -> Yes | G11: =Deadlines!E11 -> Yes | H11: =Deadlines!G11 -> Yes | I11: =Deadlines!K11 -> No | J11: =IF(F11="No","No lien rights",IF(G11="No","Untimely",IF(H11="No","Not served on the owner",IF(I11="Yes","Expired",IF(SUMIFS(Amounts!$I$4:$I$41,Amounts!$A$4:$A$41,A11)=0,"Waived in full","Enforceable"))))) -> Waived in full | K11: =IF(J11="Enforceable",SUMIFS(Amounts!$I$4:$I$41,Amounts!$A$4:$A$41,A11),0) -> 0 | L11: =D11-K11 -> 14937.5 | M11: =IF(J11="Expired","Demand a release under section 8482, then petition under sections 8480 to 8488 after 10 days",IF(J11="No lien rights","Demand a recorded release, the defect being no preliminary notice to the owner",IF(J11="Untimely","Demand a recorded release, the defect being a recording after the last day",IF(J11="Not served on the owner","Demand a recorded release, the defect being no service on the owner",IF(J11="Waived in full","Demand a recorded release, the defect being a final waiver of the whole claim",IF(I11="Not shown","Bond at 125 percent until a new index search shows no action, then demand a release",IF(O11="No","Bond at 125 percent, or pay the owner's own balance against an unconditional final release",IF(K11<D11,"Bond at 125 percent of the recorded claim, or take an amended claim at the enforceable amount","Bond at 125 percent, or pay from the money held against an unconditional final release")))))))) -> Demand a recorded release, the defect being a final waiver of the whole claim | N11: =IF(J11="Enforceable",ROUND(D11*Parameters!$B$16/100,2),0) -> 0 | O11: =IF(E11="Direct contractor","No","Yes") -> Yes
A12: Lindqvist Fire Protection | B12: =Deadlines!B12 -> 09/24/2026 | C12: =Deadlines!L12 -> 2026-0098901 | D12: 16600 | E12: =Notices!C12 -> Other claimant | F12: =Notices!N12 -> Yes | G12: =Deadlines!E12 -> Yes | H12: =Deadlines!G12 -> Yes | I12: =Deadlines!K12 -> No | J12: =IF(F12="No","No lien rights",IF(G12="No","Untimely",IF(H12="No","Not served on the owner",IF(I12="Yes","Expired",IF(SUMIFS(Amounts!$I$4:$I$41,Amounts!$A$4:$A$41,A12)=0,"Waived in full","Enforceable"))))) -> Enforceable | K12: =IF(J12="Enforceable",SUMIFS(Amounts!$I$4:$I$41,Amounts!$A$4:$A$41,A12),0) -> 7132.5 | L12: =D12-K12 -> 9467.5 | M12: =IF(J12="Expired","Demand a release under section 8482, then petition under sections 8480 to 8488 after 10 days",IF(J12="No lien rights","Demand a recorded release, the defect being no preliminary notice to the owner",IF(J12="Untimely","Demand a recorded release, the defect being a recording after the last day",IF(J12="Not served on the owner","Demand a recorded release, the defect being no service on the owner",IF(J12="Waived in full","Demand a recorded release, the defect being a final waiver of the whole claim",IF(I12="Not shown","Bond at 125 percent until a new index search shows no action, then demand a release",IF(O12="No","Bond at 125 percent, or pay the owner's own balance against an unconditional final release",IF(K12<D12,"Bond at 125 percent of the recorded claim, or take an amended claim at the enforceable amount","Bond at 125 percent, or pay from the money held against an unconditional final release")))))))) -> Bond at 125 percent of the recorded claim, or take an amended claim at the enforceable amount | N12: =IF(J12="Enforceable",ROUND(D12*Parameters!$B$16/100,2),0) -> 20750 | O12: =IF(E12="Direct contractor","No","Yes") -> Yes
A13: Sierra Pipe & Supply, Inc. | B13: =Deadlines!B13 -> 09/24/2026 | C13: =Deadlines!L13 -> 2026-0098955 | D13: 19742.64 | E13: =Notices!C13 -> Other claimant | F13: =Notices!N13 -> Yes | G13: =Deadlines!E13 -> Yes | H13: =Deadlines!G13 -> Yes | I13: =Deadlines!K13 -> No | J13: =IF(F13="No","No lien rights",IF(G13="No","Untimely",IF(H13="No","Not served on the owner",IF(I13="Yes","Expired",IF(SUMIFS(Amounts!$I$4:$I$41,Amounts!$A$4:$A$41,A13)=0,"Waived in full","Enforceable"))))) -> Enforceable | K13: =IF(J13="Enforceable",SUMIFS(Amounts!$I$4:$I$41,Amounts!$A$4:$A$41,A13),0) -> 15426.44 | L13: =D13-K13 -> 4316.2 | M13: =IF(J13="Expired","Demand a release under section 8482, then petition under sections 8480 to 8488 after 10 days",IF(J13="No lien rights","Demand a recorded release, the defect being no preliminary notice to the owner",IF(J13="Untimely","Demand a recorded release, the defect being a recording after the last day",IF(J13="Not served on the owner","Demand a recorded release, the defect being no service on the owner",IF(J13="Waived in full","Demand a recorded release, the defect being a final waiver of the whole claim",IF(I13="Not shown","Bond at 125 percent until a new index search shows no action, then demand a release",IF(O13="No","Bond at 125 percent, or pay the owner's own balance against an unconditional final release",IF(K13<D13,"Bond at 125 percent of the recorded claim, or take an amended claim at the enforceable amount","Bond at 125 percent, or pay from the money held against an unconditional final release")))))))) -> Bond at 125 percent of the recorded claim, or take an amended claim at the enforceable amount | N13: =IF(J13="Enforceable",ROUND(D13*Parameters!$B$16/100,2),0) -> 24678.3 | O13: =IF(E13="Direct contractor","No","Yes") -> Yes
A14: Ostrowski Electric, Inc. | B14: =Deadlines!B14 -> 09/28/2026 | C14: =Deadlines!L14 -> 2026-0100263 | D14: 61477 | E14: =Notices!C14 -> Other claimant | F14: =Notices!N14 -> Yes | G14: =Deadlines!E14 -> Yes | H14: =Deadlines!G14 -> Yes | I14: =Deadlines!K14 -> No | J14: =IF(F14="No","No lien rights",IF(G14="No","Untimely",IF(H14="No","Not served on the owner",IF(I14="Yes","Expired",IF(SUMIFS(Amounts!$I$4:$I$41,Amounts!$A$4:$A$41,A14)=0,"Waived in full","Enforceable"))))) -> Enforceable | K14: =IF(J14="Enforceable",SUMIFS(Amounts!$I$4:$I$41,Amounts!$A$4:$A$41,A14),0) -> 61477 | L14: =D14-K14 -> 0 | M14: =IF(J14="Expired","Demand a release under section 8482, then petition under sections 8480 to 8488 after 10 days",IF(J14="No lien rights","Demand a recorded release, the defect being no preliminary notice to the owner",IF(J14="Untimely","Demand a recorded release, the defect being a recording after the last day",IF(J14="Not served on the owner","Demand a recorded release, the defect being no service on the owner",IF(J14="Waived in full","Demand a recorded release, the defect being a final waiver of the whole claim",IF(I14="Not shown","Bond at 125 percent until a new index search shows no action, then demand a release",IF(O14="No","Bond at 125 percent, or pay the owner's own balance against an unconditional final release",IF(K14<D14,"Bond at 125 percent of the recorded claim, or take an amended claim at the enforceable amount","Bond at 125 percent, or pay from the money held against an unconditional final release")))))))) -> Bond at 125 percent, or pay from the money held against an unconditional final release | N14: =IF(J14="Enforceable",ROUND(D14*Parameters!$B$16/100,2),0) -> 76846.25 | O14: =IF(E14="Direct contractor","No","Yes") -> Yes
A15: Calder Drywall & Plaster, LLC | B15: =Deadlines!B15 -> 09/29/2026 | C15: =Deadlines!L15 -> 2026-0100719 | D15: 38915 | E15: =Notices!C15 -> Other claimant | F15: =Notices!N15 -> Yes | G15: =Deadlines!E15 -> Yes | H15: =Deadlines!G15 -> Yes | I15: =Deadlines!K15 -> No | J15: =IF(F15="No","No lien rights",IF(G15="No","Untimely",IF(H15="No","Not served on the owner",IF(I15="Yes","Expired",IF(SUMIFS(Amounts!$I$4:$I$41,Amounts!$A$4:$A$41,A15)=0,"Waived in full","Enforceable"))))) -> Enforceable | K15: =IF(J15="Enforceable",SUMIFS(Amounts!$I$4:$I$41,Amounts!$A$4:$A$41,A15),0) -> 38915 | L15: =D15-K15 -> 0 | M15: =IF(J15="Expired","Demand a release under section 8482, then petition under sections 8480 to 8488 after 10 days",IF(J15="No lien rights","Demand a recorded release, the defect being no preliminary notice to the owner",IF(J15="Untimely","Demand a recorded release, the defect being a recording after the last day",IF(J15="Not served on the owner","Demand a recorded release, the defect being no service on the owner",IF(J15="Waived in full","Demand a recorded release, the defect being a final waiver of the whole claim",IF(I15="Not shown","Bond at 125 percent until a new index search shows no action, then demand a release",IF(O15="No","Bond at 125 percent, or pay the owner's own balance against an unconditional final release",IF(K15<D15,"Bond at 125 percent of the recorded claim, or take an amended claim at the enforceable amount","Bond at 125 percent, or pay from the money held against an unconditional final release")))))))) -> Bond at 125 percent, or pay from the money held against an unconditional final release | N15: =IF(J15="Enforceable",ROUND(D15*Parameters!$B$16/100,2),0) -> 48643.75 | O15: =IF(E15="Direct contractor","No","Yes") -> Yes
... A18: Capitol Wire & Lighting, Inc. | B18: =Deadlines!B18 -> 10/01/2026 | C18: =Deadlines!L18 -> 2026-0101655 | D18: 23480 | E18: =Notices!C18 -> Other claimant | F18: =Notices!N18 -> Yes | G18: =Deadlines!E18 -> Yes | H18: =Deadlines!G18 -> Yes | I18: =Deadlines!K18 -> No | J18: =IF(F18="No","No lien rights",IF(G18="No","Untimely",IF(H18="No","Not served on the owner",IF(I18="Yes","Expired",IF(SUMIFS(Amounts!$I$4:$I$41,Amounts!$A$4:$A$41,A18)=0,"Waived in full","Enforceable"))))) -> Enforceable | K18: =IF(J18="Enforceable",SUMIFS(Amounts!$I$4:$I$41,Amounts!$A$4:$A$41,A18),0) -> 23480 | L18: =D18-K18 -> 0 | M18: =IF(J18="Expired","Demand a release under section 8482, then petition under sections 8480 to 8488 after 10 days",IF(J18="No lien rights","Demand a recorded release, the defect being no preliminary notice to the owner",IF(J18="Untimely","Demand a recorded release, the defect being a recording after the last day",IF(J18="Not served on the owner","Demand a recorded release, the defect being no service on the owner",IF(J18="Waived in full","Demand a recorded release, the defect being a final waiver of the whole claim",IF(I18="Not shown","Bond at 125 percent until a new index search shows no action, then demand a release",IF(O18="No","Bond at 125 percent, or pay the owner's own balance against an unconditional final release",IF(K18<D18,"Bond at 125 percent of the recorded claim, or take an amended claim at the enforceable amount","Bond at 125 percent, or pay from the money held against an unconditional final release")))))))) -> Bond at 125 percent, or pay from the money held against an unconditional final release | N18: =IF(J18="Enforceable",ROUND(D18*Parameters!$B$16/100,2),0) -> 29350 | O18: =IF(E18="Direct contractor","No","Yes") -> Yes
A19: Totals | D19: =SUM(D4:D18) -> 561561.79 | K19: =SUM(K4:K18) -> 311167.47 | L19: =SUM(L4:L18) -> 250394.32 | N19: =SUM(N4:N18) -> 578094.11
A20: Claims to bond or settle | D20: =COUNTIF(J4:J18,"Enforceable") -> 10
A21: Claims to demand released | D21: =COUNTIF(J4:J18,"<>Enforceable") -> 5
A22: Recorded amount of the claims to demand released | D22: =SUMIF(J4:J18,"<>Enforceable",D4:D18) -> 99086.5
A23: Enforceable by claimants under the Dunmore-Kettle contract | D23: =SUMIFS(K4:K18,O4:O18,"Yes") -> 286087.47
A25: STANDING reads the tests in order: lien rights, the recording date, service on the owner, the 90 days to sue, and the waivers. The release bond is measured by the recorded amount (section 8424(b)), not by the enforceable amount. A claim marked Not shown under EXPIRED stays with the enforceable claims until a search run after its last day to sue shows no action, as PN-14 directs.

Sheet Note to Marguerite
A1: Note to Marguerite Okonjo on the Larkspur Crossing Building B claims
A3: Marguerite, this is the analysis of the fifteen claims of mechanics lien recorded against Larkspur Crossing Building B, worked under PN-14 from the recorder's copies, the owner's project file, Dunmore-Kettle's payment ledger, and the close-out file. The fifteen claims total $561,561.79 as recorded. Nadia expects every claim to be late, waived, or Dunmore-Kettle's to answer. Five of the fifteen can be demanded released, and ten cannot. The ten have to be bonded or settled before the bank's November 6 date, and both of the answers Nadia wants come out against her.
A4: The release bonds on the ten claims total $578,094.11 at 125 percent of the recorded amounts under section 8424(b), which is $3,094.11 over the $575,000.00 line the surety has approved. The bonds are $198,931.25 for Kastner, $76,846.25 for Ostrowski, $67,788.51 for Hedrick, $58,250.00 for Bautista, $48,643.75 for Calder Drywall, $31,350.00 for Sorensen, $29,350.00 for Capitol Wire, $24,678.30 for Sierra Pipe, $21,506.05 for Foothill, and $20,750.00 for Lindqvist. The shortest way inside the line is to pay Lindqvist's $7,132.50 of retention against an unconditional final release, which takes its $20,750.00 bond out, or to pay Sorensen's $25,080.00, which is Piedmont Ridge's own bill. The other way is an amended claim from Kastner, Hedrick, Bautista, Sierra Pipe, or Lindqvist at the enforceable amount before the bonds are written.
A5: The claimants under the Dunmore-Kettle contract could enforce $286,087.47, and Piedmont Ridge holds $283,135.50 on that contract, which is the unpaid application 8 of $93,423.00 net of its retention and the retention of $189,712.50 together, measured against the contract sum as adjusted by the six approved change orders to $3,794,250.00. The money held falls $2,951.97 short. Measured against the contract sum as signed, $3,748,250.00, the figure held would be $237,135.50 and the shortfall $48,951.97, but PN-14 takes the adjusted sum. Sorensen's $25,080.00 is outside that comparison, because Sorensen contracted with the owner itself and its claim is the owner's own debt.
A6: The notice of completion was recorded on August 26, the fifteenth day after the completion of August 11, so it is effective under section 8182(a) and shortens the time of every person that was given its copy in time. Counted the office's way, the day of completion is not counted, and the fifteenth day is. The notice was recorded on that last day.
A7: The last day for a claimant given its copy of the notice of completion was Monday, September 28, 2026. The thirtieth day after the notice of completion was recorded was Friday, September 25, and the close-out file shows the clerk's office and the recorder's office closed to the public for the whole of that day. Under Code of Civil Procedure section 12b a day on which the county office is closed for the whole day is a holiday for computing time, so section 12a carries the period over that Friday and the weekend. Ostrowski Electric recorded on that Monday, and its claim is timely.
A8: Calder Drywall & Plaster recorded on September 29, one day after that last day, and its claim is timely all the same. Calder Drywall gave the owner a preliminary notice on April 24, and it was never given a copy of the notice of completion. The certified mail log shows a copy to Calder Bros. Masonry on August 31 and none to Calder Drywall, and Calder Bros. Masonry is a different company. Devlin's September 10 memorandum says the mail log is the whole record. Under section 8190(d) the notice of completion does not shorten Calder Drywall's time, so its last day is November 9, 2026, and the whole $38,915.00 is enforceable. The release it signed for July is on Dunmore-Kettle's form S-9, which is not one of the four statutory forms and releases nothing.
A9: Capitol Wire & Lighting, Inc. recorded on October 1 and is timely for the same reason. Its copy of the notice of completion went out on Wednesday, September 9, one day after the last day to give it, in the same lot as Dunmore-Kettle's, so under section 8190(d) its last day is also November 9. Its preliminary notice was deposited on February 16, the twentieth day after its first delivery of January 27 on its own statement of account, so the notice was in time and the whole $23,480.00 is enforceable, the disputed $1,500.00 on the first invoice included. Petrakis Plumbing recorded on September 30 and is late. Its copy of the notice of completion was mailed on Tuesday, September 8, thirteen days after the recording. The tenth day was a Saturday, and the Monday after it was Labor Day, so the last day to give the copy was that Tuesday. The copy was given in time, and the September 28 last day applies to Petrakis.
A10: Sorensen Landscape contracted with the owner itself under the agreement of May 19, 2026, so it is a direct contractor. It owed no preliminary notice, because there is no construction lender, and the 30 day period never applied to it. No copy of the notice of completion was mailed to Sorensen, so its last day is November 9, 2026, and its September 30 claim for $25,080.00 is timely and enforceable in full.
A11: Kastner Mechanical could enforce $85,235.00 of its $159,145.00, the final billing and the retention. Reid's message says the July draw went out on check 4460, and the ledger carries a stop payment against check 4460 on August 24, so the conditional waiver for July rests on no payment. The ledger also carries check 4474 to Kastner for the same $73,910.00, issued September 18 and paid at the bank on September 23, two days after Kastner recorded. The July draw has been paid, and a payment received reduces the lien under section 8430(a) whether or not a waiver covers it.
A12: Ostrowski Electric could enforce $61,477.00. Check 4479 for its final draw was issued on September 30 and has not paid at the bank on the ledger exported October 3, so the conditional waiver given for it is not yet effective. If check 4479 clears, Ostrowski's enforceable amount falls to the retention of $34,250.00.
A13: Bautista Painting signed an unconditional waiver through July 31 on August 3 and was never paid. The form is effective when signed, so the $38,475.00 July draw is released against the property, and $8,125.00 remains for the retention and the August change order invoice, change order 1 being on the subcontractor list as approved. Fenwick Roofing signed a conditional waiver and release on final payment that names check 4448, and that check paid on August 3. A final form releases every lien right on the job, retention included, so none of Fenwick's $14,937.50 claim for retention can be enforced against the property.
... A19: The file leaves four points open. The civil index has to be run again for Foothill and for Tallac, because an action filed on the last day can be indexed late. Nadia should be asked for any proof that a copy of the notice of completion reached Calder Drywall, Sorensen, or Capitol Wire by another route, and for the permit as the city holds it, since Lindqvist's service stands on the address it shows. Hedrick's and Sierra Pipe's delivery dates should be checked against Dunmore-Kettle's receiving tickets before an amended claim is negotiated. The retention of $189,712.50 fell due on September 28 under section 8812(a), the forty-fifth day having been the closed Friday, the recorded claims justify holding it, and the $22,000.00 rooftop unit correction supports holding $33,000.00 on its own under section 8812(c).
