Workbook

Sheet Plan
A1: 4 WEST STAFFING PLAN, OPENING JANUARY 4, 2027
A2: Environmental Services, St. Anselm Regional Medical Center. Built on the March 2026 task standards and the calendar 2027 average of the census projection; December peak shown as a sensitivity.
A4: WORKLOAD AND POSITIONS BY SHIFT
A5: SHIFT | B5: MINUTES PER DAY | C5: DAILY POSTS | D5: FTE REQUIRED | E5: TRANSFERRED FTE | F5: APPROVED NEW FTE | G5: FTE STILL TO HIRE
A6: Day | B6: =Positions!B5 -> 698.98 | C6: =Positions!C5 -> 1.66 | D6: =Positions!E5 -> 2.62 | E6: =Positions!F5 -> 1 | F6: =Positions!G5 -> 1 | G6: =Positions!H5 -> 0.62
A7: Evening | B7: =Positions!B6 -> 211.42 | C7: =Positions!C6 -> 0.5 | D7: =Positions!E6 -> 0.79 | E7: =Positions!F6 -> 1 | F7: =Positions!G6 -> 0 | G7: =Positions!H6 -> -0.21
A8: Night | B8: =Positions!B7 -> 109.44 | C8: =Positions!C7 -> 0.26 | D8: =Positions!E7 -> 0.41 | E8: =Positions!F7 -> 0 | F8: =Positions!G7 -> 0 | G8: =Positions!H7 -> 0.41
A9: Unit total | B9: =Positions!B8 -> 1019.84 | C9: =Positions!C8 -> 2.42 | D9: =Positions!E8 -> 3.82 | E9: =Positions!F8 -> 2 | F9: =Positions!G8 -> 1 | G9: =Positions!H8 -> 0.82
A11: ANNUAL COST AGAINST THE BUDGET
A12: Annual labor cost of the required staffing | B12: =Cost!I8 -> 187933.81
A13: Annual labor budget approved for the unit | B13: =Cost!I10 -> 205000
A14: Cost against the approved budget, negative when under | B14: =Cost!I11 -> -17066.19
A15: Cost of the working plan of three FTE | B15: =Cost!I15 -> 147204.95
A17: DECEMBER PEAK SENSITIVITY
A18: FTE the December 2027 volumes would take if sustained all year | B18: =Positions!E15 -> 4.04
A19: FTE required on the calendar 2027 average basis | B19: =Positions!E8 -> 3.82
A21: The unit's requirement on the standards is above the two transfers and the one approved position, and its cost is above the approved budget; the note to the director sets out what closes the gap.

Sheet Parameters
A1: Standards, projection basis and wage parameters, with sources
A3: PARAMETER | B3: VALUE | C3: SOURCE
A4: Daily clean, occupied room, minutes | B4: 22 | C4: Standards section 1
A5: Terminal clean, minutes | B5: 43 | C5: Standards section 1
A6: Isolation terminal clean, minutes | B6: 58 | C6: Standards section 1
A7: Nurses station, minutes per service | B7: 15 | C7: Standards section 1
A8: Medication room, minutes | B8: 10 | C8: Standards section 1
A9: Clean utility, minutes | B9: 12 | C9: Standards section 1
A10: Soiled utility, minutes per service | B10: 12 | C10: Standards section 1
A11: Staff restroom, minutes per service | B11: 14 | C11: Standards section 1
A12: Public restroom, minutes per service | B12: 14 | C12: Standards section 1
A13: Family lounge, minutes | B13: 20 | C13: Standards section 1
A14: Conference room, minutes | B14: 12 | C14: Standards section 1
A15: Staff lounge, minutes | B15: 15 | C15: Standards section 1
... A47: Annual labor budget for the unit | B47: 205000 | C47: Director memo of October 7, 2026

Sheet Inventory
A1: Room inventory as issued by Facilities (unit_4west_room_inventory.csv)
A3: ROOM | B3: ROOM TYPE | C3: SQ FT | D3: ISOLATION CAPABLE | E3: CLEANING FREQUENCY
A4: 4W-401 | B4: Private patient room | C4: 253 | D4: N | E4: Daily while occupied; terminal clean on discharge
A5: 4W-402 | B5: Private patient room | C5: 273 | D5: N | E5: Daily while occupied; terminal clean on discharge
A6: 4W-403 | B6: Private patient room | C6: 248 | D6: Y | E6: Daily while occupied; terminal clean on discharge
A7: 4W-404 | B7: Private patient room | C7: 281 | D7: Y | E7: Daily while occupied; terminal clean on discharge
A8: 4W-405 | B8: Private patient room | C8: 253 | D8: N | E8: Daily while occupied; terminal clean on discharge
A9: 4W-406 | B9: Private patient room | C9: 291 | D9: N | E9: Daily while occupied; terminal clean on discharge
A10: 4W-407 | B10: Private patient room | C10: 286 | D10: N | E10: Daily while occupied; terminal clean on discharge
A11: 4W-408 | B11: Private patient room | C11: 254 | D11: N | E11: Daily while occupied; terminal clean on discharge
A12: 4W-409 | B12: Private patient room | C12: 269 | D12: N | E12: Daily while occupied; terminal clean on discharge
A13: 4W-410 | B13: Private patient room | C13: 256 | D13: N | E13: Daily while occupied; terminal clean on discharge
A14: 4W-411 | B14: Private patient room | C14: 273 | D14: N | E14: Daily while occupied; terminal clean on discharge
A15: 4W-412 | B15: Private patient room | C15: 254 | D15: N | E15: Daily while occupied; terminal clean on discharge
... A40: 4W-CORR | B40: Corridor and alcoves | C40: 4200 | D40: N | E40: Daily dust mop and damp mop; weekly burnish; monthly scrub and recoat
A42: Patient rooms | C42: =COUNTIF(B4:B40,"Private patient room") -> 24
A43: Corridor square feet | C43: =SUMIFS(C4:C40,B4:B40,"Corridor and alcoves") -> 4200
A44: Nurses stations | C44: =COUNTIF(B4:B40,"Nurses station") -> 2
A45: Staff restrooms | C45: =COUNTIF(B4:B40,"Staff restroom") -> 2
A46: Public restrooms | C46: =COUNTIF(B4:B40,"Public restroom") -> 2

Sheet Workload
A1: Daily workload, calendar 2027 average basis
A2: Minutes per day by task and by shift under the March 2026 standards. Occupied-room cleans are the average daily census less discharges; terminals are the discharges per day split by the isolation share.
A4: TASK | B4: UNITS PER DAY | C4: MINUTES PER UNIT | D4: MINUTES PER DAY | E4: DAY SHIFT | F4: EVENING SHIFT | G4: NIGHT SHIFT
A5: Daily clean, occupied rooms (census less discharges) | B5: =ROUND(Parameters!$B$22-Parameters!$B$23,2) -> 13.2 | C5: =Parameters!$B$4 -> 22 | D5: =ROUND(B5*C5,2) -> 290.4 | E5: =ROUND(D5*1,2) -> 290.4 | F5: =ROUND(D5*0,2) -> 0 | G5: =ROUND(D5*0,2) -> 0
A6: Terminal clean, standard rooms | B6: =ROUND(Parameters!$B$23*(1-Parameters!$B$24),3) -> 6.724 | C6: =Parameters!$B$5 -> 43 | D6: =ROUND(B6*C6,2) -> 289.13 | E6: =ROUND(D6*Parameters!$B$28,2) -> 187.93 | F6: =ROUND(D6*Parameters!$B$29,2) -> 86.74 | G6: =ROUND(D6*Parameters!$B$30,2) -> 14.46
A7: Terminal clean, isolation rooms | B7: =ROUND(Parameters!$B$23*Parameters!$B$24,3) -> 1.476 | C7: =Parameters!$B$6 -> 58 | D7: =ROUND(B7*C7,2) -> 85.61 | E7: =ROUND(D7*Parameters!$B$28,2) -> 55.65 | F7: =ROUND(D7*Parameters!$B$29,2) -> 25.68 | G7: =ROUND(D7*Parameters!$B$30,2) -> 4.28
A8: Nurses stations | B8: =Inventory!$C$44 -> 2 | C8: =Parameters!$B$7 -> 15 | D8: =ROUND(B8*C8,2) -> 30 | E8: =ROUND(D8*Parameters!$B$31,2) -> 15 | F8: =ROUND(D8*Parameters!$B$32,2) -> 9 | G8: =ROUND(D8*Parameters!$B$33,2) -> 6
A9: Medication room | B9: 1 | C9: =Parameters!$B$8 -> 10 | D9: =ROUND(B9*C9,2) -> 10 | E9: =ROUND(D9*Parameters!$B$31,2) -> 5 | F9: =ROUND(D9*Parameters!$B$32,2) -> 3 | G9: =ROUND(D9*Parameters!$B$33,2) -> 2
A10: Clean utility | B10: 1 | C10: =Parameters!$B$9 -> 12 | D10: =ROUND(B10*C10,2) -> 12 | E10: =ROUND(D10*Parameters!$B$31,2) -> 6 | F10: =ROUND(D10*Parameters!$B$32,2) -> 3.6 | G10: =ROUND(D10*Parameters!$B$33,2) -> 2.4
A11: Soiled utility, two services | B11: 2 | C11: =Parameters!$B$10 -> 12 | D11: =ROUND(B11*C11,2) -> 24 | E11: =ROUND(D11*Parameters!$B$31,2) -> 12 | F11: =ROUND(D11*Parameters!$B$32,2) -> 7.2 | G11: =ROUND(D11*Parameters!$B$33,2) -> 4.8
A12: Staff restrooms | B12: =Inventory!$C$45 -> 2 | C12: =Parameters!$B$11 -> 14 | D12: =ROUND(B12*C12,2) -> 28 | E12: =ROUND(D12*Parameters!$B$31,2) -> 14 | F12: =ROUND(D12*Parameters!$B$32,2) -> 8.4 | G12: =ROUND(D12*Parameters!$B$33,2) -> 5.6
A13: Public restrooms, two services each | B13: =Inventory!$C$46*2 -> 4 | C13: =Parameters!$B$12 -> 14 | D13: =ROUND(B13*C13,2) -> 56 | E13: =ROUND(D13*Parameters!$B$31,2) -> 28 | F13: =ROUND(D13*Parameters!$B$32,2) -> 16.8 | G13: =ROUND(D13*Parameters!$B$33,2) -> 11.2
A14: Family lounge | B14: 1 | C14: =Parameters!$B$13 -> 20 | D14: =ROUND(B14*C14,2) -> 20 | E14: =ROUND(D14*Parameters!$B$31,2) -> 10 | F14: =ROUND(D14*Parameters!$B$32,2) -> 6 | G14: =ROUND(D14*Parameters!$B$33,2) -> 4
A15: Conference room | B15: 1 | C15: =Parameters!$B$14 -> 12 | D15: =ROUND(B15*C15,2) -> 12 | E15: =ROUND(D15*Parameters!$B$31,2) -> 6 | F15: =ROUND(D15*Parameters!$B$32,2) -> 3.6 | G15: =ROUND(D15*Parameters!$B$33,2) -> 2.4
A16: Staff lounge | B16: 1 | C16: =Parameters!$B$15 -> 15 | D16: =ROUND(B16*C16,2) -> 15 | E16: =ROUND(D16*Parameters!$B$31,2) -> 7.5 | F16: =ROUND(D16*Parameters!$B$32,2) -> 4.5 | G16: =ROUND(D16*Parameters!$B$33,2) -> 3
A17: Corridor dust and damp mop, per 100 square feet | B17: =Inventory!$C$43/100 -> 42 | C17: =Parameters!$B$16 -> 1.5 | D17: =ROUND(B17*C17,2) -> 63 | E17: =ROUND(D17*Parameters!$B$31,2) -> 31.5 | F17: =ROUND(D17*Parameters!$B$32,2) -> 18.9 | G17: =ROUND(D17*Parameters!$B$33,2) -> 12.6
A18: High-touch disinfection rounds | B18: 2 | C18: =Parameters!$B$17 -> 30 | D18: =ROUND(B18*C18,2) -> 60 | E18: =ROUND(D18*Parameters!$B$31,2) -> 30 | F18: =ROUND(D18*Parameters!$B$32,2) -> 18 | G18: =ROUND(D18*Parameters!$B$33,2) -> 12
A19: Corridor burnish, weekly averaged to a day | B19: =ROUND(1/Parameters!$B$20,4) -> 0.1429 | C19: =Parameters!$B$18 -> 90 | D19: =ROUND(B19*C19,2) -> 12.86 | E19: =ROUND(D19*0,2) -> 0 | F19: =ROUND(D19*0,2) -> 0 | G19: =ROUND(D19*1,2) -> 12.86
A20: Corridor scrub and recoat, monthly averaged to a day | B20: =ROUND(1/Parameters!$B$21,4) -> 0.0329 | C20: =Parameters!$B$19 -> 360 | D20: =ROUND(B20*C20,2) -> 11.84 | E20: =ROUND(D20*0,2) -> 0 | F20: =ROUND(D20*0,2) -> 0 | G20: =ROUND(D20*1,2) -> 11.84
A21: Minutes per day | D21: =SUM(D5:D20) -> 1019.84 | E21: =SUM(E5:E20) -> 698.98 | F21: =SUM(F5:F20) -> 211.42 | G21: =SUM(G5:G20) -> 109.44
A22: Hours per day | D22: =ROUND(D21/60,2) -> 17

Sheet Workload Dec Peak
A1: Daily workload, December 2027 peak sensitivity
A2: Minutes per day by task and by shift under the March 2026 standards. Occupied-room cleans are the average daily census less discharges; terminals are the discharges per day split by the isolation share.
A4: TASK | B4: UNITS PER DAY | C4: MINUTES PER UNIT | D4: MINUTES PER DAY | E4: DAY SHIFT | F4: EVENING SHIFT | G4: NIGHT SHIFT
A5: Daily clean, occupied rooms (census less discharges) | B5: =ROUND(Parameters!$B$25-Parameters!$B$26,2) -> 14.5 | C5: =Parameters!$B$4 -> 22 | D5: =ROUND(B5*C5,2) -> 319 | E5: =ROUND(D5*1,2) -> 319 | F5: =ROUND(D5*0,2) -> 0 | G5: =ROUND(D5*0,2) -> 0
A6: Terminal clean, standard rooms | B6: =ROUND(Parameters!$B$26*(1-Parameters!$B$27),3) -> 6.786 | C6: =Parameters!$B$5 -> 43 | D6: =ROUND(B6*C6,2) -> 291.8 | E6: =ROUND(D6*Parameters!$B$28,2) -> 189.67 | F6: =ROUND(D6*Parameters!$B$29,2) -> 87.54 | G6: =ROUND(D6*Parameters!$B$30,2) -> 14.59
A7: Terminal clean, isolation rooms | B7: =ROUND(Parameters!$B$26*Parameters!$B$27,3) -> 1.914 | C7: =Parameters!$B$6 -> 58 | D7: =ROUND(B7*C7,2) -> 111.01 | E7: =ROUND(D7*Parameters!$B$28,2) -> 72.16 | F7: =ROUND(D7*Parameters!$B$29,2) -> 33.3 | G7: =ROUND(D7*Parameters!$B$30,2) -> 5.55
A8: Nurses stations | B8: =Inventory!$C$44 -> 2 | C8: =Parameters!$B$7 -> 15 | D8: =ROUND(B8*C8,2) -> 30 | E8: =ROUND(D8*Parameters!$B$31,2) -> 15 | F8: =ROUND(D8*Parameters!$B$32,2) -> 9 | G8: =ROUND(D8*Parameters!$B$33,2) -> 6
A9: Medication room | B9: 1 | C9: =Parameters!$B$8 -> 10 | D9: =ROUND(B9*C9,2) -> 10 | E9: =ROUND(D9*Parameters!$B$31,2) -> 5 | F9: =ROUND(D9*Parameters!$B$32,2) -> 3 | G9: =ROUND(D9*Parameters!$B$33,2) -> 2
A10: Clean utility | B10: 1 | C10: =Parameters!$B$9 -> 12 | D10: =ROUND(B10*C10,2) -> 12 | E10: =ROUND(D10*Parameters!$B$31,2) -> 6 | F10: =ROUND(D10*Parameters!$B$32,2) -> 3.6 | G10: =ROUND(D10*Parameters!$B$33,2) -> 2.4
A11: Soiled utility, two services | B11: 2 | C11: =Parameters!$B$10 -> 12 | D11: =ROUND(B11*C11,2) -> 24 | E11: =ROUND(D11*Parameters!$B$31,2) -> 12 | F11: =ROUND(D11*Parameters!$B$32,2) -> 7.2 | G11: =ROUND(D11*Parameters!$B$33,2) -> 4.8
A12: Staff restrooms | B12: =Inventory!$C$45 -> 2 | C12: =Parameters!$B$11 -> 14 | D12: =ROUND(B12*C12,2) -> 28 | E12: =ROUND(D12*Parameters!$B$31,2) -> 14 | F12: =ROUND(D12*Parameters!$B$32,2) -> 8.4 | G12: =ROUND(D12*Parameters!$B$33,2) -> 5.6
A13: Public restrooms, two services each | B13: =Inventory!$C$46*2 -> 4 | C13: =Parameters!$B$12 -> 14 | D13: =ROUND(B13*C13,2) -> 56 | E13: =ROUND(D13*Parameters!$B$31,2) -> 28 | F13: =ROUND(D13*Parameters!$B$32,2) -> 16.8 | G13: =ROUND(D13*Parameters!$B$33,2) -> 11.2
A14: Family lounge | B14: 1 | C14: =Parameters!$B$13 -> 20 | D14: =ROUND(B14*C14,2) -> 20 | E14: =ROUND(D14*Parameters!$B$31,2) -> 10 | F14: =ROUND(D14*Parameters!$B$32,2) -> 6 | G14: =ROUND(D14*Parameters!$B$33,2) -> 4
A15: Conference room | B15: 1 | C15: =Parameters!$B$14 -> 12 | D15: =ROUND(B15*C15,2) -> 12 | E15: =ROUND(D15*Parameters!$B$31,2) -> 6 | F15: =ROUND(D15*Parameters!$B$32,2) -> 3.6 | G15: =ROUND(D15*Parameters!$B$33,2) -> 2.4
A16: Staff lounge | B16: 1 | C16: =Parameters!$B$15 -> 15 | D16: =ROUND(B16*C16,2) -> 15 | E16: =ROUND(D16*Parameters!$B$31,2) -> 7.5 | F16: =ROUND(D16*Parameters!$B$32,2) -> 4.5 | G16: =ROUND(D16*Parameters!$B$33,2) -> 3
A17: Corridor dust and damp mop, per 100 square feet | B17: =Inventory!$C$43/100 -> 42 | C17: =Parameters!$B$16 -> 1.5 | D17: =ROUND(B17*C17,2) -> 63 | E17: =ROUND(D17*Parameters!$B$31,2) -> 31.5 | F17: =ROUND(D17*Parameters!$B$32,2) -> 18.9 | G17: =ROUND(D17*Parameters!$B$33,2) -> 12.6
A18: High-touch disinfection rounds | B18: 2 | C18: =Parameters!$B$17 -> 30 | D18: =ROUND(B18*C18,2) -> 60 | E18: =ROUND(D18*Parameters!$B$31,2) -> 30 | F18: =ROUND(D18*Parameters!$B$32,2) -> 18 | G18: =ROUND(D18*Parameters!$B$33,2) -> 12
A19: Corridor burnish, weekly averaged to a day | B19: =ROUND(1/Parameters!$B$20,4) -> 0.1429 | C19: =Parameters!$B$18 -> 90 | D19: =ROUND(B19*C19,2) -> 12.86 | E19: =ROUND(D19*0,2) -> 0 | F19: =ROUND(D19*0,2) -> 0 | G19: =ROUND(D19*1,2) -> 12.86
A20: Corridor scrub and recoat, monthly averaged to a day | B20: =ROUND(1/Parameters!$B$21,4) -> 0.0329 | C20: =Parameters!$B$19 -> 360 | D20: =ROUND(B20*C20,2) -> 11.84 | E20: =ROUND(D20*0,2) -> 0 | F20: =ROUND(D20*0,2) -> 0 | G20: =ROUND(D20*1,2) -> 11.84
A21: Minutes per day | D21: =SUM(D5:D20) -> 1076.51 | E21: =SUM(E5:E20) -> 745.83 | F21: =SUM(F5:F20) -> 219.84 | G21: =SUM(G5:G20) -> 110.84
A22: Hours per day | D22: =ROUND(D21/60,2) -> 17.94

Sheet Positions
A1: Daily posts, annual shifts and full-time equivalents by shift, calendar 2027 average basis
A2: Posts are the shift's minutes per day over 420 productive minutes; annual shifts are posts times 365; full-time equivalents are annual shifts over 231.4 worked shifts per FTE (standards section 4).
A4: SHIFT | B4: MINUTES PER DAY | C4: DAILY POSTS | D4: ANNUAL SHIFTS | E4: FTE REQUIRED | F4: TRANSFERRED FTE | G4: APPROVED NEW FTE | H4: FTE STILL TO HIRE
A5: Day | B5: =Workload!E21 -> 698.98 | C5: =ROUND(B5/Parameters!$B$34,2) -> 1.66 | D5: =ROUND(C5*Parameters!$B$35,1) -> 605.9 | E5: =ROUND(D5/Parameters!$B$36,2) -> 2.62 | F5: =Parameters!$B$45 -> 1 | G5: =Parameters!$B$44 -> 1 | H5: =ROUND(E5-F5-G5,2) -> 0.62
A6: Evening | B6: =Workload!F21 -> 211.42 | C6: =ROUND(B6/Parameters!$B$34,2) -> 0.5 | D6: =ROUND(C6*Parameters!$B$35,1) -> 182.5 | E6: =ROUND(D6/Parameters!$B$36,2) -> 0.79 | F6: =Parameters!$B$46 -> 1 | G6: 0 | H6: =ROUND(E6-F6-G6,2) -> -0.21
A7: Night | B7: =Workload!G21 -> 109.44 | C7: =ROUND(B7/Parameters!$B$34,2) -> 0.26 | D7: =ROUND(C7*Parameters!$B$35,1) -> 94.9 | E7: =ROUND(D7/Parameters!$B$36,2) -> 0.41 | F7: =0 -> 0 | G7: 0 | H7: =ROUND(E7-F7-G7,2) -> 0.41
A8: Unit total | B8: =SUM(B5:B7) -> 1019.84 | C8: =SUM(C5:C7) -> 2.42 | D8: =SUM(D5:D7) -> 883.3 | E8: =SUM(E5:E7) -> 3.82 | F8: =SUM(F5:F7) -> 2 | G8: =SUM(G5:G7) -> 1 | H8: =SUM(H5:H7) -> 0.82
A10: December peak sensitivity
A11: SHIFT | B11: MINUTES PER DAY | C11: DAILY POSTS | D11: ANNUAL SHIFTS IF SUSTAINED | E11: FTE IF SUSTAINED
A12: Day | B12: ='Workload Dec Peak'!E21 -> 745.83 | C12: =ROUND(B12/Parameters!$B$34,2) -> 1.78 | D12: =ROUND(C12*Parameters!$B$35,1) -> 649.7 | E12: =ROUND(D12/Parameters!$B$36,2) -> 2.81
A13: Evening | B13: ='Workload Dec Peak'!F21 -> 219.84 | C13: =ROUND(B13/Parameters!$B$34,2) -> 0.52 | D13: =ROUND(C13*Parameters!$B$35,1) -> 189.8 | E13: =ROUND(D13/Parameters!$B$36,2) -> 0.82
A14: Night | B14: ='Workload Dec Peak'!G21 -> 110.84 | C14: =ROUND(B14/Parameters!$B$34,2) -> 0.26 | D14: =ROUND(C14*Parameters!$B$35,1) -> 94.9 | E14: =ROUND(D14/Parameters!$B$36,2) -> 0.41
A15: Unit total at the December peak | E15: =SUM(E12:E14) -> 4.04

Sheet Cost
A1: Annual labor cost of the required staffing at the current wage scale, calendar 2027 average basis
A2: Each FTE is costed at 2,080 paid hours at the Housekeeper I base rate, plus the shift differential on every paid hour, plus the weekend differential on two-sevenths of paid hours, plus the benefits load on the whole (standards section 5).
A4: SHIFT | B4: FTE REQUIRED | C4: PAID HOURS | D4: BASE WAGES | E4: SHIFT DIFFERENTIAL | F4: WEEKEND DIFFERENTIAL | G4: WAGES AND DIFFERENTIALS | H4: BENEFITS LOAD | I4: ANNUAL COST
A5: Day | B5: =Positions!E5 -> 2.62 | C5: =ROUND(B5*Parameters!$B$37,1) -> 5449.6 | D5: =ROUND(C5*Parameters!$B$38,2) -> 97275.36 | E5: =ROUND(C5*0,2) -> 0 | F5: =ROUND(C5*Parameters!$B$42/Parameters!$B$20*Parameters!$B$41,2) -> 1557.03 | G5: =SUM(D5:F5) -> 98832.39 | H5: =ROUND(G5*Parameters!$B$43,2) -> 27178.91 | I5: =SUM(G5:H5) -> 126011.3
A6: Evening | B6: =Positions!E6 -> 0.79 | C6: =ROUND(B6*Parameters!$B$37,1) -> 1643.2 | D6: =ROUND(C6*Parameters!$B$38,2) -> 29331.12 | E6: =ROUND(C6*Parameters!$B$39,2) -> 1807.52 | F6: =ROUND(C6*Parameters!$B$42/Parameters!$B$20*Parameters!$B$41,2) -> 469.49 | G6: =SUM(D6:F6) -> 31608.13 | H6: =ROUND(G6*Parameters!$B$43,2) -> 8692.24 | I6: =SUM(G6:H6) -> 40300.37
A7: Night | B7: =Positions!E7 -> 0.41 | C7: =ROUND(B7*Parameters!$B$37,1) -> 852.8 | D7: =ROUND(C7*Parameters!$B$38,2) -> 15222.48 | E7: =ROUND(C7*Parameters!$B$40,2) -> 1492.4 | F7: =ROUND(C7*Parameters!$B$42/Parameters!$B$20*Parameters!$B$41,2) -> 243.66 | G7: =SUM(D7:F7) -> 16958.54 | H7: =ROUND(G7*Parameters!$B$43,2) -> 4663.6 | I7: =SUM(G7:H7) -> 21622.14
A8: Unit total | B8: =SUM(B5:B7) -> 3.82 | C8: =SUM(C5:C7) -> 7945.6 | D8: =SUM(D5:D7) -> 141828.96 | E8: =SUM(E5:E7) -> 3299.92 | F8: =SUM(F5:F7) -> 2270.18 | G8: =SUM(G5:G7) -> 147399.06 | H8: =SUM(H5:H7) -> 40534.75 | I8: =SUM(I5:I7) -> 187933.81
A10: Annual labor budget approved for the unit | I10: =Parameters!$B$47 -> 205000
A11: Cost against the approved budget, negative when under | I11: =ROUND(I8-I10,2) -> -17066.19
A12: Cost of the director's working plan: two transfers and one new day position, three FTE costed the same way
A13: Day, two FTE | C13: =2*Parameters!$B$37 -> 4160 | D13: =ROUND(C13*Parameters!$B$38,2) -> 74256 | E13: 0 | F13: =ROUND(C13*Parameters!$B$42/Parameters!$B$20*Parameters!$B$41,2) -> 1188.57 | G13: =SUM(D13:F13) -> 75444.57 | H13: =ROUND(G13*Parameters!$B$43,2) -> 20747.26 | I13: =SUM(G13:H13) -> 96191.83
A14: Evening, one FTE | C14: =Parameters!$B$37 -> 2080 | D14: =ROUND(C14*Parameters!$B$38,2) -> 37128 | E14: =ROUND(C14*Parameters!$B$39,2) -> 2288 | F14: =ROUND(C14*Parameters!$B$42/Parameters!$B$20*Parameters!$B$41,2) -> 594.29 | G14: =SUM(D14:F14) -> 40010.29 | H14: =ROUND(G14*Parameters!$B$43,2) -> 11002.83 | I14: =SUM(G14:H14) -> 51013.12
A15: Working plan, three FTE | I15: =SUM(I13:I14) -> 147204.95

Sheet Note to Marisol
A1: To: Marisol Ybarra, Director of Environmental Services
A2: Date: October 16, 2026
A3: Re: 4 West staffing plan against the standards and the budget
A5: Your working plan does not hold under the March standards, and the reason is positions rather than dollars. The unit needs 3.82 full-time equivalents on the calendar 2027 average: 2.62 on days, 0.79 on evenings and 0.41 on nights. The two transfers and the one approved position make 3.00, so the plan is 0.82 FTE short, and the shortfall sits on days and nights.
A6: The cost of the required 3.82 FTE at the current scale is $187,933.81 a year with differentials and benefits, which is $17,066.19 under the $205,000.00 budget. Your working plan of three FTE costs $147,204.95 the same way. The budget already covers the staffing the standards call for. What is missing is Finance's approval of 0.82 FTE beyond the one position, and the money to pay for it is inside the figure you have.
A7: On days the unit needs 2.62 FTE against Guzman and the one new position, so a further 0.62 FTE, which is a 0.6 part-time Housekeeper I on seven-day rotation with the float pool covering the rest. On evenings Haugen's 1.00 FTE covers the 0.79 required with 0.21 to spare, which the float pool can use elsewhere. On nights the 0.41 FTE for the terminal cleans, the night share of the common areas and the corridor floor care is covered by no transfer and no approved position, since the building night crew is not in this unit's budget, so a 0.4 part-time night position or a costed share of Jankowski's time is needed.
A8: The workload is 1,019.84 minutes a day, 17.00 hours, built as the standards direct. Occupied-room cleans are counted at 13.2 rooms a day at 22 minutes, the census less discharges, because the 8.2 discharges a day take the terminal clean in place of the daily clean. The terminals are 6.724 standard cleans at 43 minutes and 1.476 isolation cleans at 58 minutes, split by the isolation share of discharges. The common areas come from the inventory, and the weekly burnish and the monthly scrub are averaged to a day. Under the shift allocation in the standards the day shift carries 698.98 minutes, the evening 211.42 and the night 109.44.
A9: Posts are the shift minutes over 420 productive minutes, 1.66 on days, 0.50 on evenings and 0.26 on nights, carried to two decimals as the standards direct rather than rounded to whole people, with partial posts covered from the float pool. Each post is 365 shifts a year, and each FTE supplies 231.4 worked shifts after the 11 percent of non-productive time, which is where the 2.62, 0.79 and 0.41 come from.
A10: The December peak would take 4.04 FTE if it ran all year, 0.22 above the plan basis, almost all of it on days. The plan is built on the calendar 2027 average as you asked, and December is covered from the float pool and overtime rather than by a position.
A11: Costing follows the standards: every FTE at the $17.85 Housekeeper I rate on 2,080 paid hours, the $1.10 evening and $1.75 night differentials on every paid hour of those shifts, the $1.00 weekend differential on two-sevenths of paid hours under seven-day rotation, and the benefits load on all of it, transfers included.
A12: Two things this plan does not settle. Quiroga's leave and the float pool's own load decide whether the partial posts can be covered from the pool in January, and the standards carry no allowance for the first weeks of a new unit, when the census may run below the full run rate the projection assumes from opening.
